Workbook

Sheet Instrucciones
B1: VALIDADOR DE RETENCIONES DEL IMPUESTO A LA RENTA DE 5TA CATEGORÍA – PERÚ
B2: Cálculo mensual (art. 40 del Reglamento de la LIR) y anual por tramos (art. 53 de la LIR), para varios trabajadores (capacidad: 100 trabajadores y 1500 filas de ingresos).
B5: ¿QUÉ HACE ESTA PLANTILLA?
B6: • | C6: Calcula, para cada trabajador y cada mes, la retención de 5ta categoría según el art. 40 del Reglamento de la LIR: proyección de la remuneración ordinaria, gratificaciones por percibir, ingresos de meses anteriores, deducción de 7 UIT, escala progresiva por tramos y divisores.
B7: • | C7: Aplica el procedimiento para ingresos extraordinarios o pagos particulares (utilidades, bonos, reintegros, liquidaciones) en el mes en que se pagan.
B8: • | C8: Acumula ingresos y retenciones de otros empleadores (empleo simultáneo o empleador anterior en el mismo ejercicio).
B9: • | C9: Compara la retención calculada con la retención efectuada en planilla y marca las diferencias.
B10: • | C10: Resume el impuesto anual por tramos y estima el saldo de la declaración jurada anual con la deducción adicional de hasta 3 UIT.
B12: PASOS
B13: 1 | C13: Parámetros: indique el ejercicio y verifique la UIT (2026: S/ 5,500 – D.S. N° 301-2025-EF). Para otro año, agregue su UIT en la tabla 'UIT por ejercicio'.
B14: 2 | C14: Trabajadores: un trabajador por fila con código único, fechas de ingreso y cese, seguro de salud (define el % de la bonificación extraordinaria) y opciones de proyección.
B15: 3 | C15: Ingresos: una fila por concepto con código del trabajador, concepto (catálogo), origen, frecuencia, monto por pago y meses. Las columnas Ene–Dic se llenan solas según la frecuencia:
C16: – Mensual: todos los meses entre 'Mes inicio' y 'Mes fin' (vacío = diciembre).
C17: – Bimestral / Trimestral / Cuatrimestral / Semestral: cada 2 / 3 / 4 / 6 meses contados desde 'Mes inicio', hasta 'Mes fin'.
C18: – Julio y Diciembre: gratificaciones ordinarias y su bonificación extraordinaria.
C19: – Pago único: solo en el 'Mes inicio' (utilidades, bonos, reintegros, liquidación, etc.).
C20: – Ingresos variables (horas extras, comisiones): una fila 'Pago único' por mes. Aumento de sueldo: cierre la fila con 'Mes fin' y agregue otra con el nuevo monto.
C21: – Registre el mes en que el ingreso se paga o se pone a disposición (art. 57 LIR: lo percibido).
C22: – Otros empleadores: Origen = 'Otro empleador'. Sus retenciones (certificado de rentas y retenciones) con el concepto 'Retención de 5ta efectuada por otro empleador'.
B23: 4 | C23: Retenciones Planilla: digite la retención de 5ta descontada cada mes (boleta / PLAME). Deje en blanco los meses sin información.
B24: 5 | C24: Revise: 'Cálculo Mensual' (12 filas por trabajador, con filtro), 'Resumen Anual' (por trabajador y por tramos) y 'Ficha Trabajador' (elija el código en la celda amarilla).
B26: LEYENDA
B27: Dato | C27: Celda de ingreso de datos (fondo amarillo, texto azul).
B28: Fórmula | C28: Fórmula: no modificar (texto negro; columnas auxiliares en gris).
B29: Vínculo | C29: Vínculo a otra hoja (texto verde).
B30: 1,234.56 | C30: Resultado clave (fondo verde).
B31: • | C31: Resultado de la validación: 'OK' (dentro de la tolerancia), 'Retuvo de menos', 'Retuvo de más', 'No corresponde' (no hay retención calculada ni registrada), 'Sin dato planilla' o 'Revisar: sin vínculo' (hay retención en un mes sin vínculo laboral).
B33: PROCEDIMIENTO DE CÁLCULO MENSUAL (art. 40 del Reglamento de la LIR – D.S. N° 122-94-EF)
B34: a) | C34: Remuneración ordinaria del mes × meses que faltan para terminar el ejercicio (incluido el mes), más las gratificaciones ordinarias (y bonificación extraordinaria) aún no percibidas.
B35: b) | C35: Más las remuneraciones y demás ingresos afectos percibidos en los meses anteriores del ejercicio (incluye otros empleadores).
B36: c) | C36: Menos 7 UIT = renta neta anual proyectada.
B37: d) | C37: Impuesto anual proyectado con la escala progresiva acumulativa (art. 53 LIR): hasta 5 UIT 8%; más de 5 hasta 20 UIT 14%; más de 20 hasta 35 UIT 17%; más de 35 hasta 45 UIT 20%; más de 45 UIT 30%.
B38: e) | C38: Retención del mes = (impuesto anual − retenciones previas) / divisor: enero a marzo ÷ 12 (sin descontar); abril: − ret. ene–mar ÷ 9; mayo a julio: − ret. ene–abr ÷ 8; agosto: − ret. ene–jul ÷ 5; setiembre a noviembre: − ret. ene–ago ÷ 4; diciembre: regularización (impuesto anual − ret. ene–nov).
B39: f) | C39: Ingresos extraordinarios del mes (utilidades, gratificaciones o bonificaciones extraordinarias, reintegros, pagos particulares): retención adicional = impuesto con el extraordinario − impuesto sin él, sobre la misma proyección. Se suma a la retención ordinaria del mes.
B40: g) | C40: Mes de cese: impuesto sobre los ingresos percibidos hasta el cese, sin proyectar, menos todas las retenciones anteriores. Si en diciembre o en el cese lo retenido supera el impuesto, se muestra el exceso a devolver.
B42: OTROS EMPLEADORES
B43: • | C43: Empleo simultáneo: el trabajador informa al empleador que paga la mayor remuneración las rentas de los demás, para que las acumule y efectúe la retención sobre el total. Por defecto, los ingresos del otro empleador se suman conforme se perciben; si en Trabajadores marca 'Sí' en '¿Proyectar rem. ordinaria de otro empleador?', la remuneración ordinaria del otro empleador también se proyecta hasta diciembre.
B44: • | C44: Empleador anterior en el mismo ejercicio: registre sus rentas y las retenciones del certificado de rentas y retenciones; se suman a los ingresos de meses anteriores y se descuentan como retenciones ya efectuadas.
B46: SUPUESTOS Y LIMITACIONES
B47: • | C47: Retenciones de meses anteriores: según el parámetro, se descuentan las de planilla (cuando se digitaron) o las calculadas. Con 'Planilla (si existe)', un error de un mes se corrige en los meses siguientes, como ocurre en la práctica.
B48: • | C48: La deducción adicional de hasta 3 UIT (arrendamiento, honorarios médicos y profesionales, hoteles y restaurantes, aportes a EsSalud de trabajadores del hogar, etc.) no la aplica el empleador: solo se usa en el Resumen Anual para estimar el saldo de la DJ anual.
B49: • | C49: Gratificación estimada: si la gratificación de julio o diciembre aún no se registró, se estima con la remuneración computable del mes × (1 + % bonificación) × meses completos del semestre / 6, solo en los meses anteriores al de pago. Registre la gratificación real cuando se pague.
B50: • | C50: No incluye donaciones (art. 49 LIR), rentas de 4ta categoría, créditos ni convenios para evitar la doble imposición.
B51: • | C51: La retención calculada se redondea a 2 decimales; las diferencias dentro de la tolerancia (Parámetros) se consideran OK.
B52: • | C52: No elimine filas ni columnas: borre solo el contenido de las celdas amarillas. Para ampliar la capacidad, vuelva a generar el archivo con generar_validador_5ta.py (--trabajadores, --filas-ingresos).
B53: • | C53: Herramienta de apoyo: verifique los criterios con la normativa vigente y los pronunciamientos de SUNAT.
B55: BASE LEGAL
B56: • | C56: TUO de la Ley del Impuesto a la Renta (D.S. N° 179-2004-EF): art. 18 inc. c) (inafectaciones), art. 34 (rentas de 5ta categoría), art. 46 (deducción de 7 UIT y hasta 3 UIT adicionales), art. 53 (escala), art. 57 (imputación por lo percibido), art. 75 (retención del empleador).
B57: • | C57: Reglamento de la LIR (D.S. N° 122-94-EF): art. 40 (procedimiento de retención) y normas sobre trabajadores con más de un empleador y certificados de rentas y retenciones.
B58: • | C58: D.S. N° 301-2025-EF: UIT 2026 = S/ 5,500.
B59: • | C59: Ley N° 27735 (gratificaciones); Leyes N° 30334 y 30712 (bonificación extraordinaria).
B61: DATOS DE EJEMPLO
B62: • | C62: Se incluyen 4 trabajadores de ejemplo (códigos EJ-001 a EJ-004) con sus ingresos y las retenciones de planilla de enero a setiembre. Hay 2 diferencias intencionales (EJ-001 en abril: no se retuvo sobre las utilidades; EJ-004 en marzo: se retuvo de más) para mostrar la validación. Bórrelos (solo el contenido) antes de usar la plantilla.

Sheet Parámetros
A1: PARÁMETROS DEL CÁLCULO
A2: Celdas amarillas: valores editables. Tasas, divisores y UIT según normativa vigente.
B4: DATOS GENERALES | D4: Equivalente S/ | E4: Comentario
B5: Empresa (razón social) | C5: EMPRESA DEMO S.A.C. | E5: Dato informativo.
B6: RUC | C6: 20000000001 | E6: Dato informativo.
B7: Ejercicio gravable | C7: 2026 | E7: Año que se valida.
B8: UIT del ejercicio (S/) | C8: =IFERROR(VLOOKUP(C7,UIT_TABLA,2,FALSE()),0) -> 5500 | E8: Se obtiene de la tabla 'UIT por ejercicio'. Si sale 0, agregue la UIT del año.
B9: Deducción fija anual (UIT) – art. 46 LIR | C9: 7 | D9: =C9*C8 -> 38500 | E9: La aplica el empleador en cada cálculo mensual.
B10: Deducción adicional máxima por gastos (UIT) – art. 46 LIR | C10: 3 | D10: =C10*C8 -> 16500 | E10: Solo para estimar la DJ anual (no la aplica el empleador).
B11: Bonificación extraordinaria Ley 30334 – EsSalud | C11: 0.09 | E11: Equivale al aporte a EsSalud sobre la gratificación.
B12: Bonificación extraordinaria Ley 30334 – EPS | C12: 0.0675 | E12: Trabajadores afiliados a una EPS.
B13: ¿Proyectar la bonificación extraordinaria con las gratificaciones? | C13: Sí | E13: Sí: se proyecta como la gratificación. No: se trata como ingreso extraordinario.
B14: Retenciones de meses anteriores que se descuentan | C14: Planilla (si existe) | E14: 'Planilla (si existe)': usa lo retenido en planilla; si falta, lo calculado.
B15: Tolerancia para validar diferencias (S/) | C15: 1 | E15: Diferencias menores o iguales se marcan como OK.
B17: ESCALA PROGRESIVA ACUMULATIVA – art. 53 LIR
B18: Tramo | C18: Desde (UIT) | D18: Hasta (UIT) | E18: Tasa | F18: Desde (S/) | G18: Hasta (S/) | H18: Tasa incremental
B19: 1 | C19: 0 | D19: 5 | E19: 0.08 | F19: =C19*UIT -> 0 | G19: =IF(D19="",1000000000000000,D19*UIT) -> 27500 | H19: =E19 -> 0.08
B20: 2 | C20: 5 | D20: 20 | E20: 0.14 | F20: =C20*UIT -> 27500 | G20: =IF(D20="",1000000000000000,D20*UIT) -> 110000 | H20: =E20-E19 -> 0.06
B21: 3 | C21: 20 | D21: 35 | E21: 0.17 | F21: =C21*UIT -> 110000 | G21: =IF(D21="",1000000000000000,D21*UIT) -> 192500 | H21: =E21-E20 -> 0.03
B22: 4 | C22: 35 | D22: 45 | E22: 0.2 | F22: =C22*UIT -> 192500 | G22: =IF(D22="",1000000000000000,D22*UIT) -> 247500 | H22: =E22-E21 -> 0.03
B23: 5 | C23: 45 | E23: 0.3 | F23: =C23*UIT -> 247500 | G23: =IF(D23="",1000000000000000,D23*UIT) -> 1e+15 | H23: =E23-E22 -> 0.1
B24: Hasta (UIT) en blanco = en adelante. La tasa incremental se usa para calcular el impuesto acumulado con SUMPRODUCT.
B26: DIVISORES MENSUALES – art. 40 Reglamento LIR (D.S. N° 122-94-EF)
B27: Mes N° | C27: Mes | D27: Divisor | E27: Descuenta retenciones hasta el mes | F27: Regla
B28: 1 | C28: Enero | D28: 12 | E28: 0 | F28: Impuesto anual / 12
B29: 2 | C29: Febrero | D29: 12 | E29: 0 | F29: Impuesto anual / 12
B30: 3 | C30: Marzo | D30: 12 | E30: 0 | F30: Impuesto anual / 12
B31: 4 | C31: Abril | D31: 9 | E31: 3 | F31: (Impuesto anual − retenciones ene–mar) / 9
B32: 5 | C32: Mayo | D32: 8 | E32: 4 | F32: (Impuesto anual − retenciones ene–abr) / 8
B33: 6 | C33: Junio | D33: 8 | E33: 4 | F33: (Impuesto anual − retenciones ene–abr) / 8
B34: 7 | C34: Julio | D34: 8 | E34: 4 | F34: (Impuesto anual − retenciones ene–abr) / 8
B35: 8 | C35: Agosto | D35: 5 | E35: 7 | F35: (Impuesto anual − retenciones ene–jul) / 5
B36: 9 | C36: Setiembre | D36: 4 | E36: 8 | F36: (Impuesto anual − retenciones ene–ago) / 4
B37: 10 | C37: Octubre | D37: 4 | E37: 8 | F37: (Impuesto anual − retenciones ene–ago) / 4
B38: 11 | C38: Noviembre | D38: 4 | E38: 8 | F38: (Impuesto anual − retenciones ene–ago) / 4
B39: 12 | C39: Diciembre | D39: 1 | E39: 11 | F39: Regularización: impuesto anual − retenciones ene–nov
B41: UIT POR EJERCICIO
B42: Año | C42: UIT (S/) | D42: Norma
B43: 2020 | C43: 4300 | D43: D.S. N° 380-2019-EF
B44: 2021 | C44: 4400 | D44: D.S. N° 392-2020-EF
B45: 2022 | C45: 4600 | D45: D.S. N° 398-2021-EF
B46: 2023 | C46: 4950 | D46: D.S. N° 309-2022-EF
B47: 2024 | C47: 5150 | D47: D.S. N° 309-2023-EF
B48: 2025 | C48: 5350 | D48: D.S. N° 260-2024-EF
B49: 2026 | C49: 5500 | D49: D.S. N° 301-2025-EF
B54: FRECUENCIAS DE PAGO (hoja Ingresos)
B55: Frecuencia | C55: Cada (meses) | D55: Meses en que se paga
B56: Mensual | C56: 1 | D56: Todos los meses entre Mes inicio y Mes fin
B57: Bimestral | C57: 2 | D57: Cada 2 meses desde Mes inicio hasta Mes fin
B58: Trimestral | C58: 3 | D58: Cada 3 meses desde Mes inicio hasta Mes fin
B59: Cuatrimestral | C59: 4 | D59: Cada 4 meses desde Mes inicio hasta Mes fin
B60: Semestral | C60: 6 | D60: Cada 6 meses desde Mes inicio (p. ej. inicio 5 = mayo y noviembre)
B61: Julio y Diciembre | C61: 0 | D61: Julio y diciembre (gratificaciones), dentro de Mes inicio–Mes fin
B62: Pago único | C62: 12 | D62: Solo en el Mes inicio (pago particular / esporádico)
B64: TIPOS DE CONCEPTO (hoja Conceptos)
B65: Tipo | C65: Descripción | E65: Tratamiento en el cálculo
B66: ORD | C66: Remuneración ordinaria mensual | E66: Se proyecta: monto del mes × meses que faltan para terminar el ejercicio (incluido el mes).
B67: GRA | C67: Gratificación ordinaria (julio / diciembre) | E67: Se suma a la proyección mientras no haya sido percibida (incluye la del mes de pago).
B68: BON | C68: Bonificación extraordinaria Ley 30334 | E68: Igual que GRA; o como ingreso extraordinario si el parámetro de proyección es 'No'.
B69: EXT | C69: Ingreso extraordinario / pago particular | E69: No se proyecta: retención adicional en el mes de pago (art. 40 Reglamento LIR).
B70: INA | C70: Inafecto / no constituye renta de 5ta | E70: No integra la renta bruta. Solo informativo.
B71: RET | C71: Retención de 5ta efectuada por otro empleador | E71: Se descuenta como retención ya efectuada en el mes registrado.
B73: LISTAS DESPLEGABLES
B74: Sí / No | C74: Origen del ingreso | D74: Seguro de salud | E74: Retenciones previas
B75: Sí | C75: Empresa principal | D75: EsSalud | E75: Planilla (si existe)
B76: No | C76: Otro empleador | D76: EPS | E76: Calculadas
D77: Sin bonificación

Sheet Conceptos
A1: CATÁLOGO DE CONCEPTOS
A2: Puede agregar conceptos en las filas libres. El Tipo define el tratamiento en el cálculo (ver Parámetros > Tipos de concepto).
A4: N° | B4: Concepto | C4: Tipo | D4: Computable para gratificación | E4: Frecuencia sugerida | F4: Comentario / base legal
A5: 1 | B5: Remuneración básica / sueldo | C5: ORD | D5: Sí | E5: Mensual | F5: Remuneración ordinaria (art. 34 inc. a LIR).
A6: 2 | B6: Asignación familiar | C6: ORD | D6: Sí | E6: Mensual | F6: 10% de la RMV (Ley N° 25129).
A7: 3 | B7: Remuneración vacacional | C7: ORD | D7: Sí | E7: Mensual | F7: Sustituye a la remuneración del mes de descanso vacacional.
A8: 4 | B8: Bonificación mensual fija (cargo, convenio, etc.) | C8: ORD | D8: Sí | E8: Mensual | F8: Pago regular de cada mes.
A9: 5 | B9: Alimentación principal en dinero | C9: ORD | D9: Sí | E9: Mensual | F9: Pago regular de cada mes.
A10: 6 | B10: Horas extras | C10: ORD | D10: No | E10: Pago único | F10: Ordinaria del mes. Marque 'Sí' en computable si es regular para la gratificación.
A11: 7 | B11: Comisiones / destajo | C11: ORD | D11: No | E11: Pago único | F11: Remuneración variable del mes. Registre una fila por mes.
A12: 8 | B12: Gratificación ordinaria (Fiestas Patrias / Navidad) | C12: GRA | D12: No | E12: Julio y Diciembre | F12: Ley N° 27735.
A13: 9 | B13: Bonificación extraordinaria Ley 30334 (9% / 6.75%) | C13: BON | D13: No | E13: Julio y Diciembre | F13: Afecta a renta de 5ta; inafecta a aportaciones (Leyes N° 30334 y 30712).
A14: 10 | B14: Participación en las utilidades | C14: EXT | D14: No | E14: Pago único | F14: D. Leg. N° 892.
A15: 11 | B15: Bono / gratificación extraordinaria | C15: EXT | D15: No | E15: Pago único | F15: Pago no regular; procedimiento de ingresos extraordinarios.
A16: 12 | B16: Bono semestral (productividad, metas, etc.) | C16: EXT | D16: No | E16: Semestral | F16: No se proyecta; se grava en cada mes de pago.
A17: 13 | B17: Bono trimestral (ventas, metas, etc.) | C17: EXT | D17: No | E17: Trimestral | F17: No se proyecta; se grava en cada mes de pago.
A18: 14 | B18: Bono por cierre de pliego / convenio colectivo | C18: EXT | D18: No | E18: Pago único
A19: 15 | B19: Reintegro de remuneraciones | C19: EXT | D19: No | E19: Pago único | F19: Montos devengados en meses anteriores pagados en el mes.
A20: 16 | B20: Asignación por escolaridad / bono anual | C20: EXT | D20: No | E20: Pago único
A21: 17 | B21: Vacaciones truncas | C21: EXT | D21: No | E21: Pago único | F21: Liquidación de beneficios sociales.
A22: 18 | B22: Gratificación trunca | C22: EXT | D22: No | E22: Pago único | F22: Liquidación de beneficios sociales.
A23: 19 | B23: Remuneración de otro empleador (total del mes) | C23: ORD | D23: No | E23: Mensual | F23: Usar con Origen = 'Otro empleador' (declaración jurada del trabajador).
A24: 20 | B24: Retención de 5ta efectuada por otro empleador | C24: RET | D24: No | E24: Pago único | F24: Según certificado de rentas y retenciones. Usar con Origen = 'Otro empleador'.
A25: 21 | B25: CTS – Compensación por tiempo de servicios | C25: INA | D25: No | E25: Semestral | F25: Inafecta (art. 18 inc. c LIR).
A26: 22 | B26: Indemnización por despido arbitrario | C26: INA | D26: No | E26: Pago único | F26: Inafecta dentro del límite legal (art. 18 inc. c LIR).
A27: 23 | B27: Movilidad supeditada a la asistencia | C27: INA | D27: No | E27: Mensual | F27: Condición de trabajo; no constituye renta de 5ta.
A28: 24 | B28: Viáticos / gastos de representación sustentados | C28: INA | D28: No | E28: Pago único | F28: Gastos para el cumplimiento de funciones; no constituyen renta.
A29: 25
A30: 26
A31: 27
A32: 28
A33: 29
A34: 30
A35: 31
A36: 32
A37: 33
A38: 34
A39: 35
A40: 36
... A64: 60

Sheet Trabajadores
A1: TRABAJADORES
A2: Un trabajador por fila (capacidad: 100). Código único. No elimine filas: borre el contenido de las celdas amarillas.
A3: Las columnas grises se calculan solas. 'Gastos adicionales' (alquiler, honorarios, restaurantes, etc.) solo se usan para estimar la DJ anual.
A5: N° | B5: Código | C5: DNI | D5: Apellidos y nombres | E5: Cargo / área | F5: Fecha de ingreso | G5: Fecha de cese | H5: Seguro de salud | I5: ¿Proyectar gratificaciones? | J5: ¿Proyectar rem. ordinaria de otro empleador? | K5: Gastos adicionales sustentados – DJ (S/) | L5: Observaciones | M5: Mes inicio cálculo | N5: Mes fin cálculo | O5: ¿Cesa en el ejercicio? | P5: % bonif. extraord. | Q5: Primer mes completo | R5: Meses comput. 1er sem. | S5: Meses comput. 2do sem. | T5: Validación
A6: 1 | B6: EJ-001 | C6: 40123456 | D6: PÉREZ GARCÍA, ANA (EJEMPLO) | E6: Analista contable | F6: 43525 | H6: EsSalud | I6: Sí | J6: No | K6: 6000 | L6: Aumento desde julio, utilidades en abril, bono semestral y trimestral. | M6: =IF($B6="","",IF($F6="",1,IF(YEAR($F6)<ANIO,1,IF(YEAR($F6)=ANIO,MONTH($F6),13)))) -> 1 | N6: =IF($B6="","",IF($G6="",12,IF(YEAR($G6)>ANIO,12,IF(YEAR($G6)=ANIO,MONTH($G6),0)))) -> 12 | O6: =IF($B6="","",IF($G6="","No",IF(YEAR($G6)=ANIO,"Sí","No"))) -> No | P6: =IF($B6="","",IF($H6="EPS",BON_EPS,IF($H6="Sin bonificación",0,BON_ESSALUD))) -> 0.09 | Q6: =IF($B6="","",IF($F6="",1,IF(YEAR($F6)<ANIO,1,IF(YEAR($F6)>ANIO,13,IF(DAY($F6)=1,MONTH($F6),MONTH($F6)+1))))) -> 1 | R6: =IF($B6="","",MAX(0,MIN(6,7-$Q6))) -> 6 | S6: =IF($B6="","",MAX(0,MIN(6,13-MAX($Q6,7)))) -> 6 | T6: =IF($B6="","",IF(COUNTIF($B$6:$B$105,$B6)>1,"Código duplicado",IF($D6="","Falta nombre",IF(AND($F6<>"",$G6<>""),IF($G6<$F6,"Cese anterior al ingreso","OK"),"OK")))) -> OK
A7: 2 | B7: EJ-002 | C7: 45678912 | D7: QUISPE MAMANI, LUIS (EJEMPLO) | E7: Asistente de ventas | F7: 46143 | H7: EsSalud | I7: Sí | J7: No | K7: 3500 | L7: Ingresó en mayo; trae rentas y retenciones de su empleador anterior (ene–abr). | M7: =IF($B7="","",IF($F7="",1,IF(YEAR($F7)<ANIO,1,IF(YEAR($F7)=ANIO,MONTH($F7),13)))) -> 5 | N7: =IF($B7="","",IF($G7="",12,IF(YEAR($G7)>ANIO,12,IF(YEAR($G7)=ANIO,MONTH($G7),0)))) -> 12 | O7: =IF($B7="","",IF($G7="","No",IF(YEAR($G7)=ANIO,"Sí","No"))) -> No | P7: =IF($B7="","",IF($H7="EPS",BON_EPS,IF($H7="Sin bonificación",0,BON_ESSALUD))) -> 0.09 | Q7: =IF($B7="","",IF($F7="",1,IF(YEAR($F7)<ANIO,1,IF(YEAR($F7)>ANIO,13,IF(DAY($F7)=1,MONTH($F7),MONTH($F7)+1))))) -> 5 | R7: =IF($B7="","",MAX(0,MIN(6,7-$Q7))) -> 2 | S7: =IF($B7="","",MAX(0,MIN(6,13-MAX($Q7,7)))) -> 6 | T7: =IF($B7="","",IF(COUNTIF($B$6:$B$105,$B7)>1,"Código duplicado",IF($D7="","Falta nombre",IF(AND($F7<>"",$G7<>""),IF($G7<$F7,"Cese anterior al ingreso","OK"),"OK")))) -> OK
A8: 3 | B8: EJ-003 | C8: 70112233 | D8: TORRES ROJAS, MARÍA (EJEMPLO) | E8: Jefa de proyectos | F8: 44788 | G8: 46295 | H8: EPS | I8: Sí | J8: Sí | K8: 0 | L8: Trabajo simultáneo en otra empresa; cese el 30/09 con liquidación. | M8: =IF($B8="","",IF($F8="",1,IF(YEAR($F8)<ANIO,1,IF(YEAR($F8)=ANIO,MONTH($F8),13)))) -> 1 | N8: =IF($B8="","",IF($G8="",12,IF(YEAR($G8)>ANIO,12,IF(YEAR($G8)=ANIO,MONTH($G8),0)))) -> 9 | O8: =IF($B8="","",IF($G8="","No",IF(YEAR($G8)=ANIO,"Sí","No"))) -> Sí | P8: =IF($B8="","",IF($H8="EPS",BON_EPS,IF($H8="Sin bonificación",0,BON_ESSALUD))) -> 0.0675 | Q8: =IF($B8="","",IF($F8="",1,IF(YEAR($F8)<ANIO,1,IF(YEAR($F8)>ANIO,13,IF(DAY($F8)=1,MONTH($F8),MONTH($F8)+1))))) -> 1 | R8: =IF($B8="","",MAX(0,MIN(6,7-$Q8))) -> 6 | S8: =IF($B8="","",MAX(0,MIN(6,13-MAX($Q8,7)))) -> 6 | T8: =IF($B8="","",IF(COUNTIF($B$6:$B$105,$B8)>1,"Código duplicado",IF($D8="","Falta nombre",IF(AND($F8<>"",$G8<>""),IF($G8<$F8,"Cese anterior al ingreso","OK"),"OK")))) -> OK
A9: 4 | B9: EJ-004 | C9: 09876543 | D9: SALAZAR VEGA, CARLOS (EJEMPLO) | E9: Gerente general | F9: 42009 | H9: EsSalud | I9: Sí | J9: No | K9: 16500 | L9: Bono anual por resultados en marzo (alcanza el tramo de 30%). | M9: =IF($B9="","",IF($F9="",1,IF(YEAR($F9)<ANIO,1,IF(YEAR($F9)=ANIO,MONTH($F9),13)))) -> 1 | N9: =IF($B9="","",IF($G9="",12,IF(YEAR($G9)>ANIO,12,IF(YEAR($G9)=ANIO,MONTH($G9),0)))) -> 12 | O9: =IF($B9="","",IF($G9="","No",IF(YEAR($G9)=ANIO,"Sí","No"))) -> No | P9: =IF($B9="","",IF($H9="EPS",BON_EPS,IF($H9="Sin bonificación",0,BON_ESSALUD))) -> 0.09 | Q9: =IF($B9="","",IF($F9="",1,IF(YEAR($F9)<ANIO,1,IF(YEAR($F9)>ANIO,13,IF(DAY($F9)=1,MONTH($F9),MONTH($F9)+1))))) -> 1 | R9: =IF($B9="","",MAX(0,MIN(6,7-$Q9))) -> 6 | S9: =IF($B9="","",MAX(0,MIN(6,13-MAX($Q9,7)))) -> 6 | T9: =IF($B9="","",IF(COUNTIF($B$6:$B$105,$B9)>1,"Código duplicado",IF($D9="","Falta nombre",IF(AND($F9<>"",$G9<>""),IF($G9<$F9,"Cese anterior al ingreso","OK"),"OK")))) -> OK
A10: 5 | M10: =IF($B10="","",IF($F10="",1,IF(YEAR($F10)<ANIO,1,IF(YEAR($F10)=ANIO,MONTH($F10),13)))) | N10: =IF($B10="","",IF($G10="",12,IF(YEAR($G10)>ANIO,12,IF(YEAR($G10)=ANIO,MONTH($G10),0)))) | O10: =IF($B10="","",IF($G10="","No",IF(YEAR($G10)=ANIO,"Sí","No"))) | P10: =IF($B10="","",IF($H10="EPS",BON_EPS,IF($H10="Sin bonificación",0,BON_ESSALUD))) | Q10: =IF($B10="","",IF($F10="",1,IF(YEAR($F10)<ANIO,1,IF(YEAR($F10)>ANIO,13,IF(DAY($F10)=1,MONTH($F10),MONTH($F10)+1))))) | R10: =IF($B10="","",MAX(0,MIN(6,7-$Q10))) | S10: =IF($B10="","",MAX(0,MIN(6,13-MAX($Q10,7)))) | T10: =IF($B10="","",IF(COUNTIF($B$6:$B$105,$B10)>1,"Código duplicado",IF($D10="","Falta nombre",IF(AND($F10<>"",$G10<>""),IF($G10<$F10,"Cese anterior al ingreso","OK"),"OK"))))
A11: 6 | M11: =IF($B11="","",IF($F11="",1,IF(YEAR($F11)<ANIO,1,IF(YEAR($F11)=ANIO,MONTH($F11),13)))) | N11: =IF($B11="","",IF($G11="",12,IF(YEAR($G11)>ANIO,12,IF(YEAR($G11)=ANIO,MONTH($G11),0)))) | O11: =IF($B11="","",IF($G11="","No",IF(YEAR($G11)=ANIO,"Sí","No"))) | P11: =IF($B11="","",IF($H11="EPS",BON_EPS,IF($H11="Sin bonificación",0,BON_ESSALUD))) | Q11: =IF($B11="","",IF($F11="",1,IF(YEAR($F11)<ANIO,1,IF(YEAR($F11)>ANIO,13,IF(DAY($F11)=1,MONTH($F11),MONTH($F11)+1))))) | R11: =IF($B11="","",MAX(0,MIN(6,7-$Q11))) | S11: =IF($B11="","",MAX(0,MIN(6,13-MAX($Q11,7)))) | T11: =IF($B11="","",IF(COUNTIF($B$6:$B$105,$B11)>1,"Código duplicado",IF($D11="","Falta nombre",IF(AND($F11<>"",$G11<>""),IF($G11<$F11,"Cese anterior al ingreso","OK"),"OK"))))
A12: 7 | M12: =IF($B12="","",IF($F12="",1,IF(YEAR($F12)<ANIO,1,IF(YEAR($F12)=ANIO,MONTH($F12),13)))) | N12: =IF($B12="","",IF($G12="",12,IF(YEAR($G12)>ANIO,12,IF(YEAR($G12)=ANIO,MONTH($G12),0)))) | O12: =IF($B12="","",IF($G12="","No",IF(YEAR($G12)=ANIO,"Sí","No"))) | P12: =IF($B12="","",IF($H12="EPS",BON_EPS,IF($H12="Sin bonificación",0,BON_ESSALUD))) | Q12: =IF($B12="","",IF($F12="",1,IF(YEAR($F12)<ANIO,1,IF(YEAR($F12)>ANIO,13,IF(DAY($F12)=1,MONTH($F12),MONTH($F12)+1))))) | R12: =IF($B12="","",MAX(0,MIN(6,7-$Q12))) | S12: =IF($B12="","",MAX(0,MIN(6,13-MAX($Q12,7)))) | T12: =IF($B12="","",IF(COUNTIF($B$6:$B$105,$B12)>1,"Código duplicado",IF($D12="","Falta nombre",IF(AND($F12<>"",$G12<>""),IF($G12<$F12,"Cese anterior al ingreso","OK"),"OK"))))
A13: 8 | M13: =IF($B13="","",IF($F13="",1,IF(YEAR($F13)<ANIO,1,IF(YEAR($F13)=ANIO,MONTH($F13),13)))) | N13: =IF($B13="","",IF($G13="",12,IF(YEAR($G13)>ANIO,12,IF(YEAR($G13)=ANIO,MONTH($G13),0)))) | O13: =IF($B13="","",IF($G13="","No",IF(YEAR($G13)=ANIO,"Sí","No"))) | P13: =IF($B13="","",IF($H13="EPS",BON_EPS,IF($H13="Sin bonificación",0,BON_ESSALUD))) | Q13: =IF($B13="","",IF($F13="",1,IF(YEAR($F13)<ANIO,1,IF(YEAR($F13)>ANIO,13,IF(DAY($F13)=1,MONTH($F13),MONTH($F13)+1))))) | R13: =IF($B13="","",MAX(0,MIN(6,7-$Q13))) | S13: =IF($B13="","",MAX(0,MIN(6,13-MAX($Q13,7)))) | T13: =IF($B13="","",IF(COUNTIF($B$6:$B$105,$B13)>1,"Código duplicado",IF($D13="","Falta nombre",IF(AND($F13<>"",$G13<>""),IF($G13<$F13,"Cese anterior al ingreso","OK"),"OK"))))
A14: 9 | M14: =IF($B14="","",IF($F14="",1,IF(YEAR($F14)<ANIO,1,IF(YEAR($F14)=ANIO,MONTH($F14),13)))) | N14: =IF($B14="","",IF($G14="",12,IF(YEAR($G14)>ANIO,12,IF(YEAR($G14)=ANIO,MONTH($G14),0)))) | O14: =IF($B14="","",IF($G14="","No",IF(YEAR($G14)=ANIO,"Sí","No"))) | P14: =IF($B14="","",IF($H14="EPS",BON_EPS,IF($H14="Sin bonificación",0,BON_ESSALUD))) | Q14: =IF($B14="","",IF($F14="",1,IF(YEAR($F14)<ANIO,1,IF(YEAR($F14)>ANIO,13,IF(DAY($F14)=1,MONTH($F14),MONTH($F14)+1))))) | R14: =IF($B14="","",MAX(0,MIN(6,7-$Q14))) | S14: =IF($B14="","",MAX(0,MIN(6,13-MAX($Q14,7)))) | T14: =IF($B14="","",IF(COUNTIF($B$6:$B$105,$B14)>1,"Código duplicado",IF($D14="","Falta nombre",IF(AND($F14<>"",$G14<>""),IF($G14<$F14,"Cese anterior al ingreso","OK"),"OK"))))
A15: 10 | M15: =IF($B15="","",IF($F15="",1,IF(YEAR($F15)<ANIO,1,IF(YEAR($F15)=ANIO,MONTH($F15),13)))) | N15: =IF($B15="","",IF($G15="",12,IF(YEAR($G15)>ANIO,12,IF(YEAR($G15)=ANIO,MONTH($G15),0)))) | O15: =IF($B15="","",IF($G15="","No",IF(YEAR($G15)=ANIO,"Sí","No"))) | P15: =IF($B15="","",IF($H15="EPS",BON_EPS,IF($H15="Sin bonificación",0,BON_ESSALUD))) | Q15: =IF($B15="","",IF($F15="",1,IF(YEAR($F15)<ANIO,1,IF(YEAR($F15)>ANIO,13,IF(DAY($F15)=1,MONTH($F15),MONTH($F15)+1))))) | R15: =IF($B15="","",MAX(0,MIN(6,7-$Q15))) | S15: =IF($B15="","",MAX(0,MIN(6,13-MAX($Q15,7)))) | T15: =IF($B15="","",IF(COUNTIF($B$6:$B$105,$B15)>1,"Código duplicado",IF($D15="","Falta nombre",IF(AND($F15<>"",$G15<>""),IF($G15<$F15,"Cese anterior al ingreso","OK"),"OK"))))
A16: 11 | M16: =IF($B16="","",IF($F16="",1,IF(YEAR($F16)<ANIO,1,IF(YEAR($F16)=ANIO,MONTH($F16),13)))) | N16: =IF($B16="","",IF($G16="",12,IF(YEAR($G16)>ANIO,12,IF(YEAR($G16)=ANIO,MONTH($G16),0)))) | O16: =IF($B16="","",IF($G16="","No",IF(YEAR($G16)=ANIO,"Sí","No"))) | P16: =IF($B16="","",IF($H16="EPS",BON_EPS,IF($H16="Sin bonificación",0,BON_ESSALUD))) | Q16: =IF($B16="","",IF($F16="",1,IF(YEAR($F16)<ANIO,1,IF(YEAR($F16)>ANIO,13,IF(DAY($F16)=1,MONTH($F16),MONTH($F16)+1))))) | R16: =IF($B16="","",MAX(0,MIN(6,7-$Q16))) | S16: =IF($B16="","",MAX(0,MIN(6,13-MAX($Q16,7)))) | T16: =IF($B16="","",IF(COUNTIF($B$6:$B$105,$B16)>1,"Código duplicado",IF($D16="","Falta nombre",IF(AND($F16<>"",$G16<>""),IF($G16<$F16,"Cese anterior al ingreso","OK"),"OK"))))
A17: 12 | M17: =IF($B17="","",IF($F17="",1,IF(YEAR($F17)<ANIO,1,IF(YEAR($F17)=ANIO,MONTH($F17),13)))) | N17: =IF($B17="","",IF($G17="",12,IF(YEAR($G17)>ANIO,12,IF(YEAR($G17)=ANIO,MONTH($G17),0)))) | O17: =IF($B17="","",IF($G17="","No",IF(YEAR($G17)=ANIO,"Sí","No"))) | P17: =IF($B17="","",IF($H17="EPS",BON_EPS,IF($H17="Sin bonificación",0,BON_ESSALUD))) | Q17: =IF($B17="","",IF($F17="",1,IF(YEAR($F17)<ANIO,1,IF(YEAR($F17)>ANIO,13,IF(DAY($F17)=1,MONTH($F17),MONTH($F17)+1))))) | R17: =IF($B17="","",MAX(0,MIN(6,7-$Q17))) | S17: =IF($B17="","",MAX(0,MIN(6,13-MAX($Q17,7)))) | T17: =IF($B17="","",IF(COUNTIF($B$6:$B$105,$B17)>1,"Código duplicado",IF($D17="","Falta nombre",IF(AND($F17<>"",$G17<>""),IF($G17<$F17,"Cese anterior al ingreso","OK"),"OK"))))
A18: 13 | M18: =IF($B18="","",IF($F18="",1,IF(YEAR($F18)<ANIO,1,IF(YEAR($F18)=ANIO,MONTH($F18),13)))) | N18: =IF($B18="","",IF($G18="",12,IF(YEAR($G18)>ANIO,12,IF(YEAR($G18)=ANIO,MONTH($G18),0)))) | O18: =IF($B18="","",IF($G18="","No",IF(YEAR($G18)=ANIO,"Sí","No"))) | P18: =IF($B18="","",IF($H18="EPS",BON_EPS,IF($H18="Sin bonificación",0,BON_ESSALUD))) | Q18: =IF($B18="","",IF($F18="",1,IF(YEAR($F18)<ANIO,1,IF(YEAR($F18)>ANIO,13,IF(DAY($F18)=1,MONTH($F18),MONTH($F18)+1))))) | R18: =IF($B18="","",MAX(0,MIN(6,7-$Q18))) | S18: =IF($B18="","",MAX(0,MIN(6,13-MAX($Q18,7)))) | T18: =IF($B18="","",IF(COUNTIF($B$6:$B$105,$B18)>1,"Código duplicado",IF($D18="","Falta nombre",IF(AND($F18<>"",$G18<>""),IF($G18<$F18,"Cese anterior al ingreso","OK"),"OK"))))
A19: 14 | M19: =IF($B19="","",IF($F19="",1,IF(YEAR($F19)<ANIO,1,IF(YEAR($F19)=ANIO,MONTH($F19),13)))) | N19: =IF($B19="","",IF($G19="",12,IF(YEAR($G19)>ANIO,12,IF(YEAR($G19)=ANIO,MONTH($G19),0)))) | O19: =IF($B19="","",IF($G19="","No",IF(YEAR($G19)=ANIO,"Sí","No"))) | P19: =IF($B19="","",IF($H19="EPS",BON_EPS,IF($H19="Sin bonificación",0,BON_ESSALUD))) | Q19: =IF($B19="","",IF($F19="",1,IF(YEAR($F19)<ANIO,1,IF(YEAR($F19)>ANIO,13,IF(DAY($F19)=1,MONTH($F19),MONTH($F19)+1))))) | R19: =IF($B19="","",MAX(0,MIN(6,7-$Q19))) | S19: =IF($B19="","",MAX(0,MIN(6,13-MAX($Q19,7)))) | T19: =IF($B19="","",IF(COUNTIF($B$6:$B$105,$B19)>1,"Código duplicado",IF($D19="","Falta nombre",IF(AND($F19<>"",$G19<>""),IF($G19<$F19,"Cese anterior al ingreso","OK"),"OK"))))
A20: 15 | M20: =IF($B20="","",IF($F20="",1,IF(YEAR($F20)<ANIO,1,IF(YEAR($F20)=ANIO,MONTH($F20),13)))) | N20: =IF($B20="","",IF($G20="",12,IF(YEAR($G20)>ANIO,12,IF(YEAR($G20)=ANIO,MONTH($G20),0)))) | O20: =IF($B20="","",IF($G20="","No",IF(YEAR($G20)=ANIO,"Sí","No"))) | P20: =IF($B20="","",IF($H20="EPS",BON_EPS,IF($H20="Sin bonificación",0,BON_ESSALUD))) | Q20: =IF($B20="","",IF($F20="",1,IF(YEAR($F20)<ANIO,1,IF(YEAR($F20)>ANIO,13,IF(DAY($F20)=1,MONTH($F20),MONTH($F20)+1))))) | R20: =IF($B20="","",MAX(0,MIN(6,7-$Q20))) | S20: =IF($B20="","",MAX(0,MIN(6,13-MAX($Q20,7)))) | T20: =IF($B20="","",IF(COUNTIF($B$6:$B$105,$B20)>1,"Código duplicado",IF($D20="","Falta nombre",IF(AND($F20<>"",$G20<>""),IF($G20<$F20,"Cese anterior al ingreso","OK"),"OK"))))
A21: 16 | M21: =IF($B21="","",IF($F21="",1,IF(YEAR($F21)<ANIO,1,IF(YEAR($F21)=ANIO,MONTH($F21),13)))) | N21: =IF($B21="","",IF($G21="",12,IF(YEAR($G21)>ANIO,12,IF(YEAR($G21)=ANIO,MONTH($G21),0)))) | O21: =IF($B21="","",IF($G21="","No",IF(YEAR($G21)=ANIO,"Sí","No"))) | P21: =IF($B21="","",IF($H21="EPS",BON_EPS,IF($H21="Sin bonificación",0,BON_ESSALUD))) | Q21: =IF($B21="","",IF($F21="",1,IF(YEAR($F21)<ANIO,1,IF(YEAR($F21)>ANIO,13,IF(DAY($F21)=1,MONTH($F21),MONTH($F21)+1))))) | R21: =IF($B21="","",MAX(0,MIN(6,7-$Q21))) | S21: =IF($B21="","",MAX(0,MIN(6,13-MAX($Q21,7)))) | T21: =IF($B21="","",IF(COUNTIF($B$6:$B$105,$B21)>1,"Código duplicado",IF($D21="","Falta nombre",IF(AND($F21<>"",$G21<>""),IF($G21<$F21,"Cese anterior al ingreso","OK"),"OK"))))
... A105: 100 | M105: =IF($B105="","",IF($F105="",1,IF(YEAR($F105)<ANIO,1,IF(YEAR($F105)=ANIO,MONTH($F105),13)))) | N105: =IF($B105="","",IF($G105="",12,IF(YEAR($G105)>ANIO,12,IF(YEAR($G105)=ANIO,MONTH($G105),0)))) | O105: =IF($B105="","",IF($G105="","No",IF(YEAR($G105)=ANIO,"Sí","No"))) | P105: =IF($B105="","",IF($H105="EPS",BON_EPS,IF($H105="Sin bonificación",0,BON_ESSALUD))) | Q105: =IF($B105="","",IF($F105="",1,IF(YEAR($F105)<ANIO,1,IF(YEAR($F105)>ANIO,13,IF(DAY($F105)=1,MONTH($F105),MONTH($F105)+1))))) | R105: =IF($B105="","",MAX(0,MIN(6,7-$Q105))) | S105: =IF($B105="","",MAX(0,MIN(6,13-MAX($Q105,7)))) | T105: =IF($B105="","",IF(COUNTIF($B$6:$B$105,$B105)>1,"Código duplicado",IF($D105="","Falta nombre",IF(AND($F105<>"",$G105<>""),IF($G105<$F105,"Cese anterior al ingreso","OK"),"OK"))))

Sheet Ingresos
A1: REGISTRO DE INGRESOS
A2: Una fila por concepto. Elija la frecuencia y la plantilla distribuye el monto en los meses de pago (Ene–Dic). Registre el mes en que se paga (criterio de lo percibido).
A3: Ingresos variables (horas extras, comisiones): una fila 'Pago único' por mes. Cambio de sueldo: cierre la fila con 'Mes fin' y cree otra con el nuevo monto. Otros empleadores: Origen = 'Otro empleador'.
A5: N° | B5: Código trabajador | C5: Trabajador | D5: Concepto | E5: Tipo | F5: Comp. grat. | G5: Origen | H5: Otro empleador (RUC – razón social) | I5: Frecuencia | J5: Monto por pago (S/) | K5: Mes inicio / pago (1-12) | L5: Mes fin (1-12) | M5: Clase | N5: Cada (meses) | O5: Ene | P5: Feb | Q5: Mar | R5: Abr | S5: May | T5: Jun | U5: Jul | V5: Ago | W5: Set | X5: Oct | Y5: Nov | Z5: Dic | AA5: Total año | AB5: Validación
A6: 1 | B6: EJ-001 | C6: =IF($B6="","",IFERROR(INDEX(Trabajadores!$D$6:$D$105,MATCH($B6,LST_COD,0)),"¿Código?")) -> PÉREZ GARCÍA, ANA (EJEMPLO) | D6: Remuneración básica / sueldo | E6: =IF($D6="","",IFERROR(VLOOKUP($D6,CONC_TABLA,2,FALSE()),"")) -> ORD | F6: =IF($D6="","",IFERROR(VLOOKUP($D6,CONC_TABLA,3,FALSE()),"")) -> Sí | G6: Empresa principal | I6: Mensual | J6: 8500 | K6: 1 | L6: 6 | M6: =IF(OR($B6="",$E6=""),"",IF($E6="INA","INA",IF($G6="Otro empleador",IF($E6="RET","RETO",IF($E6="ORD","OTO","OTX")),IF($E6="RET","ERR",$E6)))) -> ORD | N6: =IF($I6="","",IFERROR(VLOOKUP($I6,FREC_TABLA,2,FALSE()),"")) -> 1 | O6: =IF(OR($M6="",$M6="ERR",$J6="",$K6="",$N6=""),0,IF($N6=0,IF(AND(OR(1=7,1=12),1>=$K6,1<=IF($L6="",12,$L6)),$J6,0),IF(AND(1>=$K6,1<=IF($L6="",12,$L6),MOD(1-$K6,$N6)=0),$J6,0))) -> 8500 | P6: =IF(OR($M6="",$M6="ERR",$J6="",$K6="",$N6=""),0,IF($N6=0,IF(AND(OR(2=7,2=12),2>=$K6,2<=IF($L6="",12,$L6)),$J6,0),IF(AND(2>=$K6,2<=IF($L6="",12,$L6),MOD(2-$K6,$N6)=0),$J6,0))) -> 8500 | Q6: =IF(OR($M6="",$M6="ERR",$J6="",$K6="",$N6=""),0,IF($N6=0,IF(AND(OR(3=7,3=12),3>=$K6,3<=IF($L6="",12,$L6)),$J6,0),IF(AND(3>=$K6,3<=IF($L6="",12,$L6),MOD(3-$K6,$N6)=0),$J6,0))) -> 8500 | R6: =IF(OR($M6="",$M6="ERR",$J6="",$K6="",$N6=""),0,IF($N6=0,IF(AND(OR(4=7,4=12),4>=$K6,4<=IF($L6="",12,$L6)),$J6,0),IF(AND(4>=$K6,4<=IF($L6="",12,$L6),MOD(4-$K6,$N6)=0),$J6,0))) -> 8500 | S6: =IF(OR($M6="",$M6="ERR",$J6="",$K6="",$N6=""),0,IF($N6=0,IF(AND(OR(5=7,5=12),5>=$K6,5<=IF($L6="",12,$L6)),$J6,0),IF(AND(5>=$K6,5<=IF($L6="",12,$L6),MOD(5-$K6,$N6)=0),$J6,0))) -> 8500 | T6: =IF(OR($M6="",$M6="ERR",$J6="",$K6="",$N6=""),0,IF($N6=0,IF(AND(OR(6=7,6=12),6>=$K6,6<=IF($L6="",12,$L6)),$J6,0),IF(AND(6>=$K6,6<=IF($L6="",12,$L6),MOD(6-$K6,$N6)=0),$J6,0))) -> 8500 | U6: =IF(OR($M6="",$M6="ERR",$J6="",$K6="",$N6=""),0,IF($N6=0,IF(AND(OR(7=7,7=12),7>=$K6,7<=IF($L6="",12,$L6)),$J6,0),IF(AND(7>=$K6,7<=IF($L6="",12,$L6),MOD(7-$K6,$N6)=0),$J6,0))) -> 0 | V6: =IF(OR($M6="",$M6="ERR",$J6="",$K6="",$N6=""),0,IF($N6=0,IF(AND(OR(8=7,8=12),8>=$K6,8<=IF($L6="",12,$L6)),$J6,0),IF(AND(8>=$K6,8<=IF($L6="",12,$L6),MOD(8-$K6,$N6)=0),$J6,0))) -> 0 | W6: =IF(OR($M6="",$M6="ERR",$J6="",$K6="",$N6=""),0,IF($N6=0,IF(AND(OR(9=7,9=12),9>=$K6,9<=IF($L6="",12,$L6)),$J6,0),IF(AND(9>=$K6,9<=IF($L6="",12,$L6),MOD(9-$K6,$N6)=0),$J6,0))) -> 0 | X6: =IF(OR($M6="",$M6="ERR",$J6="",$K6="",$N6=""),0,IF($N6=0,IF(AND(OR(10=7,10=12),10>=$K6,10<=IF($L6="",12,$L6)),$J6,0),IF(AND(10>=$K6,10<=IF($L6="",12,$L6),MOD(10-$K6,$N6)=0),$J6,0))) -> 0 | Y6: =IF(OR($M6="",$M6="ERR",$J6="",$K6="",$N6=""),0,IF($N6=0,IF(AND(OR(11=7,11=12),11>=$K6,11<=IF($L6="",12,$L6)),$J6,0),IF(AND(11>=$K6,11<=IF($L6="",12,$L6),MOD(11-$K6,$N6)=0),$J6,0))) -> 0 | Z6: =IF(OR($M6="",$M6="ERR",$J6="",$K6="",$N6=""),0,IF($N6=0,IF(AND(OR(12=7,12=12),12>=$K6,12<=IF($L6="",12,$L6)),$J6,0),IF(AND(12>=$K6,12<=IF($L6="",12,$L6),MOD(12-$K6,$N6)=0),$J6,0))) -> 0 | AA6: =SUM(O6:Z6) -> 51000 | AB6: =IF(AND($B6="",$D6="",$J6=""),"",IF($B6="","Falta código",IF(ISNA(MATCH($B6,LST_COD,0)),"Código no registrado en Trabajadores",IF($E6="","Concepto no está en el catálogo",IF($M6="ERR","Retención de otro empleador: Origen = Otro empleador",IF(OR($J6="",$K6=""),"Falta monto o mes",IF(OR($K6<1,$K6>12),"Mes inicio inválido",IF(AND($L6<>"",OR($L6<$K6,$L6>12)),"Mes fin inválido",IF($N6="","Falta frecuencia",IF(AND($G6<>"Otro empleador",SUMPRODUCT(($O6:$Z6<>0)*(((COLUMN($O6:$Z6)-14)<INDEX(Trabajadores!$M$6:$M$105,MATCH($B6,LST_COD,0)))+((COLUMN($O6:$Z6)-14)>INDEX(Trabajadores!$N$6:$N$105,MATCH($B6,LST_COD,0)))))>0),"Aviso: hay meses fuera del periodo laboral","OK")))))))))) -> OK
A7: 2 | B7: EJ-001 | C7: =IF($B7="","",IFERROR(INDEX(Trabajadores!$D$6:$D$105,MATCH($B7,LST_COD,0)),"¿Código?")) -> PÉREZ GARCÍA, ANA (EJEMPLO) | D7: Remuneración básica / sueldo | E7: =IF($D7="","",IFERROR(VLOOKUP($D7,CONC_TABLA,2,FALSE()),"")) -> ORD | F7: =IF($D7="","",IFERROR(VLOOKUP($D7,CONC_TABLA,3,FALSE()),"")) -> Sí | G7: Empresa principal | I7: Mensual | J7: 9000 | K7: 7 | L7: 12 | M7: =IF(OR($B7="",$E7=""),"",IF($E7="INA","INA",IF($G7="Otro empleador",IF($E7="RET","RETO",IF($E7="ORD","OTO","OTX")),IF($E7="RET","ERR",$E7)))) -> ORD | N7: =IF($I7="","",IFERROR(VLOOKUP($I7,FREC_TABLA,2,FALSE()),"")) -> 1 | O7: =IF(OR($M7="",$M7="ERR",$J7="",$K7="",$N7=""),0,IF($N7=0,IF(AND(OR(1=7,1=12),1>=$K7,1<=IF($L7="",12,$L7)),$J7,0),IF(AND(1>=$K7,1<=IF($L7="",12,$L7),MOD(1-$K7,$N7)=0),$J7,0))) -> 0 | P7: =IF(OR($M7="",$M7="ERR",$J7="",$K7="",$N7=""),0,IF($N7=0,IF(AND(OR(2=7,2=12),2>=$K7,2<=IF($L7="",12,$L7)),$J7,0),IF(AND(2>=$K7,2<=IF($L7="",12,$L7),MOD(2-$K7,$N7)=0),$J7,0))) -> 0 | Q7: =IF(OR($M7="",$M7="ERR",$J7="",$K7="",$N7=""),0,IF($N7=0,IF(AND(OR(3=7,3=12),3>=$K7,3<=IF($L7="",12,$L7)),$J7,0),IF(AND(3>=$K7,3<=IF($L7="",12,$L7),MOD(3-$K7,$N7)=0),$J7,0))) -> 0 | R7: =IF(OR($M7="",$M7="ERR",$J7="",$K7="",$N7=""),0,IF($N7=0,IF(AND(OR(4=7,4=12),4>=$K7,4<=IF($L7="",12,$L7)),$J7,0),IF(AND(4>=$K7,4<=IF($L7="",12,$L7),MOD(4-$K7,$N7)=0),$J7,0))) -> 0 | S7: =IF(OR($M7="",$M7="ERR",$J7="",$K7="",$N7=""),0,IF($N7=0,IF(AND(OR(5=7,5=12),5>=$K7,5<=IF($L7="",12,$L7)),$J7,0),IF(AND(5>=$K7,5<=IF($L7="",12,$L7),MOD(5-$K7,$N7)=0),$J7,0))) -> 0 | T7: =IF(OR($M7="",$M7="ERR",$J7="",$K7="",$N7=""),0,IF($N7=0,IF(AND(OR(6=7,6=12),6>=$K7,6<=IF($L7="",12,$L7)),$J7,0),IF(AND(6>=$K7,6<=IF($L7="",12,$L7),MOD(6-$K7,$N7)=0),$J7,0))) -> 0 | U7: =IF(OR($M7="",$M7="ERR",$J7="",$K7="",$N7=""),0,IF($N7=0,IF(AND(OR(7=7,7=12),7>=$K7,7<=IF($L7="",12,$L7)),$J7,0),IF(AND(7>=$K7,7<=IF($L7="",12,$L7),MOD(7-$K7,$N7)=0),$J7,0))) -> 9000 | V7: =IF(OR($M7="",$M7="ERR",$J7="",$K7="",$N7=""),0,IF($N7=0,IF(AND(OR(8=7,8=12),8>=$K7,8<=IF($L7="",12,$L7)),$J7,0),IF(AND(8>=$K7,8<=IF($L7="",12,$L7),MOD(8-$K7,$N7)=0),$J7,0))) -> 9000 | W7: =IF(OR($M7="",$M7="ERR",$J7="",$K7="",$N7=""),0,IF($N7=0,IF(AND(OR(9=7,9=12),9>=$K7,9<=IF($L7="",12,$L7)),$J7,0),IF(AND(9>=$K7,9<=IF($L7="",12,$L7),MOD(9-$K7,$N7)=0),$J7,0))) -> 9000 | X7: =IF(OR($M7="",$M7="ERR",$J7="",$K7="",$N7=""),0,IF($N7=0,IF(AND(OR(10=7,10=12),10>=$K7,10<=IF($L7="",12,$L7)),$J7,0),IF(AND(10>=$K7,10<=IF($L7="",12,$L7),MOD(10-$K7,$N7)=0),$J7,0))) -> 9000 | Y7: =IF(OR($M7="",$M7="ERR",$J7="",$K7="",$N7=""),0,IF($N7=0,IF(AND(OR(11=7,11=12),11>=$K7,11<=IF($L7="",12,$L7)),$J7,0),IF(AND(11>=$K7,11<=IF($L7="",12,$L7),MOD(11-$K7,$N7)=0),$J7,0))) -> 9000 | Z7: =IF(OR($M7="",$M7="ERR",$J7="",$K7="",$N7=""),0,IF($N7=0,IF(AND(OR(12=7,12=12),12>=$K7,12<=IF($L7="",12,$L7)),$J7,0),IF(AND(12>=$K7,12<=IF($L7="",12,$L7),MOD(12-$K7,$N7)=0),$J7,0))) -> 9000 | AA7: =SUM(O7:Z7) -> 54000 | AB7: =IF(AND($B7="",$D7="",$J7=""),"",IF($B7="","Falta código",IF(ISNA(MATCH($B7,LST_COD,0)),"Código no registrado en Trabajadores",IF($E7="","Concepto no está en el catálogo",IF($M7="ERR","Retención de otro empleador: Origen = Otro empleador",IF(OR($J7="",$K7=""),"Falta monto o mes",IF(OR($K7<1,$K7>12),"Mes inicio inválido",IF(AND($L7<>"",OR($L7<$K7,$L7>12)),"Mes fin inválido",IF($N7="","Falta frecuencia",IF(AND($G7<>"Otro empleador",SUMPRODUCT(($O7:$Z7<>0)*(((COLUMN($O7:$Z7)-14)<INDEX(Trabajadores!$M$6:$M$105,MATCH($B7,LST_COD,0)))+((COLUMN($O7:$Z7)-14)>INDEX(Trabajadores!$N$6:$N$105,MATCH($B7,LST_COD,0)))))>0),"Aviso: hay meses fuera del periodo laboral","OK")))))))))) -> OK
A8: 3 | B8: EJ-001 | C8: =IF($B8="","",IFERROR(INDEX(Trabajadores!$D$6:$D$105,MATCH($B8,LST_COD,0)),"¿Código?")) -> PÉREZ GARCÍA, ANA (EJEMPLO) | D8: Asignación familiar | E8: =IF($D8="","",IFERROR(VLOOKUP($D8,CONC_TABLA,2,FALSE()),"")) -> ORD | F8: =IF($D8="","",IFERROR(VLOOKUP($D8,CONC_TABLA,3,FALSE()),"")) -> Sí | G8: Empresa principal | I8: Mensual | J8: 113 | K8: 1 | L8: 12 | M8: =IF(OR($B8="",$E8=""),"",IF($E8="INA","INA",IF($G8="Otro empleador",IF($E8="RET","RETO",IF($E8="ORD","OTO","OTX")),IF($E8="RET","ERR",$E8)))) -> ORD | N8: =IF($I8="","",IFERROR(VLOOKUP($I8,FREC_TABLA,2,FALSE()),"")) -> 1 | O8: =IF(OR($M8="",$M8="ERR",$J8="",$K8="",$N8=""),0,IF($N8=0,IF(AND(OR(1=7,1=12),1>=$K8,1<=IF($L8="",12,$L8)),$J8,0),IF(AND(1>=$K8,1<=IF($L8="",12,$L8),MOD(1-$K8,$N8)=0),$J8,0))) -> 113 | P8: =IF(OR($M8="",$M8="ERR",$J8="",$K8="",$N8=""),0,IF($N8=0,IF(AND(OR(2=7,2=12),2>=$K8,2<=IF($L8="",12,$L8)),$J8,0),IF(AND(2>=$K8,2<=IF($L8="",12,$L8),MOD(2-$K8,$N8)=0),$J8,0))) -> 113 | Q8: =IF(OR($M8="",$M8="ERR",$J8="",$K8="",$N8=""),0,IF($N8=0,IF(AND(OR(3=7,3=12),3>=$K8,3<=IF($L8="",12,$L8)),$J8,0),IF(AND(3>=$K8,3<=IF($L8="",12,$L8),MOD(3-$K8,$N8)=0),$J8,0))) -> 113 | R8: =IF(OR($M8="",$M8="ERR",$J8="",$K8="",$N8=""),0,IF($N8=0,IF(AND(OR(4=7,4=12),4>=$K8,4<=IF($L8="",12,$L8)),$J8,0),IF(AND(4>=$K8,4<=IF($L8="",12,$L8),MOD(4-$K8,$N8)=0),$J8,0))) -> 113 | S8: =IF(OR($M8="",$M8="ERR",$J8="",$K8="",$N8=""),0,IF($N8=0,IF(AND(OR(5=7,5=12),5>=$K8,5<=IF($L8="",12,$L8)),$J8,0),IF(AND(5>=$K8,5<=IF($L8="",12,$L8),MOD(5-$K8,$N8)=0),$J8,0))) -> 113 | T8: =IF(OR($M8="",$M8="ERR",$J8="",$K8="",$N8=""),0,IF($N8=0,IF(AND(OR(6=7,6=12),6>=$K8,6<=IF($L8="",12,$L8)),$J8,0),IF(AND(6>=$K8,6<=IF($L8="",12,$L8),MOD(6-$K8,$N8)=0),$J8,0))) -> 113 | U8: =IF(OR($M8="",$M8="ERR",$J8="",$K8="",$N8=""),0,IF($N8=0,IF(AND(OR(7=7,7=12),7>=$K8,7<=IF($L8="",12,$L8)),$J8,0),IF(AND(7>=$K8,7<=IF($L8="",12,$L8),MOD(7-$K8,$N8)=0),$J8,0))) -> 113 | V8: =IF(OR($M8="",$M8="ERR",$J8="",$K8="",$N8=""),0,IF($N8=0,IF(AND(OR(8=7,8=12),8>=$K8,8<=IF($L8="",12,$L8)),$J8,0),IF(AND(8>=$K8,8<=IF($L8="",12,$L8),MOD(8-$K8,$N8)=0),$J8,0))) -> 113 | W8: =IF(OR($M8="",$M8="ERR",$J8="",$K8="",$N8=""),0,IF($N8=0,IF(AND(OR(9=7,9=12),9>=$K8,9<=IF($L8="",12,$L8)),$J8,0),IF(AND(9>=$K8,9<=IF($L8="",12,$L8),MOD(9-$K8,$N8)=0),$J8,0))) -> 113 | X8: =IF(OR($M8="",$M8="ERR",$J8="",$K8="",$N8=""),0,IF($N8=0,IF(AND(OR(10=7,10=12),10>=$K8,10<=IF($L8="",12,$L8)),$J8,0),IF(AND(10>=$K8,10<=IF($L8="",12,$L8),MOD(10-$K8,$N8)=0),$J8,0))) -> 113 | Y8: =IF(OR($M8="",$M8="ERR",$J8="",$K8="",$N8=""),0,IF($N8=0,IF(AND(OR(11=7,11=12),11>=$K8,11<=IF($L8="",12,$L8)),$J8,0),IF(AND(11>=$K8,11<=IF($L8="",12,$L8),MOD(11-$K8,$N8)=0),$J8,0))) -> 113 | Z8: =IF(OR($M8="",$M8="ERR",$J8="",$K8="",$N8=""),0,IF($N8=0,IF(AND(OR(12=7,12=12),12>=$K8,12<=IF($L8="",12,$L8)),$J8,0),IF(AND(12>=$K8,12<=IF($L8="",12,$L8),MOD(12-$K8,$N8)=0),$J8,0))) -> 113 | AA8: =SUM(O8:Z8) -> 1356 | AB8: =IF(AND($B8="",$D8="",$J8=""),"",IF($B8="","Falta código",IF(ISNA(MATCH($B8,LST_COD,0)),"Código no registrado en Trabajadores",IF($E8="","Concepto no está en el catálogo",IF($M8="ERR","Retención de otro empleador: Origen = Otro empleador",IF(OR($J8="",$K8=""),"Falta monto o mes",IF(OR($K8<1,$K8>12),"Mes inicio inválido",IF(AND($L8<>"",OR($L8<$K8,$L8>12)),"Mes fin inválido",IF($N8="","Falta frecuencia",IF(AND($G8<>"Otro empleador",SUMPRODUCT(($O8:$Z8<>0)*(((COLUMN($O8:$Z8)-14)<INDEX(Trabajadores!$M$6:$M$105,MATCH($B8,LST_COD,0)))+((COLUMN($O8:$Z8)-14)>INDEX(Trabajadores!$N$6:$N$105,MATCH($B8,LST_COD,0)))))>0),"Aviso: hay meses fuera del periodo laboral","OK")))))))))) -> OK
A9: 4 | B9: EJ-001 | C9: =IF($B9="","",IFERROR(INDEX(Trabajadores!$D$6:$D$105,MATCH($B9,LST_COD,0)),"¿Código?")) -> PÉREZ GARCÍA, ANA (EJEMPLO) | D9: Gratificación ordinaria (Fiestas Patrias / Navidad) | E9: =IF($D9="","",IFERROR(VLOOKUP($D9,CONC_TABLA,2,FALSE()),"")) -> GRA | F9: =IF($D9="","",IFERROR(VLOOKUP($D9,CONC_TABLA,3,FALSE()),"")) -> No | G9: Empresa principal | I9: Julio y Diciembre | J9: 9113 | K9: 1 | L9: 12 | M9: =IF(OR($B9="",$E9=""),"",IF($E9="INA","INA",IF($G9="Otro empleador",IF($E9="RET","RETO",IF($E9="ORD","OTO","OTX")),IF($E9="RET","ERR",$E9)))) -> GRA | N9: =IF($I9="","",IFERROR(VLOOKUP($I9,FREC_TABLA,2,FALSE()),"")) -> 0 | O9: =IF(OR($M9="",$M9="ERR",$J9="",$K9="",$N9=""),0,IF($N9=0,IF(AND(OR(1=7,1=12),1>=$K9,1<=IF($L9="",12,$L9)),$J9,0),IF(AND(1>=$K9,1<=IF($L9="",12,$L9),MOD(1-$K9,$N9)=0),$J9,0))) -> 0 | P9: =IF(OR($M9="",$M9="ERR",$J9="",$K9="",$N9=""),0,IF($N9=0,IF(AND(OR(2=7,2=12),2>=$K9,2<=IF($L9="",12,$L9)),$J9,0),IF(AND(2>=$K9,2<=IF($L9="",12,$L9),MOD(2-$K9,$N9)=0),$J9,0))) -> 0 | Q9: =IF(OR($M9="",$M9="ERR",$J9="",$K9="",$N9=""),0,IF($N9=0,IF(AND(OR(3=7,3=12),3>=$K9,3<=IF($L9="",12,$L9)),$J9,0),IF(AND(3>=$K9,3<=IF($L9="",12,$L9),MOD(3-$K9,$N9)=0),$J9,0))) -> 0 | R9: =IF(OR($M9="",$M9="ERR",$J9="",$K9="",$N9=""),0,IF($N9=0,IF(AND(OR(4=7,4=12),4>=$K9,4<=IF($L9="",12,$L9)),$J9,0),IF(AND(4>=$K9,4<=IF($L9="",12,$L9),MOD(4-$K9,$N9)=0),$J9,0))) -> 0 | S9: =IF(OR($M9="",$M9="ERR",$J9="",$K9="",$N9=""),0,IF($N9=0,IF(AND(OR(5=7,5=12),5>=$K9,5<=IF($L9="",12,$L9)),$J9,0),IF(AND(5>=$K9,5<=IF($L9="",12,$L9),MOD(5-$K9,$N9)=0),$J9,0))) -> 0 | T9: =IF(OR($M9="",$M9="ERR",$J9="",$K9="",$N9=""),0,IF($N9=0,IF(AND(OR(6=7,6=12),6>=$K9,6<=IF($L9="",12,$L9)),$J9,0),IF(AND(6>=$K9,6<=IF($L9="",12,$L9),MOD(6-$K9,$N9)=0),$J9,0))) -> 0 | U9: =IF(OR($M9="",$M9="ERR",$J9="",$K9="",$N9=""),0,IF($N9=0,IF(AND(OR(7=7,7=12),7>=$K9,7<=IF($L9="",12,$L9)),$J9,0),IF(AND(7>=$K9,7<=IF($L9="",12,$L9),MOD(7-$K9,$N9)=0),$J9,0))) -> 9113 | V9: =IF(OR($M9="",$M9="ERR",$J9="",$K9="",$N9=""),0,IF($N9=0,IF(AND(OR(8=7,8=12),8>=$K9,8<=IF($L9="",12,$L9)),$J9,0),IF(AND(8>=$K9,8<=IF($L9="",12,$L9),MOD(8-$K9,$N9)=0),$J9,0))) -> 0 | W9: =IF(OR($M9="",$M9="ERR",$J9="",$K9="",$N9=""),0,IF($N9=0,IF(AND(OR(9=7,9=12),9>=$K9,9<=IF($L9="",12,$L9)),$J9,0),IF(AND(9>=$K9,9<=IF($L9="",12,$L9),MOD(9-$K9,$N9)=0),$J9,0))) -> 0 | X9: =IF(OR($M9="",$M9="ERR",$J9="",$K9="",$N9=""),0,IF($N9=0,IF(AND(OR(10=7,10=12),10>=$K9,10<=IF($L9="",12,$L9)),$J9,0),IF(AND(10>=$K9,10<=IF($L9="",12,$L9),MOD(10-$K9,$N9)=0),$J9,0))) -> 0 | Y9: =IF(OR($M9="",$M9="ERR",$J9="",$K9="",$N9=""),0,IF($N9=0,IF(AND(OR(11=7,11=12),11>=$K9,11<=IF($L9="",12,$L9)),$J9,0),IF(AND(11>=$K9,11<=IF($L9="",12,$L9),MOD(11-$K9,$N9)=0),$J9,0))) -> 0 | Z9: =IF(OR($M9="",$M9="ERR",$J9="",$K9="",$N9=""),0,IF($N9=0,IF(AND(OR(12=7,12=12),12>=$K9,12<=IF($L9="",12,$L9)),$J9,0),IF(AND(12>=$K9,12<=IF($L9="",12,$L9),MOD(12-$K9,$N9)=0),$J9,0))) -> 9113 | AA9: =SUM(O9:Z9) -> 18226 | AB9: =IF(AND($B9="",$D9="",$J9=""),"",IF($B9="","Falta código",IF(ISNA(MATCH($B9,LST_COD,0)),"Código no registrado en Trabajadores",IF($E9="","Concepto no está en el catálogo",IF($M9="ERR","Retención de otro empleador: Origen = Otro empleador",IF(OR($J9="",$K9=""),"Falta monto o mes",IF(OR($K9<1,$K9>12),"Mes inicio inválido",IF(AND($L9<>"",OR($L9<$K9,$L9>12)),"Mes fin inválido",IF($N9="","Falta frecuencia",IF(AND($G9<>"Otro empleador",SUMPRODUCT(($O9:$Z9<>0)*(((COLUMN($O9:$Z9)-14)<INDEX(Trabajadores!$M$6:$M$105,MATCH($B9,LST_COD,0)))+((COLUMN($O9:$Z9)-14)>INDEX(Trabajadores!$N$6:$N$105,MATCH($B9,LST_COD,0)))))>0),"Aviso: hay meses fuera del periodo laboral","OK")))))))))) -> OK
A10: 5 | B10: EJ-001 | C10: =IF($B10="","",IFERROR(INDEX(Trabajadores!$D$6:$D$105,MATCH($B10,LST_COD,0)),"¿Código?")) -> PÉREZ GARCÍA, ANA (EJEMPLO) | D10: Bonificación extraordinaria Ley 30334 (9% / 6.75%) | E10: =IF($D10="","",IFERROR(VLOOKUP($D10,CONC_TABLA,2,FALSE()),"")) -> BON | F10: =IF($D10="","",IFERROR(VLOOKUP($D10,CONC_TABLA,3,FALSE()),"")) -> No | G10: Empresa principal | I10: Julio y Diciembre | J10: 820.17 | K10: 1 | L10: 12 | M10: =IF(OR($B10="",$E10=""),"",IF($E10="INA","INA",IF($G10="Otro empleador",IF($E10="RET","RETO",IF($E10="ORD","OTO","OTX")),IF($E10="RET","ERR",$E10)))) -> BON | N10: =IF($I10="","",IFERROR(VLOOKUP($I10,FREC_TABLA,2,FALSE()),"")) -> 0 | O10: =IF(OR($M10="",$M10="ERR",$J10="",$K10="",$N10=""),0,IF($N10=0,IF(AND(OR(1=7,1=12),1>=$K10,1<=IF($L10="",12,$L10)),$J10,0),IF(AND(1>=$K10,1<=IF($L10="",12,$L10),MOD(1-$K10,$N10)=0),$J10,0))) -> 0 | P10: =IF(OR($M10="",$M10="ERR",$J10="",$K10="",$N10=""),0,IF($N10=0,IF(AND(OR(2=7,2=12),2>=$K10,2<=IF($L10="",12,$L10)),$J10,0),IF(AND(2>=$K10,2<=IF($L10="",12,$L10),MOD(2-$K10,$N10)=0),$J10,0))) -> 0 | Q10: =IF(OR($M10="",$M10="ERR",$J10="",$K10="",$N10=""),0,IF($N10=0,IF(AND(OR(3=7,3=12),3>=$K10,3<=IF($L10="",12,$L10)),$J10,0),IF(AND(3>=$K10,3<=IF($L10="",12,$L10),MOD(3-$K10,$N10)=0),$J10,0))) -> 0 | R10: =IF(OR($M10="",$M10="ERR",$J10="",$K10="",$N10=""),0,IF($N10=0,IF(AND(OR(4=7,4=12),4>=$K10,4<=IF($L10="",12,$L10)),$J10,0),IF(AND(4>=$K10,4<=IF($L10="",12,$L10),MOD(4-$K10,$N10)=0),$J10,0))) -> 0 | S10: =IF(OR($M10="",$M10="ERR",$J10="",$K10="",$N10=""),0,IF($N10=0,IF(AND(OR(5=7,5=12),5>=$K10,5<=IF($L10="",12,$L10)),$J10,0),IF(AND(5>=$K10,5<=IF($L10="",12,$L10),MOD(5-$K10,$N10)=0),$J10,0))) -> 0 | T10: =IF(OR($M10="",$M10="ERR",$J10="",$K10="",$N10=""),0,IF($N10=0,IF(AND(OR(6=7,6=12),6>=$K10,6<=IF($L10="",12,$L10)),$J10,0),IF(AND(6>=$K10,6<=IF($L10="",12,$L10),MOD(6-$K10,$N10)=0),$J10,0))) -> 0 | U10: =IF(OR($M10="",$M10="ERR",$J10="",$K10="",$N10=""),0,IF($N10=0,IF(AND(OR(7=7,7=12),7>=$K10,7<=IF($L10="",12,$L10)),$J10,0),IF(AND(7>=$K10,7<=IF($L10="",12,$L10),MOD(7-$K10,$N10)=0),$J10,0))) -> 820.17 | V10: =IF(OR($M10="",$M10="ERR",$J10="",$K10="",$N10=""),0,IF($N10=0,IF(AND(OR(8=7,8=12),8>=$K10,8<=IF($L10="",12,$L10)),$J10,0),IF(AND(8>=$K10,8<=IF($L10="",12,$L10),MOD(8-$K10,$N10)=0),$J10,0))) -> 0 | W10: =IF(OR($M10="",$M10="ERR",$J10="",$K10="",$N10=""),0,IF($N10=0,IF(AND(OR(9=7,9=12),9>=$K10,9<=IF($L10="",12,$L10)),$J10,0),IF(AND(9>=$K10,9<=IF($L10="",12,$L10),MOD(9-$K10,$N10)=0),$J10,0))) -> 0 | X10: =IF(OR($M10="",$M10="ERR",$J10="",$K10="",$N10=""),0,IF($N10=0,IF(AND(OR(10=7,10=12),10>=$K10,10<=IF($L10="",12,$L10)),$J10,0),IF(AND(10>=$K10,10<=IF($L10="",12,$L10),MOD(10-$K10,$N10)=0),$J10,0))) -> 0 | Y10: =IF(OR($M10="",$M10="ERR",$J10="",$K10="",$N10=""),0,IF($N10=0,IF(AND(OR(11=7,11=12),11>=$K10,11<=IF($L10="",12,$L10)),$J10,0),IF(AND(11>=$K10,11<=IF($L10="",12,$L10),MOD(11-$K10,$N10)=0),$J10,0))) -> 0 | Z10: =IF(OR($M10="",$M10="ERR",$J10="",$K10="",$N10=""),0,IF($N10=0,IF(AND(OR(12=7,12=12),12>=$K10,12<=IF($L10="",12,$L10)),$J10,0),IF(AND(12>=$K10,12<=IF($L10="",12,$L10),MOD(12-$K10,$N10)=0),$J10,0))) -> 820.17 | AA10: =SUM(O10:Z10) -> 1640.34 | AB10: =IF(AND($B10="",$D10="",$J10=""),"",IF($B10="","Falta código",IF(ISNA(MATCH($B10,LST_COD,0)),"Código no registrado en Trabajadores",IF($E10="","Concepto no está en el catálogo",IF($M10="ERR","Retención de otro empleador: Origen = Otro empleador",IF(OR($J10="",$K10=""),"Falta monto o mes",IF(OR($K10<1,$K10>12),"Mes inicio inválido",IF(AND($L10<>"",OR($L10<$K10,$L10>12)),"Mes fin inválido",IF($N10="","Falta frecuencia",IF(AND($G10<>"Otro empleador",SUMPRODUCT(($O10:$Z10<>0)*(((COLUMN($O10:$Z10)-14)<INDEX(Trabajadores!$M$6:$M$105,MATCH($B10,LST_COD,0)))+((COLUMN($O10:$Z10)-14)>INDEX(Trabajadores!$N$6:$N$105,MATCH($B10,LST_COD,0)))))>0),"Aviso: hay meses fuera del periodo laboral","OK")))))))))) -> OK
A11: 6 | B11: EJ-001 | C11: =IF($B11="","",IFERROR(INDEX(Trabajadores!$D$6:$D$105,MATCH($B11,LST_COD,0)),"¿Código?")) -> PÉREZ GARCÍA, ANA (EJEMPLO) | D11: Participación en las utilidades | E11: =IF($D11="","",IFERROR(VLOOKUP($D11,CONC_TABLA,2,FALSE()),"")) -> EXT | F11: =IF($D11="","",IFERROR(VLOOKUP($D11,CONC_TABLA,3,FALSE()),"")) -> No | G11: Empresa principal | I11: Pago único | J11: 12000 | K11: 4 | M11: =IF(OR($B11="",$E11=""),"",IF($E11="INA","INA",IF($G11="Otro empleador",IF($E11="RET","RETO",IF($E11="ORD","OTO","OTX")),IF($E11="RET","ERR",$E11)))) -> EXT | N11: =IF($I11="","",IFERROR(VLOOKUP($I11,FREC_TABLA,2,FALSE()),"")) -> 12 | O11: =IF(OR($M11="",$M11="ERR",$J11="",$K11="",$N11=""),0,IF($N11=0,IF(AND(OR(1=7,1=12),1>=$K11,1<=IF($L11="",12,$L11)),$J11,0),IF(AND(1>=$K11,1<=IF($L11="",12,$L11),MOD(1-$K11,$N11)=0),$J11,0))) -> 0 | P11: =IF(OR($M11="",$M11="ERR",$J11="",$K11="",$N11=""),0,IF($N11=0,IF(AND(OR(2=7,2=12),2>=$K11,2<=IF($L11="",12,$L11)),$J11,0),IF(AND(2>=$K11,2<=IF($L11="",12,$L11),MOD(2-$K11,$N11)=0),$J11,0))) -> 0 | Q11: =IF(OR($M11="",$M11="ERR",$J11="",$K11="",$N11=""),0,IF($N11=0,IF(AND(OR(3=7,3=12),3>=$K11,3<=IF($L11="",12,$L11)),$J11,0),IF(AND(3>=$K11,3<=IF($L11="",12,$L11),MOD(3-$K11,$N11)=0),$J11,0))) -> 0 | R11: =IF(OR($M11="",$M11="ERR",$J11="",$K11="",$N11=""),0,IF($N11=0,IF(AND(OR(4=7,4=12),4>=$K11,4<=IF($L11="",12,$L11)),$J11,0),IF(AND(4>=$K11,4<=IF($L11="",12,$L11),MOD(4-$K11,$N11)=0),$J11,0))) -> 12000 | S11: =IF(OR($M11="",$M11="ERR",$J11="",$K11="",$N11=""),0,IF($N11=0,IF(AND(OR(5=7,5=12),5>=$K11,5<=IF($L11="",12,$L11)),$J11,0),IF(AND(5>=$K11,5<=IF($L11="",12,$L11),MOD(5-$K11,$N11)=0),$J11,0))) -> 0 | T11: =IF(OR($M11="",$M11="ERR",$J11="",$K11="",$N11=""),0,IF($N11=0,IF(AND(OR(6=7,6=12),6>=$K11,6<=IF($L11="",12,$L11)),$J11,0),IF(AND(6>=$K11,6<=IF($L11="",12,$L11),MOD(6-$K11,$N11)=0),$J11,0))) -> 0 | U11: =IF(OR($M11="",$M11="ERR",$J11="",$K11="",$N11=""),0,IF($N11=0,IF(AND(OR(7=7,7=12),7>=$K11,7<=IF($L11="",12,$L11)),$J11,0),IF(AND(7>=$K11,7<=IF($L11="",12,$L11),MOD(7-$K11,$N11)=0),$J11,0))) -> 0 | V11: =IF(OR($M11="",$M11="ERR",$J11="",$K11="",$N11=""),0,IF($N11=0,IF(AND(OR(8=7,8=12),8>=$K11,8<=IF($L11="",12,$L11)),$J11,0),IF(AND(8>=$K11,8<=IF($L11="",12,$L11),MOD(8-$K11,$N11)=0),$J11,0))) -> 0 | W11: =IF(OR($M11="",$M11="ERR",$J11="",$K11="",$N11=""),0,IF($N11=0,IF(AND(OR(9=7,9=12),9>=$K11,9<=IF($L11="",12,$L11)),$J11,0),IF(AND(9>=$K11,9<=IF($L11="",12,$L11),MOD(9-$K11,$N11)=0),$J11,0))) -> 0 | X11: =IF(OR($M11="",$M11="ERR",$J11="",$K11="",$N11=""),0,IF($N11=0,IF(AND(OR(10=7,10=12),10>=$K11,10<=IF($L11="",12,$L11)),$J11,0),IF(AND(10>=$K11,10<=IF($L11="",12,$L11),MOD(10-$K11,$N11)=0),$J11,0))) -> 0 | Y11: =IF(OR($M11="",$M11="ERR",$J11="",$K11="",$N11=""),0,IF($N11=0,IF(AND(OR(11=7,11=12),11>=$K11,11<=IF($L11="",12,$L11)),$J11,0),IF(AND(11>=$K11,11<=IF($L11="",12,$L11),MOD(11-$K11,$N11)=0),$J11,0))) -> 0 | Z11: =IF(OR($M11="",$M11="ERR",$J11="",$K11="",$N11=""),0,IF($N11=0,IF(AND(OR(12=7,12=12),12>=$K11,12<=IF($L11="",12,$L11)),$J11,0),IF(AND(12>=$K11,12<=IF($L11="",12,$L11),MOD(12-$K11,$N11)=0),$J11,0))) -> 0 | AA11: =SUM(O11:Z11) -> 12000 | AB11: =IF(AND($B11="",$D11="",$J11=""),"",IF($B11="","Falta código",IF(ISNA(MATCH($B11,LST_COD,0)),"Código no registrado en Trabajadores",IF($E11="","Concepto no está en el catálogo",IF($M11="ERR","Retención de otro empleador: Origen = Otro empleador",IF(OR($J11="",$K11=""),"Falta monto o mes",IF(OR($K11<1,$K11>12),"Mes inicio inválido",IF(AND($L11<>"",OR($L11<$K11,$L11>12)),"Mes fin inválido",IF($N11="","Falta frecuencia",IF(AND($G11<>"Otro empleador",SUMPRODUCT(($O11:$Z11<>0)*(((COLUMN($O11:$Z11)-14)<INDEX(Trabajadores!$M$6:$M$105,MATCH($B11,LST_COD,0)))+((COLUMN($O11:$Z11)-14)>INDEX(Trabajadores!$N$6:$N$105,MATCH($B11,LST_COD,0)))))>0),"Aviso: hay meses fuera del periodo laboral","OK")))))))))) -> OK
A12: 7 | B12: EJ-001 | C12: =IF($B12="","",IFERROR(INDEX(Trabajadores!$D$6:$D$105,MATCH($B12,LST_COD,0)),"¿Código?")) -> PÉREZ GARCÍA, ANA (EJEMPLO) | D12: Bono semestral (productividad, metas, etc.) | E12: =IF($D12="","",IFERROR(VLOOKUP($D12,CONC_TABLA,2,FALSE()),"")) -> EXT | F12: =IF($D12="","",IFERROR(VLOOKUP($D12,CONC_TABLA,3,FALSE()),"")) -> No | G12: Empresa principal | I12: Semestral | J12: 2500 | K12: 6 | L12: 12 | M12: =IF(OR($B12="",$E12=""),"",IF($E12="INA","INA",IF($G12="Otro empleador",IF($E12="RET","RETO",IF($E12="ORD","OTO","OTX")),IF($E12="RET","ERR",$E12)))) -> EXT | N12: =IF($I12="","",IFERROR(VLOOKUP($I12,FREC_TABLA,2,FALSE()),"")) -> 6 | O12: =IF(OR($M12="",$M12="ERR",$J12="",$K12="",$N12=""),0,IF($N12=0,IF(AND(OR(1=7,1=12),1>=$K12,1<=IF($L12="",12,$L12)),$J12,0),IF(AND(1>=$K12,1<=IF($L12="",12,$L12),MOD(1-$K12,$N12)=0),$J12,0))) -> 0 | P12: =IF(OR($M12="",$M12="ERR",$J12="",$K12="",$N12=""),0,IF($N12=0,IF(AND(OR(2=7,2=12),2>=$K12,2<=IF($L12="",12,$L12)),$J12,0),IF(AND(2>=$K12,2<=IF($L12="",12,$L12),MOD(2-$K12,$N12)=0),$J12,0))) -> 0 | Q12: =IF(OR($M12="",$M12="ERR",$J12="",$K12="",$N12=""),0,IF($N12=0,IF(AND(OR(3=7,3=12),3>=$K12,3<=IF($L12="",12,$L12)),$J12,0),IF(AND(3>=$K12,3<=IF($L12="",12,$L12),MOD(3-$K12,$N12)=0),$J12,0))) -> 0 | R12: =IF(OR($M12="",$M12="ERR",$J12="",$K12="",$N12=""),0,IF($N12=0,IF(AND(OR(4=7,4=12),4>=$K12,4<=IF($L12="",12,$L12)),$J12,0),IF(AND(4>=$K12,4<=IF($L12="",12,$L12),MOD(4-$K12,$N12)=0),$J12,0))) -> 0 | S12: =IF(OR($M12="",$M12="ERR",$J12="",$K12="",$N12=""),0,IF($N12=0,IF(AND(OR(5=7,5=12),5>=$K12,5<=IF($L12="",12,$L12)),$J12,0),IF(AND(5>=$K12,5<=IF($L12="",12,$L12),MOD(5-$K12,$N12)=0),$J12,0))) -> 0 | T12: =IF(OR($M12="",$M12="ERR",$J12="",$K12="",$N12=""),0,IF($N12=0,IF(AND(OR(6=7,6=12),6>=$K12,6<=IF($L12="",12,$L12)),$J12,0),IF(AND(6>=$K12,6<=IF($L12="",12,$L12),MOD(6-$K12,$N12)=0),$J12,0))) -> 2500 | U12: =IF(OR($M12="",$M12="ERR",$J12="",$K12="",$N12=""),0,IF($N12=0,IF(AND(OR(7=7,7=12),7>=$K12,7<=IF($L12="",12,$L12)),$J12,0),IF(AND(7>=$K12,7<=IF($L12="",12,$L12),MOD(7-$K12,$N12)=0),$J12,0))) -> 0 | V12: =IF(OR($M12="",$M12="ERR",$J12="",$K12="",$N12=""),0,IF($N12=0,IF(AND(OR(8=7,8=12),8>=$K12,8<=IF($L12="",12,$L12)),$J12,0),IF(AND(8>=$K12,8<=IF($L12="",12,$L12),MOD(8-$K12,$N12)=0),$J12,0))) -> 0 | W12: =IF(OR($M12="",$M12="ERR",$J12="",$K12="",$N12=""),0,IF($N12=0,IF(AND(OR(9=7,9=12),9>=$K12,9<=IF($L12="",12,$L12)),$J12,0),IF(AND(9>=$K12,9<=IF($L12="",12,$L12),MOD(9-$K12,$N12)=0),$J12,0))) -> 0 | X12: =IF(OR($M12="",$M12="ERR",$J12="",$K12="",$N12=""),0,IF($N12=0,IF(AND(OR(10=7,10=12),10>=$K12,10<=IF($L12="",12,$L12)),$J12,0),IF(AND(10>=$K12,10<=IF($L12="",12,$L12),MOD(10-$K12,$N12)=0),$J12,0))) -> 0 | Y12: =IF(OR($M12="",$M12="ERR",$J12="",$K12="",$N12=""),0,IF($N12=0,IF(AND(OR(11=7,11=12),11>=$K12,11<=IF($L12="",12,$L12)),$J12,0),IF(AND(11>=$K12,11<=IF($L12="",12,$L12),MOD(11-$K12,$N12)=0),$J12,0))) -> 0 | Z12: =IF(OR($M12="",$M12="ERR",$J12="",$K12="",$N12=""),0,IF($N12=0,IF(AND(OR(12=7,12=12),12>=$K12,12<=IF($L12="",12,$L12)),$J12,0),IF(AND(12>=$K12,12<=IF($L12="",12,$L12),MOD(12-$K12,$N12)=0),$J12,0))) -> 2500 | AA12: =SUM(O12:Z12) -> 5000 | AB12: =IF(AND($B12="",$D12="",$J12=""),"",IF($B12="","Falta código",IF(ISNA(MATCH($B12,LST_COD,0)),"Código no registrado en Trabajadores",IF($E12="","Concepto no está en el catálogo",IF($M12="ERR","Retención de otro empleador: Origen = Otro empleador",IF(OR($J12="",$K12=""),"Falta monto o mes",IF(OR($K12<1,$K12>12),"Mes inicio inválido",IF(AND($L12<>"",OR($L12<$K12,$L12>12)),"Mes fin inválido",IF($N12="","Falta frecuencia",IF(AND($G12<>"Otro empleador",SUMPRODUCT(($O12:$Z12<>0)*(((COLUMN($O12:$Z12)-14)<INDEX(Trabajadores!$M$6:$M$105,MATCH($B12,LST_COD,0)))+((COLUMN($O12:$Z12)-14)>INDEX(Trabajadores!$N$6:$N$105,MATCH($B12,LST_COD,0)))))>0),"Aviso: hay meses fuera del periodo laboral","OK")))))))))) -> OK
A13: 8 | B13: EJ-001 | C13: =IF($B13="","",IFERROR(INDEX(Trabajadores!$D$6:$D$105,MATCH($B13,LST_COD,0)),"¿Código?")) -> PÉREZ GARCÍA, ANA (EJEMPLO) | D13: Bono trimestral (ventas, metas, etc.) | E13: =IF($D13="","",IFERROR(VLOOKUP($D13,CONC_TABLA,2,FALSE()),"")) -> EXT | F13: =IF($D13="","",IFERROR(VLOOKUP($D13,CONC_TABLA,3,FALSE()),"")) -> No | G13: Empresa principal | I13: Trimestral | J13: 1200 | K13: 3 | L13: 12 | M13: =IF(OR($B13="",$E13=""),"",IF($E13="INA","INA",IF($G13="Otro empleador",IF($E13="RET","RETO",IF($E13="ORD","OTO","OTX")),IF($E13="RET","ERR",$E13)))) -> EXT | N13: =IF($I13="","",IFERROR(VLOOKUP($I13,FREC_TABLA,2,FALSE()),"")) -> 3 | O13: =IF(OR($M13="",$M13="ERR",$J13="",$K13="",$N13=""),0,IF($N13=0,IF(AND(OR(1=7,1=12),1>=$K13,1<=IF($L13="",12,$L13)),$J13,0),IF(AND(1>=$K13,1<=IF($L13="",12,$L13),MOD(1-$K13,$N13)=0),$J13,0))) -> 0 | P13: =IF(OR($M13="",$M13="ERR",$J13="",$K13="",$N13=""),0,IF($N13=0,IF(AND(OR(2=7,2=12),2>=$K13,2<=IF($L13="",12,$L13)),$J13,0),IF(AND(2>=$K13,2<=IF($L13="",12,$L13),MOD(2-$K13,$N13)=0),$J13,0))) -> 0 | Q13: =IF(OR($M13="",$M13="ERR",$J13="",$K13="",$N13=""),0,IF($N13=0,IF(AND(OR(3=7,3=12),3>=$K13,3<=IF($L13="",12,$L13)),$J13,0),IF(AND(3>=$K13,3<=IF($L13="",12,$L13),MOD(3-$K13,$N13)=0),$J13,0))) -> 1200 | R13: =IF(OR($M13="",$M13="ERR",$J13="",$K13="",$N13=""),0,IF($N13=0,IF(AND(OR(4=7,4=12),4>=$K13,4<=IF($L13="",12,$L13)),$J13,0),IF(AND(4>=$K13,4<=IF($L13="",12,$L13),MOD(4-$K13,$N13)=0),$J13,0))) -> 0 | S13: =IF(OR($M13="",$M13="ERR",$J13="",$K13="",$N13=""),0,IF($N13=0,IF(AND(OR(5=7,5=12),5>=$K13,5<=IF($L13="",12,$L13)),$J13,0),IF(AND(5>=$K13,5<=IF($L13="",12,$L13),MOD(5-$K13,$N13)=0),$J13,0))) -> 0 | T13: =IF(OR($M13="",$M13="ERR",$J13="",$K13="",$N13=""),0,IF($N13=0,IF(AND(OR(6=7,6=12),6>=$K13,6<=IF($L13="",12,$L13)),$J13,0),IF(AND(6>=$K13,6<=IF($L13="",12,$L13),MOD(6-$K13,$N13)=0),$J13,0))) -> 1200 | U13: =IF(OR($M13="",$M13="ERR",$J13="",$K13="",$N13=""),0,IF($N13=0,IF(AND(OR(7=7,7=12),7>=$K13,7<=IF($L13="",12,$L13)),$J13,0),IF(AND(7>=$K13,7<=IF($L13="",12,$L13),MOD(7-$K13,$N13)=0),$J13,0))) -> 0 | V13: =IF(OR($M13="",$M13="ERR",$J13="",$K13="",$N13=""),0,IF($N13=0,IF(AND(OR(8=7,8=12),8>=$K13,8<=IF($L13="",12,$L13)),$J13,0),IF(AND(8>=$K13,8<=IF($L13="",12,$L13),MOD(8-$K13,$N13)=0),$J13,0))) -> 0 | W13: =IF(OR($M13="",$M13="ERR",$J13="",$K13="",$N13=""),0,IF($N13=0,IF(AND(OR(9=7,9=12),9>=$K13,9<=IF($L13="",12,$L13)),$J13,0),IF(AND(9>=$K13,9<=IF($L13="",12,$L13),MOD(9-$K13,$N13)=0),$J13,0))) -> 1200 | X13: =IF(OR($M13="",$M13="ERR",$J13="",$K13="",$N13=""),0,IF($N13=0,IF(AND(OR(10=7,10=12),10>=$K13,10<=IF($L13="",12,$L13)),$J13,0),IF(AND(10>=$K13,10<=IF($L13="",12,$L13),MOD(10-$K13,$N13)=0),$J13,0))) -> 0 | Y13: =IF(OR($M13="",$M13="ERR",$J13="",$K13="",$N13=""),0,IF($N13=0,IF(AND(OR(11=7,11=12),11>=$K13,11<=IF($L13="",12,$L13)),$J13,0),IF(AND(11>=$K13,11<=IF($L13="",12,$L13),MOD(11-$K13,$N13)=0),$J13,0))) -> 0 | Z13: =IF(OR($M13="",$M13="ERR",$J13="",$K13="",$N13=""),0,IF($N13=0,IF(AND(OR(12=7,12=12),12>=$K13,12<=IF($L13="",12,$L13)),$J13,0),IF(AND(12>=$K13,12<=IF($L13="",12,$L13),MOD(12-$K13,$N13)=0),$J13,0))) -> 1200 | AA13: =SUM(O13:Z13) -> 4800 | AB13: =IF(AND($B13="",$D13="",$J13=""),"",IF($B13="","Falta código",IF(ISNA(MATCH($B13,LST_COD,0)),"Código no registrado en Trabajadores",IF($E13="","Concepto no está en el catálogo",IF($M13="ERR","Retención de otro empleador: Origen = Otro empleador",IF(OR($J13="",$K13=""),"Falta monto o mes",IF(OR($K13<1,$K13>12),"Mes inicio inválido",IF(AND($L13<>"",OR($L13<$K13,$L13>12)),"Mes fin inválido",IF($N13="","Falta frecuencia",IF(AND($G13<>"Otro empleador",SUMPRODUCT(($O13:$Z13<>0)*(((COLUMN($O13:$Z13)-14)<INDEX(Trabajadores!$M$6:$M$105,MATCH($B13,LST_COD,0)))+((COLUMN($O13:$Z13)-14)>INDEX(Trabajadores!$N$6:$N$105,MATCH($B13,LST_COD,0)))))>0),"Aviso: hay meses fuera del periodo laboral","OK")))))))))) -> OK
A14: 9 | B14: EJ-001 | C14: =IF($B14="","",IFERROR(INDEX(Trabajadores!$D$6:$D$105,MATCH($B14,LST_COD,0)),"¿Código?")) -> PÉREZ GARCÍA, ANA (EJEMPLO) | D14: Horas extras | E14: =IF($D14="","",IFERROR(VLOOKUP($D14,CONC_TABLA,2,FALSE()),"")) -> ORD | F14: =IF($D14="","",IFERROR(VLOOKUP($D14,CONC_TABLA,3,FALSE()),"")) -> No | G14: Empresa principal | I14: Pago único | J14: 640 | K14: 2 | M14: =IF(OR($B14="",$E14=""),"",IF($E14="INA","INA",IF($G14="Otro empleador",IF($E14="RET","RETO",IF($E14="ORD","OTO","OTX")),IF($E14="RET","ERR",$E14)))) -> ORD | N14: =IF($I14="","",IFERROR(VLOOKUP($I14,FREC_TABLA,2,FALSE()),"")) -> 12 | O14: =IF(OR($M14="",$M14="ERR",$J14="",$K14="",$N14=""),0,IF($N14=0,IF(AND(OR(1=7,1=12),1>=$K14,1<=IF($L14="",12,$L14)),$J14,0),IF(AND(1>=$K14,1<=IF($L14="",12,$L14),MOD(1-$K14,$N14)=0),$J14,0))) -> 0 | P14: =IF(OR($M14="",$M14="ERR",$J14="",$K14="",$N14=""),0,IF($N14=0,IF(AND(OR(2=7,2=12),2>=$K14,2<=IF($L14="",12,$L14)),$J14,0),IF(AND(2>=$K14,2<=IF($L14="",12,$L14),MOD(2-$K14,$N14)=0),$J14,0))) -> 640 | Q14: =IF(OR($M14="",$M14="ERR",$J14="",$K14="",$N14=""),0,IF($N14=0,IF(AND(OR(3=7,3=12),3>=$K14,3<=IF($L14="",12,$L14)),$J14,0),IF(AND(3>=$K14,3<=IF($L14="",12,$L14),MOD(3-$K14,$N14)=0),$J14,0))) -> 0 | R14: =IF(OR($M14="",$M14="ERR",$J14="",$K14="",$N14=""),0,IF($N14=0,IF(AND(OR(4=7,4=12),4>=$K14,4<=IF($L14="",12,$L14)),$J14,0),IF(AND(4>=$K14,4<=IF($L14="",12,$L14),MOD(4-$K14,$N14)=0),$J14,0))) -> 0 | S14: =IF(OR($M14="",$M14="ERR",$J14="",$K14="",$N14=""),0,IF($N14=0,IF(AND(OR(5=7,5=12),5>=$K14,5<=IF($L14="",12,$L14)),$J14,0),IF(AND(5>=$K14,5<=IF($L14="",12,$L14),MOD(5-$K14,$N14)=0),$J14,0))) -> 0 | T14: =IF(OR($M14="",$M14="ERR",$J14="",$K14="",$N14=""),0,IF($N14=0,IF(AND(OR(6=7,6=12),6>=$K14,6<=IF($L14="",12,$L14)),$J14,0),IF(AND(6>=$K14,6<=IF($L14="",12,$L14),MOD(6-$K14,$N14)=0),$J14,0))) -> 0 | U14: =IF(OR($M14="",$M14="ERR",$J14="",$K14="",$N14=""),0,IF($N14=0,IF(AND(OR(7=7,7=12),7>=$K14,7<=IF($L14="",12,$L14)),$J14,0),IF(AND(7>=$K14,7<=IF($L14="",12,$L14),MOD(7-$K14,$N14)=0),$J14,0))) -> 0 | V14: =IF(OR($M14="",$M14="ERR",$J14="",$K14="",$N14=""),0,IF($N14=0,IF(AND(OR(8=7,8=12),8>=$K14,8<=IF($L14="",12,$L14)),$J14,0),IF(AND(8>=$K14,8<=IF($L14="",12,$L14),MOD(8-$K14,$N14)=0),$J14,0))) -> 0 | W14: =IF(OR($M14="",$M14="ERR",$J14="",$K14="",$N14=""),0,IF($N14=0,IF(AND(OR(9=7,9=12),9>=$K14,9<=IF($L14="",12,$L14)),$J14,0),IF(AND(9>=$K14,9<=IF($L14="",12,$L14),MOD(9-$K14,$N14)=0),$J14,0))) -> 0 | X14: =IF(OR($M14="",$M14="ERR",$J14="",$K14="",$N14=""),0,IF($N14=0,IF(AND(OR(10=7,10=12),10>=$K14,10<=IF($L14="",12,$L14)),$J14,0),IF(AND(10>=$K14,10<=IF($L14="",12,$L14),MOD(10-$K14,$N14)=0),$J14,0))) -> 0 | Y14: =IF(OR($M14="",$M14="ERR",$J14="",$K14="",$N14=""),0,IF($N14=0,IF(AND(OR(11=7,11=12),11>=$K14,11<=IF($L14="",12,$L14)),$J14,0),IF(AND(11>=$K14,11<=IF($L14="",12,$L14),MOD(11-$K14,$N14)=0),$J14,0))) -> 0 | Z14: =IF(OR($M14="",$M14="ERR",$J14="",$K14="",$N14=""),0,IF($N14=0,IF(AND(OR(12=7,12=12),12>=$K14,12<=IF($L14="",12,$L14)),$J14,0),IF(AND(12>=$K14,12<=IF($L14="",12,$L14),MOD(12-$K14,$N14)=0),$J14,0))) -> 0 | AA14: =SUM(O14:Z14) -> 640 | AB14: =IF(AND($B14="",$D14="",$J14=""),"",IF($B14="","Falta código",IF(ISNA(MATCH($B14,LST_COD,0)),"Código no registrado en Trabajadores",IF($E14="","Concepto no está en el catálogo",IF($M14="ERR","Retención de otro empleador: Origen = Otro empleador",IF(OR($J14="",$K14=""),"Falta monto o mes",IF(OR($K14<1,$K14>12),"Mes inicio inválido",IF(AND($L14<>"",OR($L14<$K14,$L14>12)),"Mes fin inválido",IF($N14="","Falta frecuencia",IF(AND($G14<>"Otro empleador",SUMPRODUCT(($O14:$Z14<>0)*(((COLUMN($O14:$Z14)-14)<INDEX(Trabajadores!$M$6:$M$105,MATCH($B14,LST_COD,0)))+((COLUMN($O14:$Z14)-14)>INDEX(Trabajadores!$N$6:$N$105,MATCH($B14,LST_COD,0)))))>0),"Aviso: hay meses fuera del periodo laboral","OK")))))))))) -> OK
A15: 10 | B15: EJ-001 | C15: =IF($B15="","",IFERROR(INDEX(Trabajadores!$D$6:$D$105,MATCH($B15,LST_COD,0)),"¿Código?")) -> PÉREZ GARCÍA, ANA (EJEMPLO) | D15: Horas extras | E15: =IF($D15="","",IFERROR(VLOOKUP($D15,CONC_TABLA,2,FALSE()),"")) -> ORD | F15: =IF($D15="","",IFERROR(VLOOKUP($D15,CONC_TABLA,3,FALSE()),"")) -> No | G15: Empresa principal | I15: Pago único | J15: 415.5 | K15: 8 | M15: =IF(OR($B15="",$E15=""),"",IF($E15="INA","INA",IF($G15="Otro empleador",IF($E15="RET","RETO",IF($E15="ORD","OTO","OTX")),IF($E15="RET","ERR",$E15)))) -> ORD | N15: =IF($I15="","",IFERROR(VLOOKUP($I15,FREC_TABLA,2,FALSE()),"")) -> 12 | O15: =IF(OR($M15="",$M15="ERR",$J15="",$K15="",$N15=""),0,IF($N15=0,IF(AND(OR(1=7,1=12),1>=$K15,1<=IF($L15="",12,$L15)),$J15,0),IF(AND(1>=$K15,1<=IF($L15="",12,$L15),MOD(1-$K15,$N15)=0),$J15,0))) -> 0 | P15: =IF(OR($M15="",$M15="ERR",$J15="",$K15="",$N15=""),0,IF($N15=0,IF(AND(OR(2=7,2=12),2>=$K15,2<=IF($L15="",12,$L15)),$J15,0),IF(AND(2>=$K15,2<=IF($L15="",12,$L15),MOD(2-$K15,$N15)=0),$J15,0))) -> 0 | Q15: =IF(OR($M15="",$M15="ERR",$J15="",$K15="",$N15=""),0,IF($N15=0,IF(AND(OR(3=7,3=12),3>=$K15,3<=IF($L15="",12,$L15)),$J15,0),IF(AND(3>=$K15,3<=IF($L15="",12,$L15),MOD(3-$K15,$N15)=0),$J15,0))) -> 0 | R15: =IF(OR($M15="",$M15="ERR",$J15="",$K15="",$N15=""),0,IF($N15=0,IF(AND(OR(4=7,4=12),4>=$K15,4<=IF($L15="",12,$L15)),$J15,0),IF(AND(4>=$K15,4<=IF($L15="",12,$L15),MOD(4-$K15,$N15)=0),$J15,0))) -> 0 | S15: =IF(OR($M15="",$M15="ERR",$J15="",$K15="",$N15=""),0,IF($N15=0,IF(AND(OR(5=7,5=12),5>=$K15,5<=IF($L15="",12,$L15)),$J15,0),IF(AND(5>=$K15,5<=IF($L15="",12,$L15),MOD(5-$K15,$N15)=0),$J15,0))) -> 0 | T15: =IF(OR($M15="",$M15="ERR",$J15="",$K15="",$N15=""),0,IF($N15=0,IF(AND(OR(6=7,6=12),6>=$K15,6<=IF($L15="",12,$L15)),$J15,0),IF(AND(6>=$K15,6<=IF($L15="",12,$L15),MOD(6-$K15,$N15)=0),$J15,0))) -> 0 | U15: =IF(OR($M15="",$M15="ERR",$J15="",$K15="",$N15=""),0,IF($N15=0,IF(AND(OR(7=7,7=12),7>=$K15,7<=IF($L15="",12,$L15)),$J15,0),IF(AND(7>=$K15,7<=IF($L15="",12,$L15),MOD(7-$K15,$N15)=0),$J15,0))) -> 0 | V15: =IF(OR($M15="",$M15="ERR",$J15="",$K15="",$N15=""),0,IF($N15=0,IF(AND(OR(8=7,8=12),8>=$K15,8<=IF($L15="",12,$L15)),$J15,0),IF(AND(8>=$K15,8<=IF($L15="",12,$L15),MOD(8-$K15,$N15)=0),$J15,0))) -> 415.5 | W15: =IF(OR($M15="",$M15="ERR",$J15="",$K15="",$N15=""),0,IF($N15=0,IF(AND(OR(9=7,9=12),9>=$K15,9<=IF($L15="",12,$L15)),$J15,0),IF(AND(9>=$K15,9<=IF($L15="",12,$L15),MOD(9-$K15,$N15)=0),$J15,0))) -> 0 | X15: =IF(OR($M15="",$M15="ERR",$J15="",$K15="",$N15=""),0,IF($N15=0,IF(AND(OR(10=7,10=12),10>=$K15,10<=IF($L15="",12,$L15)),$J15,0),IF(AND(10>=$K15,10<=IF($L15="",12,$L15),MOD(10-$K15,$N15)=0),$J15,0))) -> 0 | Y15: =IF(OR($M15="",$M15="ERR",$J15="",$K15="",$N15=""),0,IF($N15=0,IF(AND(OR(11=7,11=12),11>=$K15,11<=IF($L15="",12,$L15)),$J15,0),IF(AND(11>=$K15,11<=IF($L15="",12,$L15),MOD(11-$K15,$N15)=0),$J15,0))) -> 0 | Z15: =IF(OR($M15="",$M15="ERR",$J15="",$K15="",$N15=""),0,IF($N15=0,IF(AND(OR(12=7,12=12),12>=$K15,12<=IF($L15="",12,$L15)),$J15,0),IF(AND(12>=$K15,12<=IF($L15="",12,$L15),MOD(12-$K15,$N15)=0),$J15,0))) -> 0 | AA15: =SUM(O15:Z15) -> 415.5 | AB15: =IF(AND($B15="",$D15="",$J15=""),"",IF($B15="","Falta código",IF(ISNA(MATCH($B15,LST_COD,0)),"Código no registrado en Trabajadores",IF($E15="","Concepto no está en el catálogo",IF($M15="ERR","Retención de otro empleador: Origen = Otro empleador",IF(OR($J15="",$K15=""),"Falta monto o mes",IF(OR($K15<1,$K15>12),"Mes inicio inválido",IF(AND($L15<>"",OR($L15<$K15,$L15>12)),"Mes fin inválido",IF($N15="","Falta frecuencia",IF(AND($G15<>"Otro empleador",SUMPRODUCT(($O15:$Z15<>0)*(((COLUMN($O15:$Z15)-14)<INDEX(Trabajadores!$M$6:$M$105,MATCH($B15,LST_COD,0)))+((COLUMN($O15:$Z15)-14)>INDEX(Trabajadores!$N$6:$N$105,MATCH($B15,LST_COD,0)))))>0),"Aviso: hay meses fuera del periodo laboral","OK")))))))))) -> OK
A16: 11 | B16: EJ-001 | C16: =IF($B16="","",IFERROR(INDEX(Trabajadores!$D$6:$D$105,MATCH($B16,LST_COD,0)),"¿Código?")) -> PÉREZ GARCÍA, ANA (EJEMPLO) | D16: CTS – Compensación por tiempo de servicios | E16: =IF($D16="","",IFERROR(VLOOKUP($D16,CONC_TABLA,2,FALSE()),"")) -> INA | F16: =IF($D16="","",IFERROR(VLOOKUP($D16,CONC_TABLA,3,FALSE()),"")) -> No | G16: Empresa principal | I16: Semestral | J16: 5150 | K16: 5 | L16: 11 | M16: =IF(OR($B16="",$E16=""),"",IF($E16="INA","INA",IF($G16="Otro empleador",IF($E16="RET","RETO",IF($E16="ORD","OTO","OTX")),IF($E16="RET","ERR",$E16)))) -> INA | N16: =IF($I16="","",IFERROR(VLOOKUP($I16,FREC_TABLA,2,FALSE()),"")) -> 6 | O16: =IF(OR($M16="",$M16="ERR",$J16="",$K16="",$N16=""),0,IF($N16=0,IF(AND(OR(1=7,1=12),1>=$K16,1<=IF($L16="",12,$L16)),$J16,0),IF(AND(1>=$K16,1<=IF($L16="",12,$L16),MOD(1-$K16,$N16)=0),$J16,0))) -> 0 | P16: =IF(OR($M16="",$M16="ERR",$J16="",$K16="",$N16=""),0,IF($N16=0,IF(AND(OR(2=7,2=12),2>=$K16,2<=IF($L16="",12,$L16)),$J16,0),IF(AND(2>=$K16,2<=IF($L16="",12,$L16),MOD(2-$K16,$N16)=0),$J16,0))) -> 0 | Q16: =IF(OR($M16="",$M16="ERR",$J16="",$K16="",$N16=""),0,IF($N16=0,IF(AND(OR(3=7,3=12),3>=$K16,3<=IF($L16="",12,$L16)),$J16,0),IF(AND(3>=$K16,3<=IF($L16="",12,$L16),MOD(3-$K16,$N16)=0),$J16,0))) -> 0 | R16: =IF(OR($M16="",$M16="ERR",$J16="",$K16="",$N16=""),0,IF($N16=0,IF(AND(OR(4=7,4=12),4>=$K16,4<=IF($L16="",12,$L16)),$J16,0),IF(AND(4>=$K16,4<=IF($L16="",12,$L16),MOD(4-$K16,$N16)=0),$J16,0))) -> 0 | S16: =IF(OR($M16="",$M16="ERR",$J16="",$K16="",$N16=""),0,IF($N16=0,IF(AND(OR(5=7,5=12),5>=$K16,5<=IF($L16="",12,$L16)),$J16,0),IF(AND(5>=$K16,5<=IF($L16="",12,$L16),MOD(5-$K16,$N16)=0),$J16,0))) -> 5150 | T16: =IF(OR($M16="",$M16="ERR",$J16="",$K16="",$N16=""),0,IF($N16=0,IF(AND(OR(6=7,6=12),6>=$K16,6<=IF($L16="",12,$L16)),$J16,0),IF(AND(6>=$K16,6<=IF($L16="",12,$L16),MOD(6-$K16,$N16)=0),$J16,0))) -> 0 | U16: =IF(OR($M16="",$M16="ERR",$J16="",$K16="",$N16=""),0,IF($N16=0,IF(AND(OR(7=7,7=12),7>=$K16,7<=IF($L16="",12,$L16)),$J16,0),IF(AND(7>=$K16,7<=IF($L16="",12,$L16),MOD(7-$K16,$N16)=0),$J16,0))) -> 0 | V16: =IF(OR($M16="",$M16="ERR",$J16="",$K16="",$N16=""),0,IF($N16=0,IF(AND(OR(8=7,8=12),8>=$K16,8<=IF($L16="",12,$L16)),$J16,0),IF(AND(8>=$K16,8<=IF($L16="",12,$L16),MOD(8-$K16,$N16)=0),$J16,0))) -> 0 | W16: =IF(OR($M16="",$M16="ERR",$J16="",$K16="",$N16=""),0,IF($N16=0,IF(AND(OR(9=7,9=12),9>=$K16,9<=IF($L16="",12,$L16)),$J16,0),IF(AND(9>=$K16,9<=IF($L16="",12,$L16),MOD(9-$K16,$N16)=0),$J16,0))) -> 0 | X16: =IF(OR($M16="",$M16="ERR",$J16="",$K16="",$N16=""),0,IF($N16=0,IF(AND(OR(10=7,10=12),10>=$K16,10<=IF($L16="",12,$L16)),$J16,0),IF(AND(10>=$K16,10<=IF($L16="",12,$L16),MOD(10-$K16,$N16)=0),$J16,0))) -> 0 | Y16: =IF(OR($M16="",$M16="ERR",$J16="",$K16="",$N16=""),0,IF($N16=0,IF(AND(OR(11=7,11=12),11>=$K16,11<=IF($L16="",12,$L16)),$J16,0),IF(AND(11>=$K16,11<=IF($L16="",12,$L16),MOD(11-$K16,$N16)=0),$J16,0))) -> 5150 | Z16: =IF(OR($M16="",$M16="ERR",$J16="",$K16="",$N16=""),0,IF($N16=0,IF(AND(OR(12=7,12=12),12>=$K16,12<=IF($L16="",12,$L16)),$J16,0),IF(AND(12>=$K16,12<=IF($L16="",12,$L16),MOD(12-$K16,$N16)=0),$J16,0))) -> 0 | AA16: =SUM(O16:Z16) -> 10300 | AB16: =IF(AND($B16="",$D16="",$J16=""),"",IF($B16="","Falta código",IF(ISNA(MATCH($B16,LST_COD,0)),"Código no registrado en Trabajadores",IF($E16="","Concepto no está en el catálogo",IF($M16="ERR","Retención de otro empleador: Origen = Otro empleador",IF(OR($J16="",$K16=""),"Falta monto o mes",IF(OR($K16<1,$K16>12),"Mes inicio inválido",IF(AND($L16<>"",OR($L16<$K16,$L16>12)),"Mes fin inválido",IF($N16="","Falta frecuencia",IF(AND($G16<>"Otro empleador",SUMPRODUCT(($O16:$Z16<>0)*(((COLUMN($O16:$Z16)-14)<INDEX(Trabajadores!$M$6:$M$105,MATCH($B16,LST_COD,0)))+((COLUMN($O16:$Z16)-14)>INDEX(Trabajadores!$N$6:$N$105,MATCH($B16,LST_COD,0)))))>0),"Aviso: hay meses fuera del periodo laboral","OK")))))))))) -> OK
A17: 12 | B17: EJ-001 | C17: =IF($B17="","",IFERROR(INDEX(Trabajadores!$D$6:$D$105,MATCH($B17,LST_COD,0)),"¿Código?")) -> PÉREZ GARCÍA, ANA (EJEMPLO) | D17: Movilidad supeditada a la asistencia | E17: =IF($D17="","",IFERROR(VLOOKUP($D17,CONC_TABLA,2,FALSE()),"")) -> INA | F17: =IF($D17="","",IFERROR(VLOOKUP($D17,CONC_TABLA,3,FALSE()),"")) -> No | G17: Empresa principal | I17: Mensual | J17: 300 | K17: 1 | L17: 12 | M17: =IF(OR($B17="",$E17=""),"",IF($E17="INA","INA",IF($G17="Otro empleador",IF($E17="RET","RETO",IF($E17="ORD","OTO","OTX")),IF($E17="RET","ERR",$E17)))) -> INA | N17: =IF($I17="","",IFERROR(VLOOKUP($I17,FREC_TABLA,2,FALSE()),"")) -> 1 | O17: =IF(OR($M17="",$M17="ERR",$J17="",$K17="",$N17=""),0,IF($N17=0,IF(AND(OR(1=7,1=12),1>=$K17,1<=IF($L17="",12,$L17)),$J17,0),IF(AND(1>=$K17,1<=IF($L17="",12,$L17),MOD(1-$K17,$N17)=0),$J17,0))) -> 300 | P17: =IF(OR($M17="",$M17="ERR",$J17="",$K17="",$N17=""),0,IF($N17=0,IF(AND(OR(2=7,2=12),2>=$K17,2<=IF($L17="",12,$L17)),$J17,0),IF(AND(2>=$K17,2<=IF($L17="",12,$L17),MOD(2-$K17,$N17)=0),$J17,0))) -> 300 | Q17: =IF(OR($M17="",$M17="ERR",$J17="",$K17="",$N17=""),0,IF($N17=0,IF(AND(OR(3=7,3=12),3>=$K17,3<=IF($L17="",12,$L17)),$J17,0),IF(AND(3>=$K17,3<=IF($L17="",12,$L17),MOD(3-$K17,$N17)=0),$J17,0))) -> 300 | R17: =IF(OR($M17="",$M17="ERR",$J17="",$K17="",$N17=""),0,IF($N17=0,IF(AND(OR(4=7,4=12),4>=$K17,4<=IF($L17="",12,$L17)),$J17,0),IF(AND(4>=$K17,4<=IF($L17="",12,$L17),MOD(4-$K17,$N17)=0),$J17,0))) -> 300 | S17: =IF(OR($M17="",$M17="ERR",$J17="",$K17="",$N17=""),0,IF($N17=0,IF(AND(OR(5=7,5=12),5>=$K17,5<=IF($L17="",12,$L17)),$J17,0),IF(AND(5>=$K17,5<=IF($L17="",12,$L17),MOD(5-$K17,$N17)=0),$J17,0))) -> 300 | T17: =IF(OR($M17="",$M17="ERR",$J17="",$K17="",$N17=""),0,IF($N17=0,IF(AND(OR(6=7,6=12),6>=$K17,6<=IF($L17="",12,$L17)),$J17,0),IF(AND(6>=$K17,6<=IF($L17="",12,$L17),MOD(6-$K17,$N17)=0),$J17,0))) -> 300 | U17: =IF(OR($M17="",$M17="ERR",$J17="",$K17="",$N17=""),0,IF($N17=0,IF(AND(OR(7=7,7=12),7>=$K17,7<=IF($L17="",12,$L17)),$J17,0),IF(AND(7>=$K17,7<=IF($L17="",12,$L17),MOD(7-$K17,$N17)=0),$J17,0))) -> 300 | V17: =IF(OR($M17="",$M17="ERR",$J17="",$K17="",$N17=""),0,IF($N17=0,IF(AND(OR(8=7,8=12),8>=$K17,8<=IF($L17="",12,$L17)),$J17,0),IF(AND(8>=$K17,8<=IF($L17="",12,$L17),MOD(8-$K17,$N17)=0),$J17,0))) -> 300 | W17: =IF(OR($M17="",$M17="ERR",$J17="",$K17="",$N17=""),0,IF($N17=0,IF(AND(OR(9=7,9=12),9>=$K17,9<=IF($L17="",12,$L17)),$J17,0),IF(AND(9>=$K17,9<=IF($L17="",12,$L17),MOD(9-$K17,$N17)=0),$J17,0))) -> 300 | X17: =IF(OR($M17="",$M17="ERR",$J17="",$K17="",$N17=""),0,IF($N17=0,IF(AND(OR(10=7,10=12),10>=$K17,10<=IF($L17="",12,$L17)),$J17,0),IF(AND(10>=$K17,10<=IF($L17="",12,$L17),MOD(10-$K17,$N17)=0),$J17,0))) -> 300 | Y17: =IF(OR($M17="",$M17="ERR",$J17="",$K17="",$N17=""),0,IF($N17=0,IF(AND(OR(11=7,11=12),11>=$K17,11<=IF($L17="",12,$L17)),$J17,0),IF(AND(11>=$K17,11<=IF($L17="",12,$L17),MOD(11-$K17,$N17)=0),$J17,0))) -> 300 | Z17: =IF(OR($M17="",$M17="ERR",$J17="",$K17="",$N17=""),0,IF($N17=0,IF(AND(OR(12=7,12=12),12>=$K17,12<=IF($L17="",12,$L17)),$J17,0),IF(AND(12>=$K17,12<=IF($L17="",12,$L17),MOD(12-$K17,$N17)=0),$J17,0))) -> 300 | AA17: =SUM(O17:Z17) -> 3600 | AB17: =IF(AND($B17="",$D17="",$J17=""),"",IF($B17="","Falta código",IF(ISNA(MATCH($B17,LST_COD,0)),"Código no registrado en Trabajadores",IF($E17="","Concepto no está en el catálogo",IF($M17="ERR","Retención de otro empleador: Origen = Otro empleador",IF(OR($J17="",$K17=""),"Falta monto o mes",IF(OR($K17<1,$K17>12),"Mes inicio inválido",IF(AND($L17<>"",OR($L17<$K17,$L17>12)),"Mes fin inválido",IF($N17="","Falta frecuencia",IF(AND($G17<>"Otro empleador",SUMPRODUCT(($O17:$Z17<>0)*(((COLUMN($O17:$Z17)-14)<INDEX(Trabajadores!$M$6:$M$105,MATCH($B17,LST_COD,0)))+((COLUMN($O17:$Z17)-14)>INDEX(Trabajadores!$N$6:$N$105,MATCH($B17,LST_COD,0)))))>0),"Aviso: hay meses fuera del periodo laboral","OK")))))))))) -> OK
A18: 13 | B18: EJ-002 | C18: =IF($B18="","",IFERROR(INDEX(Trabajadores!$D$6:$D$105,MATCH($B18,LST_COD,0)),"¿Código?")) -> QUISPE MAMANI, LUIS (EJEMPLO) | D18: Remuneración de otro empleador (total del mes) | E18: =IF($D18="","",IFERROR(VLOOKUP($D18,CONC_TABLA,2,FALSE()),"")) -> ORD | F18: =IF($D18="","",IFERROR(VLOOKUP($D18,CONC_TABLA,3,FALSE()),"")) -> No | G18: Otro empleador | H18: 20111111111 – COMERCIAL ANTERIOR S.A. | I18: Mensual | J18: 5000 | K18: 1 | L18: 4 | M18: =IF(OR($B18="",$E18=""),"",IF($E18="INA","INA",IF($G18="Otro empleador",IF($E18="RET","RETO",IF($E18="ORD","OTO","OTX")),IF($E18="RET","ERR",$E18)))) -> OTO | N18: =IF($I18="","",IFERROR(VLOOKUP($I18,FREC_TABLA,2,FALSE()),"")) -> 1 | O18: =IF(OR($M18="",$M18="ERR",$J18="",$K18="",$N18=""),0,IF($N18=0,IF(AND(OR(1=7,1=12),1>=$K18,1<=IF($L18="",12,$L18)),$J18,0),IF(AND(1>=$K18,1<=IF($L18="",12,$L18),MOD(1-$K18,$N18)=0),$J18,0))) -> 5000 | P18: =IF(OR($M18="",$M18="ERR",$J18="",$K18="",$N18=""),0,IF($N18=0,IF(AND(OR(2=7,2=12),2>=$K18,2<=IF($L18="",12,$L18)),$J18,0),IF(AND(2>=$K18,2<=IF($L18="",12,$L18),MOD(2-$K18,$N18)=0),$J18,0))) -> 5000 | Q18: =IF(OR($M18="",$M18="ERR",$J18="",$K18="",$N18=""),0,IF($N18=0,IF(AND(OR(3=7,3=12),3>=$K18,3<=IF($L18="",12,$L18)),$J18,0),IF(AND(3>=$K18,3<=IF($L18="",12,$L18),MOD(3-$K18,$N18)=0),$J18,0))) -> 5000 | R18: =IF(OR($M18="",$M18="ERR",$J18="",$K18="",$N18=""),0,IF($N18=0,IF(AND(OR(4=7,4=12),4>=$K18,4<=IF($L18="",12,$L18)),$J18,0),IF(AND(4>=$K18,4<=IF($L18="",12,$L18),MOD(4-$K18,$N18)=0),$J18,0))) -> 5000 | S18: =IF(OR($M18="",$M18="ERR",$J18="",$K18="",$N18=""),0,IF($N18=0,IF(AND(OR(5=7,5=12),5>=$K18,5<=IF($L18="",12,$L18)),$J18,0),IF(AND(5>=$K18,5<=IF($L18="",12,$L18),MOD(5-$K18,$N18)=0),$J18,0))) -> 0 | T18: =IF(OR($M18="",$M18="ERR",$J18="",$K18="",$N18=""),0,IF($N18=0,IF(AND(OR(6=7,6=12),6>=$K18,6<=IF($L18="",12,$L18)),$J18,0),IF(AND(6>=$K18,6<=IF($L18="",12,$L18),MOD(6-$K18,$N18)=0),$J18,0))) -> 0 | U18: =IF(OR($M18="",$M18="ERR",$J18="",$K18="",$N18=""),0,IF($N18=0,IF(AND(OR(7=7,7=12),7>=$K18,7<=IF($L18="",12,$L18)),$J18,0),IF(AND(7>=$K18,7<=IF($L18="",12,$L18),MOD(7-$K18,$N18)=0),$J18,0))) -> 0 | V18: =IF(OR($M18="",$M18="ERR",$J18="",$K18="",$N18=""),0,IF($N18=0,IF(AND(OR(8=7,8=12),8>=$K18,8<=IF($L18="",12,$L18)),$J18,0),IF(AND(8>=$K18,8<=IF($L18="",12,$L18),MOD(8-$K18,$N18)=0),$J18,0))) -> 0 | W18: =IF(OR($M18="",$M18="ERR",$J18="",$K18="",$N18=""),0,IF($N18=0,IF(AND(OR(9=7,9=12),9>=$K18,9<=IF($L18="",12,$L18)),$J18,0),IF(AND(9>=$K18,9<=IF($L18="",12,$L18),MOD(9-$K18,$N18)=0),$J18,0))) -> 0 | X18: =IF(OR($M18="",$M18="ERR",$J18="",$K18="",$N18=""),0,IF($N18=0,IF(AND(OR(10=7,10=12),10>=$K18,10<=IF($L18="",12,$L18)),$J18,0),IF(AND(10>=$K18,10<=IF($L18="",12,$L18),MOD(10-$K18,$N18)=0),$J18,0))) -> 0 | Y18: =IF(OR($M18="",$M18="ERR",$J18="",$K18="",$N18=""),0,IF($N18=0,IF(AND(OR(11=7,11=12),11>=$K18,11<=IF($L18="",12,$L18)),$J18,0),IF(AND(11>=$K18,11<=IF($L18="",12,$L18),MOD(11-$K18,$N18)=0),$J18,0))) -> 0 | Z18: =IF(OR($M18="",$M18="ERR",$J18="",$K18="",$N18=""),0,IF($N18=0,IF(AND(OR(12=7,12=12),12>=$K18,12<=IF($L18="",12,$L18)),$J18,0),IF(AND(12>=$K18,12<=IF($L18="",12,$L18),MOD(12-$K18,$N18)=0),$J18,0))) -> 0 | AA18: =SUM(O18:Z18) -> 20000 | AB18: =IF(AND($B18="",$D18="",$J18=""),"",IF($B18="","Falta código",IF(ISNA(MATCH($B18,LST_COD,0)),"Código no registrado en Trabajadores",IF($E18="","Concepto no está en el catálogo",IF($M18="ERR","Retención de otro empleador: Origen = Otro empleador",IF(OR($J18="",$K18=""),"Falta monto o mes",IF(OR($K18<1,$K18>12),"Mes inicio inválido",IF(AND($L18<>"",OR($L18<$K18,$L18>12)),"Mes fin inválido",IF($N18="","Falta frecuencia",IF(AND($G18<>"Otro empleador",SUMPRODUCT(($O18:$Z18<>0)*(((COLUMN($O18:$Z18)-14)<INDEX(Trabajadores!$M$6:$M$105,MATCH($B18,LST_COD,0)))+((COLUMN($O18:$Z18)-14)>INDEX(Trabajadores!$N$6:$N$105,MATCH($B18,LST_COD,0)))))>0),"Aviso: hay meses fuera del periodo laboral","OK")))))))))) -> OK
A19: 14 | B19: EJ-002 | C19: =IF($B19="","",IFERROR(INDEX(Trabajadores!$D$6:$D$105,MATCH($B19,LST_COD,0)),"¿Código?")) -> QUISPE MAMANI, LUIS (EJEMPLO) | D19: Gratificación trunca | E19: =IF($D19="","",IFERROR(VLOOKUP($D19,CONC_TABLA,2,FALSE()),"")) -> EXT | F19: =IF($D19="","",IFERROR(VLOOKUP($D19,CONC_TABLA,3,FALSE()),"")) -> No | G19: Otro empleador | H19: 20111111111 – COMERCIAL ANTERIOR S.A. | I19: Pago único | J19: 2725 | K19: 4 | M19: =IF(OR($B19="",$E19=""),"",IF($E19="INA","INA",IF($G19="Otro empleador",IF($E19="RET","RETO",IF($E19="ORD","OTO","OTX")),IF($E19="RET","ERR",$E19)))) -> OTX | N19: =IF($I19="","",IFERROR(VLOOKUP($I19,FREC_TABLA,2,FALSE()),"")) -> 12 | O19: =IF(OR($M19="",$M19="ERR",$J19="",$K19="",$N19=""),0,IF($N19=0,IF(AND(OR(1=7,1=12),1>=$K19,1<=IF($L19="",12,$L19)),$J19,0),IF(AND(1>=$K19,1<=IF($L19="",12,$L19),MOD(1-$K19,$N19)=0),$J19,0))) -> 0 | P19: =IF(OR($M19="",$M19="ERR",$J19="",$K19="",$N19=""),0,IF($N19=0,IF(AND(OR(2=7,2=12),2>=$K19,2<=IF($L19="",12,$L19)),$J19,0),IF(AND(2>=$K19,2<=IF($L19="",12,$L19),MOD(2-$K19,$N19)=0),$J19,0))) -> 0 | Q19: =IF(OR($M19="",$M19="ERR",$J19="",$K19="",$N19=""),0,IF($N19=0,IF(AND(OR(3=7,3=12),3>=$K19,3<=IF($L19="",12,$L19)),$J19,0),IF(AND(3>=$K19,3<=IF($L19="",12,$L19),MOD(3-$K19,$N19)=0),$J19,0))) -> 0 | R19: =IF(OR($M19="",$M19="ERR",$J19="",$K19="",$N19=""),0,IF($N19=0,IF(AND(OR(4=7,4=12),4>=$K19,4<=IF($L19="",12,$L19)),$J19,0),IF(AND(4>=$K19,4<=IF($L19="",12,$L19),MOD(4-$K19,$N19)=0),$J19,0))) -> 2725 | S19: =IF(OR($M19="",$M19="ERR",$J19="",$K19="",$N19=""),0,IF($N19=0,IF(AND(OR(5=7,5=12),5>=$K19,5<=IF($L19="",12,$L19)),$J19,0),IF(AND(5>=$K19,5<=IF($L19="",12,$L19),MOD(5-$K19,$N19)=0),$J19,0))) -> 0 | T19: =IF(OR($M19="",$M19="ERR",$J19="",$K19="",$N19=""),0,IF($N19=0,IF(AND(OR(6=7,6=12),6>=$K19,6<=IF($L19="",12,$L19)),$J19,0),IF(AND(6>=$K19,6<=IF($L19="",12,$L19),MOD(6-$K19,$N19)=0),$J19,0))) -> 0 | U19: =IF(OR($M19="",$M19="ERR",$J19="",$K19="",$N19=""),0,IF($N19=0,IF(AND(OR(7=7,7=12),7>=$K19,7<=IF($L19="",12,$L19)),$J19,0),IF(AND(7>=$K19,7<=IF($L19="",12,$L19),MOD(7-$K19,$N19)=0),$J19,0))) -> 0 | V19: =IF(OR($M19="",$M19="ERR",$J19="",$K19="",$N19=""),0,IF($N19=0,IF(AND(OR(8=7,8=12),8>=$K19,8<=IF($L19="",12,$L19)),$J19,0),IF(AND(8>=$K19,8<=IF($L19="",12,$L19),MOD(8-$K19,$N19)=0),$J19,0))) -> 0 | W19: =IF(OR($M19="",$M19="ERR",$J19="",$K19="",$N19=""),0,IF($N19=0,IF(AND(OR(9=7,9=12),9>=$K19,9<=IF($L19="",12,$L19)),$J19,0),IF(AND(9>=$K19,9<=IF($L19="",12,$L19),MOD(9-$K19,$N19)=0),$J19,0))) -> 0 | X19: =IF(OR($M19="",$M19="ERR",$J19="",$K19="",$N19=""),0,IF($N19=0,IF(AND(OR(10=7,10=12),10>=$K19,10<=IF($L19="",12,$L19)),$J19,0),IF(AND(10>=$K19,10<=IF($L19="",12,$L19),MOD(10-$K19,$N19)=0),$J19,0))) -> 0 | Y19: =IF(OR($M19="",$M19="ERR",$J19="",$K19="",$N19=""),0,IF($N19=0,IF(AND(OR(11=7,11=12),11>=$K19,11<=IF($L19="",12,$L19)),$J19,0),IF(AND(11>=$K19,11<=IF($L19="",12,$L19),MOD(11-$K19,$N19)=0),$J19,0))) -> 0 | Z19: =IF(OR($M19="",$M19="ERR",$J19="",$K19="",$N19=""),0,IF($N19=0,IF(AND(OR(12=7,12=12),12>=$K19,12<=IF($L19="",12,$L19)),$J19,0),IF(AND(12>=$K19,12<=IF($L19="",12,$L19),MOD(12-$K19,$N19)=0),$J19,0))) -> 0 | AA19: =SUM(O19:Z19) -> 2725 | AB19: =IF(AND($B19="",$D19="",$J19=""),"",IF($B19="","Falta código",IF(ISNA(MATCH($B19,LST_COD,0)),"Código no registrado en Trabajadores",IF($E19="","Concepto no está en el catálogo",IF($M19="ERR","Retención de otro empleador: Origen = Otro empleador",IF(OR($J19="",$K19=""),"Falta monto o mes",IF(OR($K19<1,$K19>12),"Mes inicio inválido",IF(AND($L19<>"",OR($L19<$K19,$L19>12)),"Mes fin inválido",IF($N19="","Falta frecuencia",IF(AND($G19<>"Otro empleador",SUMPRODUCT(($O19:$Z19<>0)*(((COLUMN($O19:$Z19)-14)<INDEX(Trabajadores!$M$6:$M$105,MATCH($B19,LST_COD,0)))+((COLUMN($O19:$Z19)-14)>INDEX(Trabajadores!$N$6:$N$105,MATCH($B19,LST_COD,0)))))>0),"Aviso: hay meses fuera del periodo laboral","OK")))))))))) -> OK
A20: 15 | B20: EJ-002 | C20: =IF($B20="","",IFERROR(INDEX(Trabajadores!$D$6:$D$105,MATCH($B20,LST_COD,0)),"¿Código?")) -> QUISPE MAMANI, LUIS (EJEMPLO) | D20: Retención de 5ta efectuada por otro empleador | E20: =IF($D20="","",IFERROR(VLOOKUP($D20,CONC_TABLA,2,FALSE()),"")) -> RET | F20: =IF($D20="","",IFERROR(VLOOKUP($D20,CONC_TABLA,3,FALSE()),"")) -> No | G20: Otro empleador | H20: 20111111111 – COMERCIAL ANTERIOR S.A. | I20: Pago único | J20: 721.5 | K20: 3 | M20: =IF(OR($B20="",$E20=""),"",IF($E20="INA","INA",IF($G20="Otro empleador",IF($E20="RET","RETO",IF($E20="ORD","OTO","OTX")),IF($E20="RET","ERR",$E20)))) -> RETO | N20: =IF($I20="","",IFERROR(VLOOKUP($I20,FREC_TABLA,2,FALSE()),"")) -> 12 | O20: =IF(OR($M20="",$M20="ERR",$J20="",$K20="",$N20=""),0,IF($N20=0,IF(AND(OR(1=7,1=12),1>=$K20,1<=IF($L20="",12,$L20)),$J20,0),IF(AND(1>=$K20,1<=IF($L20="",12,$L20),MOD(1-$K20,$N20)=0),$J20,0))) -> 0 | P20: =IF(OR($M20="",$M20="ERR",$J20="",$K20="",$N20=""),0,IF($N20=0,IF(AND(OR(2=7,2=12),2>=$K20,2<=IF($L20="",12,$L20)),$J20,0),IF(AND(2>=$K20,2<=IF($L20="",12,$L20),MOD(2-$K20,$N20)=0),$J20,0))) -> 0 | Q20: =IF(OR($M20="",$M20="ERR",$J20="",$K20="",$N20=""),0,IF($N20=0,IF(AND(OR(3=7,3=12),3>=$K20,3<=IF($L20="",12,$L20)),$J20,0),IF(AND(3>=$K20,3<=IF($L20="",12,$L20),MOD(3-$K20,$N20)=0),$J20,0))) -> 721.5 | R20: =IF(OR($M20="",$M20="ERR",$J20="",$K20="",$N20=""),0,IF($N20=0,IF(AND(OR(4=7,4=12),4>=$K20,4<=IF($L20="",12,$L20)),$J20,0),IF(AND(4>=$K20,4<=IF($L20="",12,$L20),MOD(4-$K20,$N20)=0),$J20,0))) -> 0 | S20: =IF(OR($M20="",$M20="ERR",$J20="",$K20="",$N20=""),0,IF($N20=0,IF(AND(OR(5=7,5=12),5>=$K20,5<=IF($L20="",12,$L20)),$J20,0),IF(AND(5>=$K20,5<=IF($L20="",12,$L20),MOD(5-$K20,$N20)=0),$J20,0))) -> 0 | T20: =IF(OR($M20="",$M20="ERR",$J20="",$K20="",$N20=""),0,IF($N20=0,IF(AND(OR(6=7,6=12),6>=$K20,6<=IF($L20="",12,$L20)),$J20,0),IF(AND(6>=$K20,6<=IF($L20="",12,$L20),MOD(6-$K20,$N20)=0),$J20,0))) -> 0 | U20: =IF(OR($M20="",$M20="ERR",$J20="",$K20="",$N20=""),0,IF($N20=0,IF(AND(OR(7=7,7=12),7>=$K20,7<=IF($L20="",12,$L20)),$J20,0),IF(AND(7>=$K20,7<=IF($L20="",12,$L20),MOD(7-$K20,$N20)=0),$J20,0))) -> 0 | V20: =IF(OR($M20="",$M20="ERR",$J20="",$K20="",$N20=""),0,IF($N20=0,IF(AND(OR(8=7,8=12),8>=$K20,8<=IF($L20="",12,$L20)),$J20,0),IF(AND(8>=$K20,8<=IF($L20="",12,$L20),MOD(8-$K20,$N20)=0),$J20,0))) -> 0 | W20: =IF(OR($M20="",$M20="ERR",$J20="",$K20="",$N20=""),0,IF($N20=0,IF(AND(OR(9=7,9=12),9>=$K20,9<=IF($L20="",12,$L20)),$J20,0),IF(AND(9>=$K20,9<=IF($L20="",12,$L20),MOD(9-$K20,$N20)=0),$J20,0))) -> 0 | X20: =IF(OR($M20="",$M20="ERR",$J20="",$K20="",$N20=""),0,IF($N20=0,IF(AND(OR(10=7,10=12),10>=$K20,10<=IF($L20="",12,$L20)),$J20,0),IF(AND(10>=$K20,10<=IF($L20="",12,$L20),MOD(10-$K20,$N20)=0),$J20,0))) -> 0 | Y20: =IF(OR($M20="",$M20="ERR",$J20="",$K20="",$N20=""),0,IF($N20=0,IF(AND(OR(11=7,11=12),11>=$K20,11<=IF($L20="",12,$L20)),$J20,0),IF(AND(11>=$K20,11<=IF($L20="",12,$L20),MOD(11-$K20,$N20)=0),$J20,0))) -> 0 | Z20: =IF(OR($M20="",$M20="ERR",$J20="",$K20="",$N20=""),0,IF($N20=0,IF(AND(OR(12=7,12=12),12>=$K20,12<=IF($L20="",12,$L20)),$J20,0),IF(AND(12>=$K20,12<=IF($L20="",12,$L20),MOD(12-$K20,$N20)=0),$J20,0))) -> 0 | AA20: =SUM(O20:Z20) -> 721.5 | AB20: =IF(AND($B20="",$D20="",$J20=""),"",IF($B20="","Falta código",IF(ISNA(MATCH($B20,LST_COD,0)),"Código no registrado en Trabajadores",IF($E20="","Concepto no está en el catálogo",IF($M20="ERR","Retención de otro empleador: Origen = Otro empleador",IF(OR($J20="",$K20=""),"Falta monto o mes",IF(OR($K20<1,$K20>12),"Mes inicio inválido",IF(AND($L20<>"",OR($L20<$K20,$L20>12)),"Mes fin inválido",IF($N20="","Falta frecuencia",IF(AND($G20<>"Otro empleador",SUMPRODUCT(($O20:$Z20<>0)*(((COLUMN($O20:$Z20)-14)<INDEX(Trabajadores!$M$6:$M$105,MATCH($B20,LST_COD,0)))+((COLUMN($O20:$Z20)-14)>INDEX(Trabajadores!$N$6:$N$105,MATCH($B20,LST_COD,0)))))>0),"Aviso: hay meses fuera del periodo laboral","OK")))))))))) -> OK
A21: 16 | B21: EJ-002 | C21: =IF($B21="","",IFERROR(INDEX(Trabajadores!$D$6:$D$105,MATCH($B21,LST_COD,0)),"¿Código?")) -> QUISPE MAMANI, LUIS (EJEMPLO) | D21: Remuneración básica / sueldo | E21: =IF($D21="","",IFERROR(VLOOKUP($D21,CONC_TABLA,2,FALSE()),"")) -> ORD | F21: =IF($D21="","",IFERROR(VLOOKUP($D21,CONC_TABLA,3,FALSE()),"")) -> Sí | G21: Empresa principal | I21: Mensual | J21: 6000 | K21: 5 | L21: 12 | M21: =IF(OR($B21="",$E21=""),"",IF($E21="INA","INA",IF($G21="Otro empleador",IF($E21="RET","RETO",IF($E21="ORD","OTO","OTX")),IF($E21="RET","ERR",$E21)))) -> ORD | N21: =IF($I21="","",IFERROR(VLOOKUP($I21,FREC_TABLA,2,FALSE()),"")) -> 1 | O21: =IF(OR($M21="",$M21="ERR",$J21="",$K21="",$N21=""),0,IF($N21=0,IF(AND(OR(1=7,1=12),1>=$K21,1<=IF($L21="",12,$L21)),$J21,0),IF(AND(1>=$K21,1<=IF($L21="",12,$L21),MOD(1-$K21,$N21)=0),$J21,0))) -> 0 | P21: =IF(OR($M21="",$M21="ERR",$J21="",$K21="",$N21=""),0,IF($N21=0,IF(AND(OR(2=7,2=12),2>=$K21,2<=IF($L21="",12,$L21)),$J21,0),IF(AND(2>=$K21,2<=IF($L21="",12,$L21),MOD(2-$K21,$N21)=0),$J21,0))) -> 0 | Q21: =IF(OR($M21="",$M21="ERR",$J21="",$K21="",$N21=""),0,IF($N21=0,IF(AND(OR(3=7,3=12),3>=$K21,3<=IF($L21="",12,$L21)),$J21,0),IF(AND(3>=$K21,3<=IF($L21="",12,$L21),MOD(3-$K21,$N21)=0),$J21,0))) -> 0 | R21: =IF(OR($M21="",$M21="ERR",$J21="",$K21="",$N21=""),0,IF($N21=0,IF(AND(OR(4=7,4=12),4>=$K21,4<=IF($L21="",12,$L21)),$J21,0),IF(AND(4>=$K21,4<=IF($L21="",12,$L21),MOD(4-$K21,$N21)=0),$J21,0))) -> 0 | S21: =IF(OR($M21="",$M21="ERR",$J21="",$K21="",$N21=""),0,IF($N21=0,IF(AND(OR(5=7,5=12),5>=$K21,5<=IF($L21="",12,$L21)),$J21,0),IF(AND(5>=$K21,5<=IF($L21="",12,$L21),MOD(5-$K21,$N21)=0),$J21,0))) -> 6000 | T21: =IF(OR($M21="",$M21="ERR",$J21="",$K21="",$N21=""),0,IF($N21=0,IF(AND(OR(6=7,6=12),6>=$K21,6<=IF($L21="",12,$L21)),$J21,0),IF(AND(6>=$K21,6<=IF($L21="",12,$L21),MOD(6-$K21,$N21)=0),$J21,0))) -> 6000 | U21: =IF(OR($M21="",$M21="ERR",$J21="",$K21="",$N21=""),0,IF($N21=0,IF(AND(OR(7=7,7=12),7>=$K21,7<=IF($L21="",12,$L21)),$J21,0),IF(AND(7>=$K21,7<=IF($L21="",12,$L21),MOD(7-$K21,$N21)=0),$J21,0))) -> 6000 | V21: =IF(OR($M21="",$M21="ERR",$J21="",$K21="",$N21=""),0,IF($N21=0,IF(AND(OR(8=7,8=12),8>=$K21,8<=IF($L21="",12,$L21)),$J21,0),IF(AND(8>=$K21,8<=IF($L21="",12,$L21),MOD(8-$K21,$N21)=0),$J21,0))) -> 6000 | W21: =IF(OR($M21="",$M21="ERR",$J21="",$K21="",$N21=""),0,IF($N21=0,IF(AND(OR(9=7,9=12),9>=$K21,9<=IF($L21="",12,$L21)),$J21,0),IF(AND(9>=$K21,9<=IF($L21="",12,$L21),MOD(9-$K21,$N21)=0),$J21,0))) -> 6000 | X21: =IF(OR($M21="",$M21="ERR",$J21="",$K21="",$N21=""),0,IF($N21=0,IF(AND(OR(10=7,10=12),10>=$K21,10<=IF($L21="",12,$L21)),$J21,0),IF(AND(10>=$K21,10<=IF($L21="",12,$L21),MOD(10-$K21,$N21)=0),$J21,0))) -> 6000 | Y21: =IF(OR($M21="",$M21="ERR",$J21="",$K21="",$N21=""),0,IF($N21=0,IF(AND(OR(11=7,11=12),11>=$K21,11<=IF($L21="",12,$L21)),$J21,0),IF(AND(11>=$K21,11<=IF($L21="",12,$L21),MOD(11-$K21,$N21)=0),$J21,0))) -> 6000 | Z21: =IF(OR($M21="",$M21="ERR",$J21="",$K21="",$N21=""),0,IF($N21=0,IF(AND(OR(12=7,12=12),12>=$K21,12<=IF($L21="",12,$L21)),$J21,0),IF(AND(12>=$K21,12<=IF($L21="",12,$L21),MOD(12-$K21,$N21)=0),$J21,0))) -> 6000 | AA21: =SUM(O21:Z21) -> 48000 | AB21: =IF(AND($B21="",$D21="",$J21=""),"",IF($B21="","Falta código",IF(ISNA(MATCH($B21,LST_COD,0)),"Código no registrado en Trabajadores",IF($E21="","Concepto no está en el catálogo",IF($M21="ERR","Retención de otro empleador: Origen = Otro empleador",IF(OR($J21="",$K21=""),"Falta monto o mes",IF(OR($K21<1,$K21>12),"Mes inicio inválido",IF(AND($L21<>"",OR($L21<$K21,$L21>12)),"Mes fin inválido",IF($N21="","Falta frecuencia",IF(AND($G21<>"Otro empleador",SUMPRODUCT(($O21:$Z21<>0)*(((COLUMN($O21:$Z21)-14)<INDEX(Trabajadores!$M$6:$M$105,MATCH($B21,LST_COD,0)))+((COLUMN($O21:$Z21)-14)>INDEX(Trabajadores!$N$6:$N$105,MATCH($B21,LST_COD,0)))))>0),"Aviso: hay meses fuera del periodo laboral","OK")))))))))) -> OK
A22: 17 | B22: EJ-002 | C22: =IF($B22="","",IFERROR(INDEX(Trabajadores!$D$6:$D$105,MATCH($B22,LST_COD,0)),"¿Código?")) -> QUISPE MAMANI, LUIS (EJEMPLO) | D22: Comisiones / destajo | E22: =IF($D22="","",IFERROR(VLOOKUP($D22,CONC_TABLA,2,FALSE()),"")) -> ORD | F22: =IF($D22="","",IFERROR(VLOOKUP($D22,CONC_TABLA,3,FALSE()),"")) -> No | G22: Empresa principal | I22: Pago único | J22: 850 | K22: 6 | M22: =IF(OR($B22="",$E22=""),"",IF($E22="INA","INA",IF($G22="Otro empleador",IF($E22="RET","RETO",IF($E22="ORD","OTO","OTX")),IF($E22="RET","ERR",$E22)))) -> ORD | N22: =IF($I22="","",IFERROR(VLOOKUP($I22,FREC_TABLA,2,FALSE()),"")) -> 12 | O22: =IF(OR($M22="",$M22="ERR",$J22="",$K22="",$N22=""),0,IF($N22=0,IF(AND(OR(1=7,1=12),1>=$K22,1<=IF($L22="",12,$L22)),$J22,0),IF(AND(1>=$K22,1<=IF($L22="",12,$L22),MOD(1-$K22,$N22)=0),$J22,0))) -> 0 | P22: =IF(OR($M22="",$M22="ERR",$J22="",$K22="",$N22=""),0,IF($N22=0,IF(AND(OR(2=7,2=12),2>=$K22,2<=IF($L22="",12,$L22)),$J22,0),IF(AND(2>=$K22,2<=IF($L22="",12,$L22),MOD(2-$K22,$N22)=0),$J22,0))) -> 0 | Q22: =IF(OR($M22="",$M22="ERR",$J22="",$K22="",$N22=""),0,IF($N22=0,IF(AND(OR(3=7,3=12),3>=$K22,3<=IF($L22="",12,$L22)),$J22,0),IF(AND(3>=$K22,3<=IF($L22="",12,$L22),MOD(3-$K22,$N22)=0),$J22,0))) -> 0 | R22: =IF(OR($M22="",$M22="ERR",$J22="",$K22="",$N22=""),0,IF($N22=0,IF(AND(OR(4=7,4=12),4>=$K22,4<=IF($L22="",12,$L22)),$J22,0),IF(AND(4>=$K22,4<=IF($L22="",12,$L22),MOD(4-$K22,$N22)=0),$J22,0))) -> 0 | S22: =IF(OR($M22="",$M22="ERR",$J22="",$K22="",$N22=""),0,IF($N22=0,IF(AND(OR(5=7,5=12),5>=$K22,5<=IF($L22="",12,$L22)),$J22,0),IF(AND(5>=$K22,5<=IF($L22="",12,$L22),MOD(5-$K22,$N22)=0),$J22,0))) -> 0 | T22: =IF(OR($M22="",$M22="ERR",$J22="",$K22="",$N22=""),0,IF($N22=0,IF(AND(OR(6=7,6=12),6>=$K22,6<=IF($L22="",12,$L22)),$J22,0),IF(AND(6>=$K22,6<=IF($L22="",12,$L22),MOD(6-$K22,$N22)=0),$J22,0))) -> 850 | U22: =IF(OR($M22="",$M22="ERR",$J22="",$K22="",$N22=""),0,IF($N22=0,IF(AND(OR(7=7,7=12),7>=$K22,7<=IF($L22="",12,$L22)),$J22,0),IF(AND(7>=$K22,7<=IF($L22="",12,$L22),MOD(7-$K22,$N22)=0),$J22,0))) -> 0 | V22: =IF(OR($M22="",$M22="ERR",$J22="",$K22="",$N22=""),0,IF($N22=0,IF(AND(OR(8=7,8=12),8>=$K22,8<=IF($L22="",12,$L22)),$J22,0),IF(AND(8>=$K22,8<=IF($L22="",12,$L22),MOD(8-$K22,$N22)=0),$J22,0))) -> 0 | W22: =IF(OR($M22="",$M22="ERR",$J22="",$K22="",$N22=""),0,IF($N22=0,IF(AND(OR(9=7,9=12),9>=$K22,9<=IF($L22="",12,$L22)),$J22,0),IF(AND(9>=$K22,9<=IF($L22="",12,$L22),MOD(9-$K22,$N22)=0),$J22,0))) -> 0 | X22: =IF(OR($M22="",$M22="ERR",$J22="",$K22="",$N22=""),0,IF($N22=0,IF(AND(OR(10=7,10=12),10>=$K22,10<=IF($L22="",12,$L22)),$J22,0),IF(AND(10>=$K22,10<=IF($L22="",12,$L22),MOD(10-$K22,$N22)=0),$J22,0))) -> 0 | Y22: =IF(OR($M22="",$M22="ERR",$J22="",$K22="",$N22=""),0,IF($N22=0,IF(AND(OR(11=7,11=12),11>=$K22,11<=IF($L22="",12,$L22)),$J22,0),IF(AND(11>=$K22,11<=IF($L22="",12,$L22),MOD(11-$K22,$N22)=0),$J22,0))) -> 0 | Z22: =IF(OR($M22="",$M22="ERR",$J22="",$K22="",$N22=""),0,IF($N22=0,IF(AND(OR(12=7,12=12),12>=$K22,12<=IF($L22="",12,$L22)),$J22,0),IF(AND(12>=$K22,12<=IF($L22="",12,$L22),MOD(12-$K22,$N22)=0),$J22,0))) -> 0 | AA22: =SUM(O22:Z22) -> 850 | AB22: =IF(AND($B22="",$D22="",$J22=""),"",IF($B22="","Falta código",IF(ISNA(MATCH($B22,LST_COD,0)),"Código no registrado en Trabajadores",IF($E22="","Concepto no está en el catálogo",IF($M22="ERR","Retención de otro empleador: Origen = Otro empleador",IF(OR($J22="",$K22=""),"Falta monto o mes",IF(OR($K22<1,$K22>12),"Mes inicio inválido",IF(AND($L22<>"",OR($L22<$K22,$L22>12)),"Mes fin inválido",IF($N22="","Falta frecuencia",IF(AND($G22<>"Otro empleador",SUMPRODUCT(($O22:$Z22<>0)*(((COLUMN($O22:$Z22)-14)<INDEX(Trabajadores!$M$6:$M$105,MATCH($B22,LST_COD,0)))+((COLUMN($O22:$Z22)-14)>INDEX(Trabajadores!$N$6:$N$105,MATCH($B22,LST_COD,0)))))>0),"Aviso: hay meses fuera del periodo laboral","OK")))))))))) -> OK
A23: 18 | B23: EJ-002 | C23: =IF($B23="","",IFERROR(INDEX(Trabajadores!$D$6:$D$105,MATCH($B23,LST_COD,0)),"¿Código?")) -> QUISPE MAMANI, LUIS (EJEMPLO) | D23: Comisiones / destajo | E23: =IF($D23="","",IFERROR(VLOOKUP($D23,CONC_TABLA,2,FALSE()),"")) -> ORD | F23: =IF($D23="","",IFERROR(VLOOKUP($D23,CONC_TABLA,3,FALSE()),"")) -> No | G23: Empresa principal | I23: Pago único | J23: 1320 | K23: 8 | M23: =IF(OR($B23="",$E23=""),"",IF($E23="INA","INA",IF($G23="Otro empleador",IF($E23="RET","RETO",IF($E23="ORD","OTO","OTX")),IF($E23="RET","ERR",$E23)))) -> ORD | N23: =IF($I23="","",IFERROR(VLOOKUP($I23,FREC_TABLA,2,FALSE()),"")) -> 12 | O23: =IF(OR($M23="",$M23="ERR",$J23="",$K23="",$N23=""),0,IF($N23=0,IF(AND(OR(1=7,1=12),1>=$K23,1<=IF($L23="",12,$L23)),$J23,0),IF(AND(1>=$K23,1<=IF($L23="",12,$L23),MOD(1-$K23,$N23)=0),$J23,0))) -> 0 | P23: =IF(OR($M23="",$M23="ERR",$J23="",$K23="",$N23=""),0,IF($N23=0,IF(AND(OR(2=7,2=12),2>=$K23,2<=IF($L23="",12,$L23)),$J23,0),IF(AND(2>=$K23,2<=IF($L23="",12,$L23),MOD(2-$K23,$N23)=0),$J23,0))) -> 0 | Q23: =IF(OR($M23="",$M23="ERR",$J23="",$K23="",$N23=""),0,IF($N23=0,IF(AND(OR(3=7,3=12),3>=$K23,3<=IF($L23="",12,$L23)),$J23,0),IF(AND(3>=$K23,3<=IF($L23="",12,$L23),MOD(3-$K23,$N23)=0),$J23,0))) -> 0 | R23: =IF(OR($M23="",$M23="ERR",$J23="",$K23="",$N23=""),0,IF($N23=0,IF(AND(OR(4=7,4=12),4>=$K23,4<=IF($L23="",12,$L23)),$J23,0),IF(AND(4>=$K23,4<=IF($L23="",12,$L23),MOD(4-$K23,$N23)=0),$J23,0))) -> 0 | S23: =IF(OR($M23="",$M23="ERR",$J23="",$K23="",$N23=""),0,IF($N23=0,IF(AND(OR(5=7,5=12),5>=$K23,5<=IF($L23="",12,$L23)),$J23,0),IF(AND(5>=$K23,5<=IF($L23="",12,$L23),MOD(5-$K23,$N23)=0),$J23,0))) -> 0 | T23: =IF(OR($M23="",$M23="ERR",$J23="",$K23="",$N23=""),0,IF($N23=0,IF(AND(OR(6=7,6=12),6>=$K23,6<=IF($L23="",12,$L23)),$J23,0),IF(AND(6>=$K23,6<=IF($L23="",12,$L23),MOD(6-$K23,$N23)=0),$J23,0))) -> 0 | U23: =IF(OR($M23="",$M23="ERR",$J23="",$K23="",$N23=""),0,IF($N23=0,IF(AND(OR(7=7,7=12),7>=$K23,7<=IF($L23="",12,$L23)),$J23,0),IF(AND(7>=$K23,7<=IF($L23="",12,$L23),MOD(7-$K23,$N23)=0),$J23,0))) -> 0 | V23: =IF(OR($M23="",$M23="ERR",$J23="",$K23="",$N23=""),0,IF($N23=0,IF(AND(OR(8=7,8=12),8>=$K23,8<=IF($L23="",12,$L23)),$J23,0),IF(AND(8>=$K23,8<=IF($L23="",12,$L23),MOD(8-$K23,$N23)=0),$J23,0))) -> 1320 | W23: =IF(OR($M23="",$M23="ERR",$J23="",$K23="",$N23=""),0,IF($N23=0,IF(AND(OR(9=7,9=12),9>=$K23,9<=IF($L23="",12,$L23)),$J23,0),IF(AND(9>=$K23,9<=IF($L23="",12,$L23),MOD(9-$K23,$N23)=0),$J23,0))) -> 0 | X23: =IF(OR($M23="",$M23="ERR",$J23="",$K23="",$N23=""),0,IF($N23=0,IF(AND(OR(10=7,10=12),10>=$K23,10<=IF($L23="",12,$L23)),$J23,0),IF(AND(10>=$K23,10<=IF($L23="",12,$L23),MOD(10-$K23,$N23)=0),$J23,0))) -> 0 | Y23: =IF(OR($M23="",$M23="ERR",$J23="",$K23="",$N23=""),0,IF($N23=0,IF(AND(OR(11=7,11=12),11>=$K23,11<=IF($L23="",12,$L23)),$J23,0),IF(AND(11>=$K23,11<=IF($L23="",12,$L23),MOD(11-$K23,$N23)=0),$J23,0))) -> 0 | Z23: =IF(OR($M23="",$M23="ERR",$J23="",$K23="",$N23=""),0,IF($N23=0,IF(AND(OR(12=7,12=12),12>=$K23,12<=IF($L23="",12,$L23)),$J23,0),IF(AND(12>=$K23,12<=IF($L23="",12,$L23),MOD(12-$K23,$N23)=0),$J23,0))) -> 0 | AA23: =SUM(O23:Z23) -> 1320 | AB23: =IF(AND($B23="",$D23="",$J23=""),"",IF($B23="","Falta código",IF(ISNA(MATCH($B23,LST_COD,0)),"Código no registrado en Trabajadores",IF($E23="","Concepto no está en el catálogo",IF($M23="ERR","Retención de otro empleador: Origen = Otro empleador",IF(OR($J23="",$K23=""),"Falta monto o mes",IF(OR($K23<1,$K23>12),"Mes inicio inválido",IF(AND($L23<>"",OR($L23<$K23,$L23>12)),"Mes fin inválido",IF($N23="","Falta frecuencia",IF(AND($G23<>"Otro empleador",SUMPRODUCT(($O23:$Z23<>0)*(((COLUMN($O23:$Z23)-14)<INDEX(Trabajadores!$M$6:$M$105,MATCH($B23,LST_COD,0)))+((COLUMN($O23:$Z23)-14)>INDEX(Trabajadores!$N$6:$N$105,MATCH($B23,LST_COD,0)))))>0),"Aviso: hay meses fuera del periodo laboral","OK")))))))))) -> OK
A24: 19 | B24: EJ-002 | C24: =IF($B24="","",IFERROR(INDEX(Trabajadores!$D$6:$D$105,MATCH($B24,LST_COD,0)),"¿Código?")) -> QUISPE MAMANI, LUIS (EJEMPLO) | D24: Gratificación ordinaria (Fiestas Patrias / Navidad) | E24: =IF($D24="","",IFERROR(VLOOKUP($D24,CONC_TABLA,2,FALSE()),"")) -> GRA | F24: =IF($D24="","",IFERROR(VLOOKUP($D24,CONC_TABLA,3,FALSE()),"")) -> No | G24: Empresa principal | I24: Pago único | J24: 2000 | K24: 7 | M24: =IF(OR($B24="",$E24=""),"",IF($E24="INA","INA",IF($G24="Otro empleador",IF($E24="RET","RETO",IF($E24="ORD","OTO","OTX")),IF($E24="RET","ERR",$E24)))) -> GRA | N24: =IF($I24="","",IFERROR(VLOOKUP($I24,FREC_TABLA,2,FALSE()),"")) -> 12 | O24: =IF(OR($M24="",$M24="ERR",$J24="",$K24="",$N24=""),0,IF($N24=0,IF(AND(OR(1=7,1=12),1>=$K24,1<=IF($L24="",12,$L24)),$J24,0),IF(AND(1>=$K24,1<=IF($L24="",12,$L24),MOD(1-$K24,$N24)=0),$J24,0))) -> 0 | P24: =IF(OR($M24="",$M24="ERR",$J24="",$K24="",$N24=""),0,IF($N24=0,IF(AND(OR(2=7,2=12),2>=$K24,2<=IF($L24="",12,$L24)),$J24,0),IF(AND(2>=$K24,2<=IF($L24="",12,$L24),MOD(2-$K24,$N24)=0),$J24,0))) -> 0 | Q24: =IF(OR($M24="",$M24="ERR",$J24="",$K24="",$N24=""),0,IF($N24=0,IF(AND(OR(3=7,3=12),3>=$K24,3<=IF($L24="",12,$L24)),$J24,0),IF(AND(3>=$K24,3<=IF($L24="",12,$L24),MOD(3-$K24,$N24)=0),$J24,0))) -> 0 | R24: =IF(OR($M24="",$M24="ERR",$J24="",$K24="",$N24=""),0,IF($N24=0,IF(AND(OR(4=7,4=12),4>=$K24,4<=IF($L24="",12,$L24)),$J24,0),IF(AND(4>=$K24,4<=IF($L24="",12,$L24),MOD(4-$K24,$N24)=0),$J24,0))) -> 0 | S24: =IF(OR($M24="",$M24="ERR",$J24="",$K24="",$N24=""),0,IF($N24=0,IF(AND(OR(5=7,5=12),5>=$K24,5<=IF($L24="",12,$L24)),$J24,0),IF(AND(5>=$K24,5<=IF($L24="",12,$L24),MOD(5-$K24,$N24)=0),$J24,0))) -> 0 | T24: =IF(OR($M24="",$M24="ERR",$J24="",$K24="",$N24=""),0,IF($N24=0,IF(AND(OR(6=7,6=12),6>=$K24,6<=IF($L24="",12,$L24)),$J24,0),IF(AND(6>=$K24,6<=IF($L24="",12,$L24),MOD(6-$K24,$N24)=0),$J24,0))) -> 0 | U24: =IF(OR($M24="",$M24="ERR",$J24="",$K24="",$N24=""),0,IF($N24=0,IF(AND(OR(7=7,7=12),7>=$K24,7<=IF($L24="",12,$L24)),$J24,0),IF(AND(7>=$K24,7<=IF($L24="",12,$L24),MOD(7-$K24,$N24)=0),$J24,0))) -> 2000 | V24: =IF(OR($M24="",$M24="ERR",$J24="",$K24="",$N24=""),0,IF($N24=0,IF(AND(OR(8=7,8=12),8>=$K24,8<=IF($L24="",12,$L24)),$J24,0),IF(AND(8>=$K24,8<=IF($L24="",12,$L24),MOD(8-$K24,$N24)=0),$J24,0))) -> 0 | W24: =IF(OR($M24="",$M24="ERR",$J24="",$K24="",$N24=""),0,IF($N24=0,IF(AND(OR(9=7,9=12),9>=$K24,9<=IF($L24="",12,$L24)),$J24,0),IF(AND(9>=$K24,9<=IF($L24="",12,$L24),MOD(9-$K24,$N24)=0),$J24,0))) -> 0 | X24: =IF(OR($M24="",$M24="ERR",$J24="",$K24="",$N24=""),0,IF($N24=0,IF(AND(OR(10=7,10=12),10>=$K24,10<=IF($L24="",12,$L24)),$J24,0),IF(AND(10>=$K24,10<=IF($L24="",12,$L24),MOD(10-$K24,$N24)=0),$J24,0))) -> 0 | Y24: =IF(OR($M24="",$M24="ERR",$J24="",$K24="",$N24=""),0,IF($N24=0,IF(AND(OR(11=7,11=12),11>=$K24,11<=IF($L24="",12,$L24)),$J24,0),IF(AND(11>=$K24,11<=IF($L24="",12,$L24),MOD(11-$K24,$N24)=0),$J24,0))) -> 0 | Z24: =IF(OR($M24="",$M24="ERR",$J24="",$K24="",$N24=""),0,IF($N24=0,IF(AND(OR(12=7,12=12),12>=$K24,12<=IF($L24="",12,$L24)),$J24,0),IF(AND(12>=$K24,12<=IF($L24="",12,$L24),MOD(12-$K24,$N24)=0),$J24,0))) -> 0 | AA24: =SUM(O24:Z24) -> 2000 | AB24: =IF(AND($B24="",$D24="",$J24=""),"",IF($B24="","Falta código",IF(ISNA(MATCH($B24,LST_COD,0)),"Código no registrado en Trabajadores",IF($E24="","Concepto no está en el catálogo",IF($M24="ERR","Retención de otro empleador: Origen = Otro empleador",IF(OR($J24="",$K24=""),"Falta monto o mes",IF(OR($K24<1,$K24>12),"Mes inicio inválido",IF(AND($L24<>"",OR($L24<$K24,$L24>12)),"Mes fin inválido",IF($N24="","Falta frecuencia",IF(AND($G24<>"Otro empleador",SUMPRODUCT(($O24:$Z24<>0)*(((COLUMN($O24:$Z24)-14)<INDEX(Trabajadores!$M$6:$M$105,MATCH($B24,LST_COD,0)))+((COLUMN($O24:$Z24)-14)>INDEX(Trabajadores!$N$6:$N$105,MATCH($B24,LST_COD,0)))))>0),"Aviso: hay meses fuera del periodo laboral","OK")))))))))) -> OK
A25: 20 | B25: EJ-002 | C25: =IF($B25="","",IFERROR(INDEX(Trabajadores!$D$6:$D$105,MATCH($B25,LST_COD,0)),"¿Código?")) -> QUISPE MAMANI, LUIS (EJEMPLO) | D25: Bonificación extraordinaria Ley 30334 (9% / 6.75%) | E25: =IF($D25="","",IFERROR(VLOOKUP($D25,CONC_TABLA,2,FALSE()),"")) -> BON | F25: =IF($D25="","",IFERROR(VLOOKUP($D25,CONC_TABLA,3,FALSE()),"")) -> No | G25: Empresa principal | I25: Pago único | J25: 180 | K25: 7 | M25: =IF(OR($B25="",$E25=""),"",IF($E25="INA","INA",IF($G25="Otro empleador",IF($E25="RET","RETO",IF($E25="ORD","OTO","OTX")),IF($E25="RET","ERR",$E25)))) -> BON | N25: =IF($I25="","",IFERROR(VLOOKUP($I25,FREC_TABLA,2,FALSE()),"")) -> 12 | O25: =IF(OR($M25="",$M25="ERR",$J25="",$K25="",$N25=""),0,IF($N25=0,IF(AND(OR(1=7,1=12),1>=$K25,1<=IF($L25="",12,$L25)),$J25,0),IF(AND(1>=$K25,1<=IF($L25="",12,$L25),MOD(1-$K25,$N25)=0),$J25,0))) -> 0 | P25: =IF(OR($M25="",$M25="ERR",$J25="",$K25="",$N25=""),0,IF($N25=0,IF(AND(OR(2=7,2=12),2>=$K25,2<=IF($L25="",12,$L25)),$J25,0),IF(AND(2>=$K25,2<=IF($L25="",12,$L25),MOD(2-$K25,$N25)=0),$J25,0))) -> 0 | Q25: =IF(OR($M25="",$M25="ERR",$J25="",$K25="",$N25=""),0,IF($N25=0,IF(AND(OR(3=7,3=12),3>=$K25,3<=IF($L25="",12,$L25)),$J25,0),IF(AND(3>=$K25,3<=IF($L25="",12,$L25),MOD(3-$K25,$N25)=0),$J25,0))) -> 0 | R25: =IF(OR($M25="",$M25="ERR",$J25="",$K25="",$N25=""),0,IF($N25=0,IF(AND(OR(4=7,4=12),4>=$K25,4<=IF($L25="",12,$L25)),$J25,0),IF(AND(4>=$K25,4<=IF($L25="",12,$L25),MOD(4-$K25,$N25)=0),$J25,0))) -> 0 | S25: =IF(OR($M25="",$M25="ERR",$J25="",$K25="",$N25=""),0,IF($N25=0,IF(AND(OR(5=7,5=12),5>=$K25,5<=IF($L25="",12,$L25)),$J25,0),IF(AND(5>=$K25,5<=IF($L25="",12,$L25),MOD(5-$K25,$N25)=0),$J25,0))) -> 0 | T25: =IF(OR($M25="",$M25="ERR",$J25="",$K25="",$N25=""),0,IF($N25=0,IF(AND(OR(6=7,6=12),6>=$K25,6<=IF($L25="",12,$L25)),$J25,0),IF(AND(6>=$K25,6<=IF($L25="",12,$L25),MOD(6-$K25,$N25)=0),$J25,0))) -> 0 | U25: =IF(OR($M25="",$M25="ERR",$J25="",$K25="",$N25=""),0,IF($N25=0,IF(AND(OR(7=7,7=12),7>=$K25,7<=IF($L25="",12,$L25)),$J25,0),IF(AND(7>=$K25,7<=IF($L25="",12,$L25),MOD(7-$K25,$N25)=0),$J25,0))) -> 180 | V25: =IF(OR($M25="",$M25="ERR",$J25="",$K25="",$N25=""),0,IF($N25=0,IF(AND(OR(8=7,8=12),8>=$K25,8<=IF($L25="",12,$L25)),$J25,0),IF(AND(8>=$K25,8<=IF($L25="",12,$L25),MOD(8-$K25,$N25)=0),$J25,0))) -> 0 | W25: =IF(OR($M25="",$M25="ERR",$J25="",$K25="",$N25=""),0,IF($N25=0,IF(AND(OR(9=7,9=12),9>=$K25,9<=IF($L25="",12,$L25)),$J25,0),IF(AND(9>=$K25,9<=IF($L25="",12,$L25),MOD(9-$K25,$N25)=0),$J25,0))) -> 0 | X25: =IF(OR($M25="",$M25="ERR",$J25="",$K25="",$N25=""),0,IF($N25=0,IF(AND(OR(10=7,10=12),10>=$K25,10<=IF($L25="",12,$L25)),$J25,0),IF(AND(10>=$K25,10<=IF($L25="",12,$L25),MOD(10-$K25,$N25)=0),$J25,0))) -> 0 | Y25: =IF(OR($M25="",$M25="ERR",$J25="",$K25="",$N25=""),0,IF($N25=0,IF(AND(OR(11=7,11=12),11>=$K25,11<=IF($L25="",12,$L25)),$J25,0),IF(AND(11>=$K25,11<=IF($L25="",12,$L25),MOD(11-$K25,$N25)=0),$J25,0))) -> 0 | Z25: =IF(OR($M25="",$M25="ERR",$J25="",$K25="",$N25=""),0,IF($N25=0,IF(AND(OR(12=7,12=12),12>=$K25,12<=IF($L25="",12,$L25)),$J25,0),IF(AND(12>=$K25,12<=IF($L25="",12,$L25),MOD(12-$K25,$N25)=0),$J25,0))) -> 0 | AA25: =SUM(O25:Z25) -> 180 | AB25: =IF(AND($B25="",$D25="",$J25=""),"",IF($B25="","Falta código",IF(ISNA(MATCH($B25,LST_COD,0)),"Código no registrado en Trabajadores",IF($E25="","Concepto no está en el catálogo",IF($M25="ERR","Retención de otro empleador: Origen = Otro empleador",IF(OR($J25="",$K25=""),"Falta monto o mes",IF(OR($K25<1,$K25>12),"Mes inicio inválido",IF(AND($L25<>"",OR($L25<$K25,$L25>12)),"Mes fin inválido",IF($N25="","Falta frecuencia",IF(AND($G25<>"Otro empleador",SUMPRODUCT(($O25:$Z25<>0)*(((COLUMN($O25:$Z25)-14)<INDEX(Trabajadores!$M$6:$M$105,MATCH($B25,LST_COD,0)))+((COLUMN($O25:$Z25)-14)>INDEX(Trabajadores!$N$6:$N$105,MATCH($B25,LST_COD,0)))))>0),"Aviso: hay meses fuera del periodo laboral","OK")))))))))) -> OK
A26: 21 | B26: EJ-002 | C26: =IF($B26="","",IFERROR(INDEX(Trabajadores!$D$6:$D$105,MATCH($B26,LST_COD,0)),"¿Código?")) -> QUISPE MAMANI, LUIS (EJEMPLO) | D26: Gratificación ordinaria (Fiestas Patrias / Navidad) | E26: =IF($D26="","",IFERROR(VLOOKUP($D26,CONC_TABLA,2,FALSE()),"")) -> GRA | F26: =IF($D26="","",IFERROR(VLOOKUP($D26,CONC_TABLA,3,FALSE()),"")) -> No | G26: Empresa principal | I26: Pago único | J26: 6000 | K26: 12 | M26: =IF(OR($B26="",$E26=""),"",IF($E26="INA","INA",IF($G26="Otro empleador",IF($E26="RET","RETO",IF($E26="ORD","OTO","OTX")),IF($E26="RET","ERR",$E26)))) -> GRA | N26: =IF($I26="","",IFERROR(VLOOKUP($I26,FREC_TABLA,2,FALSE()),"")) -> 12 | O26: =IF(OR($M26="",$M26="ERR",$J26="",$K26="",$N26=""),0,IF($N26=0,IF(AND(OR(1=7,1=12),1>=$K26,1<=IF($L26="",12,$L26)),$J26,0),IF(AND(1>=$K26,1<=IF($L26="",12,$L26),MOD(1-$K26,$N26)=0),$J26,0))) -> 0 | P26: =IF(OR($M26="",$M26="ERR",$J26="",$K26="",$N26=""),0,IF($N26=0,IF(AND(OR(2=7,2=12),2>=$K26,2<=IF($L26="",12,$L26)),$J26,0),IF(AND(2>=$K26,2<=IF($L26="",12,$L26),MOD(2-$K26,$N26)=0),$J26,0))) -> 0 | Q26: =IF(OR($M26="",$M26="ERR",$J26="",$K26="",$N26=""),0,IF($N26=0,IF(AND(OR(3=7,3=12),3>=$K26,3<=IF($L26="",12,$L26)),$J26,0),IF(AND(3>=$K26,3<=IF($L26="",12,$L26),MOD(3-$K26,$N26)=0),$J26,0))) -> 0 | R26: =IF(OR($M26="",$M26="ERR",$J26="",$K26="",$N26=""),0,IF($N26=0,IF(AND(OR(4=7,4=12),4>=$K26,4<=IF($L26="",12,$L26)),$J26,0),IF(AND(4>=$K26,4<=IF($L26="",12,$L26),MOD(4-$K26,$N26)=0),$J26,0))) -> 0 | S26: =IF(OR($M26="",$M26="ERR",$J26="",$K26="",$N26=""),0,IF($N26=0,IF(AND(OR(5=7,5=12),5>=$K26,5<=IF($L26="",12,$L26)),$J26,0),IF(AND(5>=$K26,5<=IF($L26="",12,$L26),MOD(5-$K26,$N26)=0),$J26,0))) -> 0 | T26: =IF(OR($M26="",$M26="ERR",$J26="",$K26="",$N26=""),0,IF($N26=0,IF(AND(OR(6=7,6=12),6>=$K26,6<=IF($L26="",12,$L26)),$J26,0),IF(AND(6>=$K26,6<=IF($L26="",12,$L26),MOD(6-$K26,$N26)=0),$J26,0))) -> 0 | U26: =IF(OR($M26="",$M26="ERR",$J26="",$K26="",$N26=""),0,IF($N26=0,IF(AND(OR(7=7,7=12),7>=$K26,7<=IF($L26="",12,$L26)),$J26,0),IF(AND(7>=$K26,7<=IF($L26="",12,$L26),MOD(7-$K26,$N26)=0),$J26,0))) -> 0 | V26: =IF(OR($M26="",$M26="ERR",$J26="",$K26="",$N26=""),0,IF($N26=0,IF(AND(OR(8=7,8=12),8>=$K26,8<=IF($L26="",12,$L26)),$J26,0),IF(AND(8>=$K26,8<=IF($L26="",12,$L26),MOD(8-$K26,$N26)=0),$J26,0))) -> 0 | W26: =IF(OR($M26="",$M26="ERR",$J26="",$K26="",$N26=""),0,IF($N26=0,IF(AND(OR(9=7,9=12),9>=$K26,9<=IF($L26="",12,$L26)),$J26,0),IF(AND(9>=$K26,9<=IF($L26="",12,$L26),MOD(9-$K26,$N26)=0),$J26,0))) -> 0 | X26: =IF(OR($M26="",$M26="ERR",$J26="",$K26="",$N26=""),0,IF($N26=0,IF(AND(OR(10=7,10=12),10>=$K26,10<=IF($L26="",12,$L26)),$J26,0),IF(AND(10>=$K26,10<=IF($L26="",12,$L26),MOD(10-$K26,$N26)=0),$J26,0))) -> 0 | Y26: =IF(OR($M26="",$M26="ERR",$J26="",$K26="",$N26=""),0,IF($N26=0,IF(AND(OR(11=7,11=12),11>=$K26,11<=IF($L26="",12,$L26)),$J26,0),IF(AND(11>=$K26,11<=IF($L26="",12,$L26),MOD(11-$K26,$N26)=0),$J26,0))) -> 0 | Z26: =IF(OR($M26="",$M26="ERR",$J26="",$K26="",$N26=""),0,IF($N26=0,IF(AND(OR(12=7,12=12),12>=$K26,12<=IF($L26="",12,$L26)),$J26,0),IF(AND(12>=$K26,12<=IF($L26="",12,$L26),MOD(12-$K26,$N26)=0),$J26,0))) -> 6000 | AA26: =SUM(O26:Z26) -> 6000 | AB26: =IF(AND($B26="",$D26="",$J26=""),"",IF($B26="","Falta código",IF(ISNA(MATCH($B26,LST_COD,0)),"Código no registrado en Trabajadores",IF($E26="","Concepto no está en el catálogo",IF($M26="ERR","Retención de otro empleador: Origen = Otro empleador",IF(OR($J26="",$K26=""),"Falta monto o mes",IF(OR($K26<1,$K26>12),"Mes inicio inválido",IF(AND($L26<>"",OR($L26<$K26,$L26>12)),"Mes fin inválido",IF($N26="","Falta frecuencia",IF(AND($G26<>"Otro empleador",SUMPRODUCT(($O26:$Z26<>0)*(((COLUMN($O26:$Z26)-14)<INDEX(Trabajadores!$M$6:$M$105,MATCH($B26,LST_COD,0)))+((COLUMN($O26:$Z26)-14)>INDEX(Trabajadores!$N$6:$N$105,MATCH($B26,LST_COD,0)))))>0),"Aviso: hay meses fuera del periodo laboral","OK")))))))))) -> OK
A27: 22 | B27: EJ-002 | C27: =IF($B27="","",IFERROR(INDEX(Trabajadores!$D$6:$D$105,MATCH($B27,LST_COD,0)),"¿Código?")) -> QUISPE MAMANI, LUIS (EJEMPLO) | D27: Bonificación extraordinaria Ley 30334 (9% / 6.75%) | E27: =IF($D27="","",IFERROR(VLOOKUP($D27,CONC_TABLA,2,FALSE()),"")) -> BON | F27: =IF($D27="","",IFERROR(VLOOKUP($D27,CONC_TABLA,3,FALSE()),"")) -> No | G27: Empresa principal | I27: Pago único | J27: 540 | K27: 12 | M27: =IF(OR($B27="",$E27=""),"",IF($E27="INA","INA",IF($G27="Otro empleador",IF($E27="RET","RETO",IF($E27="ORD","OTO","OTX")),IF($E27="RET","ERR",$E27)))) -> BON | N27: =IF($I27="","",IFERROR(VLOOKUP($I27,FREC_TABLA,2,FALSE()),"")) -> 12 | O27: =IF(OR($M27="",$M27="ERR",$J27="",$K27="",$N27=""),0,IF($N27=0,IF(AND(OR(1=7,1=12),1>=$K27,1<=IF($L27="",12,$L27)),$J27,0),IF(AND(1>=$K27,1<=IF($L27="",12,$L27),MOD(1-$K27,$N27)=0),$J27,0))) -> 0 | P27: =IF(OR($M27="",$M27="ERR",$J27="",$K27="",$N27=""),0,IF($N27=0,IF(AND(OR(2=7,2=12),2>=$K27,2<=IF($L27="",12,$L27)),$J27,0),IF(AND(2>=$K27,2<=IF($L27="",12,$L27),MOD(2-$K27,$N27)=0),$J27,0))) -> 0 | Q27: =IF(OR($M27="",$M27="ERR",$J27="",$K27="",$N27=""),0,IF($N27=0,IF(AND(OR(3=7,3=12),3>=$K27,3<=IF($L27="",12,$L27)),$J27,0),IF(AND(3>=$K27,3<=IF($L27="",12,$L27),MOD(3-$K27,$N27)=0),$J27,0))) -> 0 | R27: =IF(OR($M27="",$M27="ERR",$J27="",$K27="",$N27=""),0,IF($N27=0,IF(AND(OR(4=7,4=12),4>=$K27,4<=IF($L27="",12,$L27)),$J27,0),IF(AND(4>=$K27,4<=IF($L27="",12,$L27),MOD(4-$K27,$N27)=0),$J27,0))) -> 0 | S27: =IF(OR($M27="",$M27="ERR",$J27="",$K27="",$N27=""),0,IF($N27=0,IF(AND(OR(5=7,5=12),5>=$K27,5<=IF($L27="",12,$L27)),$J27,0),IF(AND(5>=$K27,5<=IF($L27="",12,$L27),MOD(5-$K27,$N27)=0),$J27,0))) -> 0 | T27: =IF(OR($M27="",$M27="ERR",$J27="",$K27="",$N27=""),0,IF($N27=0,IF(AND(OR(6=7,6=12),6>=$K27,6<=IF($L27="",12,$L27)),$J27,0),IF(AND(6>=$K27,6<=IF($L27="",12,$L27),MOD(6-$K27,$N27)=0),$J27,0))) -> 0 | U27: =IF(OR($M27="",$M27="ERR",$J27="",$K27="",$N27=""),0,IF($N27=0,IF(AND(OR(7=7,7=12),7>=$K27,7<=IF($L27="",12,$L27)),$J27,0),IF(AND(7>=$K27,7<=IF($L27="",12,$L27),MOD(7-$K27,$N27)=0),$J27,0))) -> 0 | V27: =IF(OR($M27="",$M27="ERR",$J27="",$K27="",$N27=""),0,IF($N27=0,IF(AND(OR(8=7,8=12),8>=$K27,8<=IF($L27="",12,$L27)),$J27,0),IF(AND(8>=$K27,8<=IF($L27="",12,$L27),MOD(8-$K27,$N27)=0),$J27,0))) -> 0 | W27: =IF(OR($M27="",$M27="ERR",$J27="",$K27="",$N27=""),0,IF($N27=0,IF(AND(OR(9=7,9=12),9>=$K27,9<=IF($L27="",12,$L27)),$J27,0),IF(AND(9>=$K27,9<=IF($L27="",12,$L27),MOD(9-$K27,$N27)=0),$J27,0))) -> 0 | X27: =IF(OR($M27="",$M27="ERR",$J27="",$K27="",$N27=""),0,IF($N27=0,IF(AND(OR(10=7,10=12),10>=$K27,10<=IF($L27="",12,$L27)),$J27,0),IF(AND(10>=$K27,10<=IF($L27="",12,$L27),MOD(10-$K27,$N27)=0),$J27,0))) -> 0 | Y27: =IF(OR($M27="",$M27="ERR",$J27="",$K27="",$N27=""),0,IF($N27=0,IF(AND(OR(11=7,11=12),11>=$K27,11<=IF($L27="",12,$L27)),$J27,0),IF(AND(11>=$K27,11<=IF($L27="",12,$L27),MOD(11-$K27,$N27)=0),$J27,0))) -> 0 | Z27: =IF(OR($M27="",$M27="ERR",$J27="",$K27="",$N27=""),0,IF($N27=0,IF(AND(OR(12=7,12=12),12>=$K27,12<=IF($L27="",12,$L27)),$J27,0),IF(AND(12>=$K27,12<=IF($L27="",12,$L27),MOD(12-$K27,$N27)=0),$J27,0))) -> 540 | AA27: =SUM(O27:Z27) -> 540 | AB27: =IF(AND($B27="",$D27="",$J27=""),"",IF($B27="","Falta código",IF(ISNA(MATCH($B27,LST_COD,0)),"Código no registrado en Trabajadores",IF($E27="","Concepto no está en el catálogo",IF($M27="ERR","Retención de otro empleador: Origen = Otro empleador",IF(OR($J27="",$K27=""),"Falta monto o mes",IF(OR($K27<1,$K27>12),"Mes inicio inválido",IF(AND($L27<>"",OR($L27<$K27,$L27>12)),"Mes fin inválido",IF($N27="","Falta frecuencia",IF(AND($G27<>"Otro empleador",SUMPRODUCT(($O27:$Z27<>0)*(((COLUMN($O27:$Z27)-14)<INDEX(Trabajadores!$M$6:$M$105,MATCH($B27,LST_COD,0)))+((COLUMN($O27:$Z27)-14)>INDEX(Trabajadores!$N$6:$N$105,MATCH($B27,LST_COD,0)))))>0),"Aviso: hay meses fuera del periodo laboral","OK")))))))))) -> OK
A28: 23 | B28: EJ-003 | C28: =IF($B28="","",IFERROR(INDEX(Trabajadores!$D$6:$D$105,MATCH($B28,LST_COD,0)),"¿Código?")) -> TORRES ROJAS, MARÍA (EJEMPLO) | D28: Remuneración básica / sueldo | E28: =IF($D28="","",IFERROR(VLOOKUP($D28,CONC_TABLA,2,FALSE()),"")) -> ORD | F28: =IF($D28="","",IFERROR(VLOOKUP($D28,CONC_TABLA,3,FALSE()),"")) -> Sí | G28: Empresa principal | I28: Mensual | J28: 15000 | K28: 1 | L28: 9 | M28: =IF(OR($B28="",$E28=""),"",IF($E28="INA","INA",IF($G28="Otro empleador",IF($E28="RET","RETO",IF($E28="ORD","OTO","OTX")),IF($E28="RET","ERR",$E28)))) -> ORD | N28: =IF($I28="","",IFERROR(VLOOKUP($I28,FREC_TABLA,2,FALSE()),"")) -> 1 | O28: =IF(OR($M28="",$M28="ERR",$J28="",$K28="",$N28=""),0,IF($N28=0,IF(AND(OR(1=7,1=12),1>=$K28,1<=IF($L28="",12,$L28)),$J28,0),IF(AND(1>=$K28,1<=IF($L28="",12,$L28),MOD(1-$K28,$N28)=0),$J28,0))) -> 15000 | P28: =IF(OR($M28="",$M28="ERR",$J28="",$K28="",$N28=""),0,IF($N28=0,IF(AND(OR(2=7,2=12),2>=$K28,2<=IF($L28="",12,$L28)),$J28,0),IF(AND(2>=$K28,2<=IF($L28="",12,$L28),MOD(2-$K28,$N28)=0),$J28,0))) -> 15000 | Q28: =IF(OR($M28="",$M28="ERR",$J28="",$K28="",$N28=""),0,IF($N28=0,IF(AND(OR(3=7,3=12),3>=$K28,3<=IF($L28="",12,$L28)),$J28,0),IF(AND(3>=$K28,3<=IF($L28="",12,$L28),MOD(3-$K28,$N28)=0),$J28,0))) -> 15000 | R28: =IF(OR($M28="",$M28="ERR",$J28="",$K28="",$N28=""),0,IF($N28=0,IF(AND(OR(4=7,4=12),4>=$K28,4<=IF($L28="",12,$L28)),$J28,0),IF(AND(4>=$K28,4<=IF($L28="",12,$L28),MOD(4-$K28,$N28)=0),$J28,0))) -> 15000 | S28: =IF(OR($M28="",$M28="ERR",$J28="",$K28="",$N28=""),0,IF($N28=0,IF(AND(OR(5=7,5=12),5>=$K28,5<=IF($L28="",12,$L28)),$J28,0),IF(AND(5>=$K28,5<=IF($L28="",12,$L28),MOD(5-$K28,$N28)=0),$J28,0))) -> 15000 | T28: =IF(OR($M28="",$M28="ERR",$J28="",$K28="",$N28=""),0,IF($N28=0,IF(AND(OR(6=7,6=12),6>=$K28,6<=IF($L28="",12,$L28)),$J28,0),IF(AND(6>=$K28,6<=IF($L28="",12,$L28),MOD(6-$K28,$N28)=0),$J28,0))) -> 15000 | U28: =IF(OR($M28="",$M28="ERR",$J28="",$K28="",$N28=""),0,IF($N28=0,IF(AND(OR(7=7,7=12),7>=$K28,7<=IF($L28="",12,$L28)),$J28,0),IF(AND(7>=$K28,7<=IF($L28="",12,$L28),MOD(7-$K28,$N28)=0),$J28,0))) -> 15000 | V28: =IF(OR($M28="",$M28="ERR",$J28="",$K28="",$N28=""),0,IF($N28=0,IF(AND(OR(8=7,8=12),8>=$K28,8<=IF($L28="",12,$L28)),$J28,0),IF(AND(8>=$K28,8<=IF($L28="",12,$L28),MOD(8-$K28,$N28)=0),$J28,0))) -> 15000 | W28: =IF(OR($M28="",$M28="ERR",$J28="",$K28="",$N28=""),0,IF($N28=0,IF(AND(OR(9=7,9=12),9>=$K28,9<=IF($L28="",12,$L28)),$J28,0),IF(AND(9>=$K28,9<=IF($L28="",12,$L28),MOD(9-$K28,$N28)=0),$J28,0))) -> 15000 | X28: =IF(OR($M28="",$M28="ERR",$J28="",$K28="",$N28=""),0,IF($N28=0,IF(AND(OR(10=7,10=12),10>=$K28,10<=IF($L28="",12,$L28)),$J28,0),IF(AND(10>=$K28,10<=IF($L28="",12,$L28),MOD(10-$K28,$N28)=0),$J28,0))) -> 0 | Y28: =IF(OR($M28="",$M28="ERR",$J28="",$K28="",$N28=""),0,IF($N28=0,IF(AND(OR(11=7,11=12),11>=$K28,11<=IF($L28="",12,$L28)),$J28,0),IF(AND(11>=$K28,11<=IF($L28="",12,$L28),MOD(11-$K28,$N28)=0),$J28,0))) -> 0 | Z28: =IF(OR($M28="",$M28="ERR",$J28="",$K28="",$N28=""),0,IF($N28=0,IF(AND(OR(12=7,12=12),12>=$K28,12<=IF($L28="",12,$L28)),$J28,0),IF(AND(12>=$K28,12<=IF($L28="",12,$L28),MOD(12-$K28,$N28)=0),$J28,0))) -> 0 | AA28: =SUM(O28:Z28) -> 135000 | AB28: =IF(AND($B28="",$D28="",$J28=""),"",IF($B28="","Falta código",IF(ISNA(MATCH($B28,LST_COD,0)),"Código no registrado en Trabajadores",IF($E28="","Concepto no está en el catálogo",IF($M28="ERR","Retención de otro empleador: Origen = Otro empleador",IF(OR($J28="",$K28=""),"Falta monto o mes",IF(OR($K28<1,$K28>12),"Mes inicio inválido",IF(AND($L28<>"",OR($L28<$K28,$L28>12)),"Mes fin inválido",IF($N28="","Falta frecuencia",IF(AND($G28<>"Otro empleador",SUMPRODUCT(($O28:$Z28<>0)*(((COLUMN($O28:$Z28)-14)<INDEX(Trabajadores!$M$6:$M$105,MATCH($B28,LST_COD,0)))+((COLUMN($O28:$Z28)-14)>INDEX(Trabajadores!$N$6:$N$105,MATCH($B28,LST_COD,0)))))>0),"Aviso: hay meses fuera del periodo laboral","OK")))))))))) -> OK
A29: 24 | B29: EJ-003 | C29: =IF($B29="","",IFERROR(INDEX(Trabajadores!$D$6:$D$105,MATCH($B29,LST_COD,0)),"¿Código?")) -> TORRES ROJAS, MARÍA (EJEMPLO) | D29: Gratificación ordinaria (Fiestas Patrias / Navidad) | E29: =IF($D29="","",IFERROR(VLOOKUP($D29,CONC_TABLA,2,FALSE()),"")) -> GRA | F29: =IF($D29="","",IFERROR(VLOOKUP($D29,CONC_TABLA,3,FALSE()),"")) -> No | G29: Empresa principal | I29: Pago único | J29: 15000 | K29: 7 | M29: =IF(OR($B29="",$E29=""),"",IF($E29="INA","INA",IF($G29="Otro empleador",IF($E29="RET","RETO",IF($E29="ORD","OTO","OTX")),IF($E29="RET","ERR",$E29)))) -> GRA | N29: =IF($I29="","",IFERROR(VLOOKUP($I29,FREC_TABLA,2,FALSE()),"")) -> 12 | O29: =IF(OR($M29="",$M29="ERR",$J29="",$K29="",$N29=""),0,IF($N29=0,IF(AND(OR(1=7,1=12),1>=$K29,1<=IF($L29="",12,$L29)),$J29,0),IF(AND(1>=$K29,1<=IF($L29="",12,$L29),MOD(1-$K29,$N29)=0),$J29,0))) -> 0 | P29: =IF(OR($M29="",$M29="ERR",$J29="",$K29="",$N29=""),0,IF($N29=0,IF(AND(OR(2=7,2=12),2>=$K29,2<=IF($L29="",12,$L29)),$J29,0),IF(AND(2>=$K29,2<=IF($L29="",12,$L29),MOD(2-$K29,$N29)=0),$J29,0))) -> 0 | Q29: =IF(OR($M29="",$M29="ERR",$J29="",$K29="",$N29=""),0,IF($N29=0,IF(AND(OR(3=7,3=12),3>=$K29,3<=IF($L29="",12,$L29)),$J29,0),IF(AND(3>=$K29,3<=IF($L29="",12,$L29),MOD(3-$K29,$N29)=0),$J29,0))) -> 0 | R29: =IF(OR($M29="",$M29="ERR",$J29="",$K29="",$N29=""),0,IF($N29=0,IF(AND(OR(4=7,4=12),4>=$K29,4<=IF($L29="",12,$L29)),$J29,0),IF(AND(4>=$K29,4<=IF($L29="",12,$L29),MOD(4-$K29,$N29)=0),$J29,0))) -> 0 | S29: =IF(OR($M29="",$M29="ERR",$J29="",$K29="",$N29=""),0,IF($N29=0,IF(AND(OR(5=7,5=12),5>=$K29,5<=IF($L29="",12,$L29)),$J29,0),IF(AND(5>=$K29,5<=IF($L29="",12,$L29),MOD(5-$K29,$N29)=0),$J29,0))) -> 0 | T29: =IF(OR($M29="",$M29="ERR",$J29="",$K29="",$N29=""),0,IF($N29=0,IF(AND(OR(6=7,6=12),6>=$K29,6<=IF($L29="",12,$L29)),$J29,0),IF(AND(6>=$K29,6<=IF($L29="",12,$L29),MOD(6-$K29,$N29)=0),$J29,0))) -> 0 | U29: =IF(OR($M29="",$M29="ERR",$J29="",$K29="",$N29=""),0,IF($N29=0,IF(AND(OR(7=7,7=12),7>=$K29,7<=IF($L29="",12,$L29)),$J29,0),IF(AND(7>=$K29,7<=IF($L29="",12,$L29),MOD(7-$K29,$N29)=0),$J29,0))) -> 15000 | V29: =IF(OR($M29="",$M29="ERR",$J29="",$K29="",$N29=""),0,IF($N29=0,IF(AND(OR(8=7,8=12),8>=$K29,8<=IF($L29="",12,$L29)),$J29,0),IF(AND(8>=$K29,8<=IF($L29="",12,$L29),MOD(8-$K29,$N29)=0),$J29,0))) -> 0 | W29: =IF(OR($M29="",$M29="ERR",$J29="",$K29="",$N29=""),0,IF($N29=0,IF(AND(OR(9=7,9=12),9>=$K29,9<=IF($L29="",12,$L29)),$J29,0),IF(AND(9>=$K29,9<=IF($L29="",12,$L29),MOD(9-$K29,$N29)=0),$J29,0))) -> 0 | X29: =IF(OR($M29="",$M29="ERR",$J29="",$K29="",$N29=""),0,IF($N29=0,IF(AND(OR(10=7,10=12),10>=$K29,10<=IF($L29="",12,$L29)),$J29,0),IF(AND(10>=$K29,10<=IF($L29="",12,$L29),MOD(10-$K29,$N29)=0),$J29,0))) -> 0 | Y29: =IF(OR($M29="",$M29="ERR",$J29="",$K29="",$N29=""),0,IF($N29=0,IF(AND(OR(11=7,11=12),11>=$K29,11<=IF($L29="",12,$L29)),$J29,0),IF(AND(11>=$K29,11<=IF($L29="",12,$L29),MOD(11-$K29,$N29)=0),$J29,0))) -> 0 | Z29: =IF(OR($M29="",$M29="ERR",$J29="",$K29="",$N29=""),0,IF($N29=0,IF(AND(OR(12=7,12=12),12>=$K29,12<=IF($L29="",12,$L29)),$J29,0),IF(AND(12>=$K29,12<=IF($L29="",12,$L29),MOD(12-$K29,$N29)=0),$J29,0))) -> 0 | AA29: =SUM(O29:Z29) -> 15000 | AB29: =IF(AND($B29="",$D29="",$J29=""),"",IF($B29="","Falta código",IF(ISNA(MATCH($B29,LST_COD,0)),"Código no registrado en Trabajadores",IF($E29="","Concepto no está en el catálogo",IF($M29="ERR","Retención de otro empleador: Origen = Otro empleador",IF(OR($J29="",$K29=""),"Falta monto o mes",IF(OR($K29<1,$K29>12),"Mes inicio inválido",IF(AND($L29<>"",OR($L29<$K29,$L29>12)),"Mes fin inválido",IF($N29="","Falta frecuencia",IF(AND($G29<>"Otro empleador",SUMPRODUCT(($O29:$Z29<>0)*(((COLUMN($O29:$Z29)-14)<INDEX(Trabajadores!$M$6:$M$105,MATCH($B29,LST_COD,0)))+((COLUMN($O29:$Z29)-14)>INDEX(Trabajadores!$N$6:$N$105,MATCH($B29,LST_COD,0)))))>0),"Aviso: hay meses fuera del periodo laboral","OK")))))))))) -> OK
A30: 25 | B30: EJ-003 | C30: =IF($B30="","",IFERROR(INDEX(Trabajadores!$D$6:$D$105,MATCH($B30,LST_COD,0)),"¿Código?")) -> TORRES ROJAS, MARÍA (EJEMPLO) | D30: Bonificación extraordinaria Ley 30334 (9% / 6.75%) | E30: =IF($D30="","",IFERROR(VLOOKUP($D30,CONC_TABLA,2,FALSE()),"")) -> BON | F30: =IF($D30="","",IFERROR(VLOOKUP($D30,CONC_TABLA,3,FALSE()),"")) -> No | G30: Empresa principal | I30: Pago único | J30: 1012.5 | K30: 7 | M30: =IF(OR($B30="",$E30=""),"",IF($E30="INA","INA",IF($G30="Otro empleador",IF($E30="RET","RETO",IF($E30="ORD","OTO","OTX")),IF($E30="RET","ERR",$E30)))) -> BON | N30: =IF($I30="","",IFERROR(VLOOKUP($I30,FREC_TABLA,2,FALSE()),"")) -> 12 | O30: =IF(OR($M30="",$M30="ERR",$J30="",$K30="",$N30=""),0,IF($N30=0,IF(AND(OR(1=7,1=12),1>=$K30,1<=IF($L30="",12,$L30)),$J30,0),IF(AND(1>=$K30,1<=IF($L30="",12,$L30),MOD(1-$K30,$N30)=0),$J30,0))) -> 0 | P30: =IF(OR($M30="",$M30="ERR",$J30="",$K30="",$N30=""),0,IF($N30=0,IF(AND(OR(2=7,2=12),2>=$K30,2<=IF($L30="",12,$L30)),$J30,0),IF(AND(2>=$K30,2<=IF($L30="",12,$L30),MOD(2-$K30,$N30)=0),$J30,0))) -> 0 | Q30: =IF(OR($M30="",$M30="ERR",$J30="",$K30="",$N30=""),0,IF($N30=0,IF(AND(OR(3=7,3=12),3>=$K30,3<=IF($L30="",12,$L30)),$J30,0),IF(AND(3>=$K30,3<=IF($L30="",12,$L30),MOD(3-$K30,$N30)=0),$J30,0))) -> 0 | R30: =IF(OR($M30="",$M30="ERR",$J30="",$K30="",$N30=""),0,IF($N30=0,IF(AND(OR(4=7,4=12),4>=$K30,4<=IF($L30="",12,$L30)),$J30,0),IF(AND(4>=$K30,4<=IF($L30="",12,$L30),MOD(4-$K30,$N30)=0),$J30,0))) -> 0 | S30: =IF(OR($M30="",$M30="ERR",$J30="",$K30="",$N30=""),0,IF($N30=0,IF(AND(OR(5=7,5=12),5>=$K30,5<=IF($L30="",12,$L30)),$J30,0),IF(AND(5>=$K30,5<=IF($L30="",12,$L30),MOD(5-$K30,$N30)=0),$J30,0))) -> 0 | T30: =IF(OR($M30="",$M30="ERR",$J30="",$K30="",$N30=""),0,IF($N30=0,IF(AND(OR(6=7,6=12),6>=$K30,6<=IF($L30="",12,$L30)),$J30,0),IF(AND(6>=$K30,6<=IF($L30="",12,$L30),MOD(6-$K30,$N30)=0),$J30,0))) -> 0 | U30: =IF(OR($M30="",$M30="ERR",$J30="",$K30="",$N30=""),0,IF($N30=0,IF(AND(OR(7=7,7=12),7>=$K30,7<=IF($L30="",12,$L30)),$J30,0),IF(AND(7>=$K30,7<=IF($L30="",12,$L30),MOD(7-$K30,$N30)=0),$J30,0))) -> 1012.5 | V30: =IF(OR($M30="",$M30="ERR",$J30="",$K30="",$N30=""),0,IF($N30=0,IF(AND(OR(8=7,8=12),8>=$K30,8<=IF($L30="",12,$L30)),$J30,0),IF(AND(8>=$K30,8<=IF($L30="",12,$L30),MOD(8-$K30,$N30)=0),$J30,0))) -> 0 | W30: =IF(OR($M30="",$M30="ERR",$J30="",$K30="",$N30=""),0,IF($N30=0,IF(AND(OR(9=7,9=12),9>=$K30,9<=IF($L30="",12,$L30)),$J30,0),IF(AND(9>=$K30,9<=IF($L30="",12,$L30),MOD(9-$K30,$N30)=0),$J30,0))) -> 0 | X30: =IF(OR($M30="",$M30="ERR",$J30="",$K30="",$N30=""),0,IF($N30=0,IF(AND(OR(10=7,10=12),10>=$K30,10<=IF($L30="",12,$L30)),$J30,0),IF(AND(10>=$K30,10<=IF($L30="",12,$L30),MOD(10-$K30,$N30)=0),$J30,0))) -> 0 | Y30: =IF(OR($M30="",$M30="ERR",$J30="",$K30="",$N30=""),0,IF($N30=0,IF(AND(OR(11=7,11=12),11>=$K30,11<=IF($L30="",12,$L30)),$J30,0),IF(AND(11>=$K30,11<=IF($L30="",12,$L30),MOD(11-$K30,$N30)=0),$J30,0))) -> 0 | Z30: =IF(OR($M30="",$M30="ERR",$J30="",$K30="",$N30=""),0,IF($N30=0,IF(AND(OR(12=7,12=12),12>=$K30,12<=IF($L30="",12,$L30)),$J30,0),IF(AND(12>=$K30,12<=IF($L30="",12,$L30),MOD(12-$K30,$N30)=0),$J30,0))) -> 0 | AA30: =SUM(O30:Z30) -> 1012.5 | AB30: =IF(AND($B30="",$D30="",$J30=""),"",IF($B30="","Falta código",IF(ISNA(MATCH($B30,LST_COD,0)),"Código no registrado en Trabajadores",IF($E30="","Concepto no está en el catálogo",IF($M30="ERR","Retención de otro empleador: Origen = Otro empleador",IF(OR($J30="",$K30=""),"Falta monto o mes",IF(OR($K30<1,$K30>12),"Mes inicio inválido",IF(AND($L30<>"",OR($L30<$K30,$L30>12)),"Mes fin inválido",IF($N30="","Falta frecuencia",IF(AND($G30<>"Otro empleador",SUMPRODUCT(($O30:$Z30<>0)*(((COLUMN($O30:$Z30)-14)<INDEX(Trabajadores!$M$6:$M$105,MATCH($B30,LST_COD,0)))+((COLUMN($O30:$Z30)-14)>INDEX(Trabajadores!$N$6:$N$105,MATCH($B30,LST_COD,0)))))>0),"Aviso: hay meses fuera del periodo laboral","OK")))))))))) -> OK
A31: 26 | B31: EJ-003 | C31: =IF($B31="","",IFERROR(INDEX(Trabajadores!$D$6:$D$105,MATCH($B31,LST_COD,0)),"¿Código?")) -> TORRES ROJAS, MARÍA (EJEMPLO) | D31: Remuneración de otro empleador (total del mes) | E31: =IF($D31="","",IFERROR(VLOOKUP($D31,CONC_TABLA,2,FALSE()),"")) -> ORD | F31: =IF($D31="","",IFERROR(VLOOKUP($D31,CONC_TABLA,3,FALSE()),"")) -> No | G31: Otro empleador | H31: 20222222222 – CONSULTORA ANDINA S.A.C. | I31: Mensual | J31: 4000 | K31: 1 | L31: 12 | M31: =IF(OR($B31="",$E31=""),"",IF($E31="INA","INA",IF($G31="Otro empleador",IF($E31="RET","RETO",IF($E31="ORD","OTO","OTX")),IF($E31="RET","ERR",$E31)))) -> OTO | N31: =IF($I31="","",IFERROR(VLOOKUP($I31,FREC_TABLA,2,FALSE()),"")) -> 1 | O31: =IF(OR($M31="",$M31="ERR",$J31="",$K31="",$N31=""),0,IF($N31=0,IF(AND(OR(1=7,1=12),1>=$K31,1<=IF($L31="",12,$L31)),$J31,0),IF(AND(1>=$K31,1<=IF($L31="",12,$L31),MOD(1-$K31,$N31)=0),$J31,0))) -> 4000 | P31: =IF(OR($M31="",$M31="ERR",$J31="",$K31="",$N31=""),0,IF($N31=0,IF(AND(OR(2=7,2=12),2>=$K31,2<=IF($L31="",12,$L31)),$J31,0),IF(AND(2>=$K31,2<=IF($L31="",12,$L31),MOD(2-$K31,$N31)=0),$J31,0))) -> 4000 | Q31: =IF(OR($M31="",$M31="ERR",$J31="",$K31="",$N31=""),0,IF($N31=0,IF(AND(OR(3=7,3=12),3>=$K31,3<=IF($L31="",12,$L31)),$J31,0),IF(AND(3>=$K31,3<=IF($L31="",12,$L31),MOD(3-$K31,$N31)=0),$J31,0))) -> 4000 | R31: =IF(OR($M31="",$M31="ERR",$J31="",$K31="",$N31=""),0,IF($N31=0,IF(AND(OR(4=7,4=12),4>=$K31,4<=IF($L31="",12,$L31)),$J31,0),IF(AND(4>=$K31,4<=IF($L31="",12,$L31),MOD(4-$K31,$N31)=0),$J31,0))) -> 4000 | S31: =IF(OR($M31="",$M31="ERR",$J31="",$K31="",$N31=""),0,IF($N31=0,IF(AND(OR(5=7,5=12),5>=$K31,5<=IF($L31="",12,$L31)),$J31,0),IF(AND(5>=$K31,5<=IF($L31="",12,$L31),MOD(5-$K31,$N31)=0),$J31,0))) -> 4000 | T31: =IF(OR($M31="",$M31="ERR",$J31="",$K31="",$N31=""),0,IF($N31=0,IF(AND(OR(6=7,6=12),6>=$K31,6<=IF($L31="",12,$L31)),$J31,0),IF(AND(6>=$K31,6<=IF($L31="",12,$L31),MOD(6-$K31,$N31)=0),$J31,0))) -> 4000 | U31: =IF(OR($M31="",$M31="ERR",$J31="",$K31="",$N31=""),0,IF($N31=0,IF(AND(OR(7=7,7=12),7>=$K31,7<=IF($L31="",12,$L31)),$J31,0),IF(AND(7>=$K31,7<=IF($L31="",12,$L31),MOD(7-$K31,$N31)=0),$J31,0))) -> 4000 | V31: =IF(OR($M31="",$M31="ERR",$J31="",$K31="",$N31=""),0,IF($N31=0,IF(AND(OR(8=7,8=12),8>=$K31,8<=IF($L31="",12,$L31)),$J31,0),IF(AND(8>=$K31,8<=IF($L31="",12,$L31),MOD(8-$K31,$N31)=0),$J31,0))) -> 4000 | W31: =IF(OR($M31="",$M31="ERR",$J31="",$K31="",$N31=""),0,IF($N31=0,IF(AND(OR(9=7,9=12),9>=$K31,9<=IF($L31="",12,$L31)),$J31,0),IF(AND(9>=$K31,9<=IF($L31="",12,$L31),MOD(9-$K31,$N31)=0),$J31,0))) -> 4000 | X31: =IF(OR($M31="",$M31="ERR",$J31="",$K31="",$N31=""),0,IF($N31=0,IF(AND(OR(10=7,10=12),10>=$K31,10<=IF($L31="",12,$L31)),$J31,0),IF(AND(10>=$K31,10<=IF($L31="",12,$L31),MOD(10-$K31,$N31)=0),$J31,0))) -> 4000 | Y31: =IF(OR($M31="",$M31="ERR",$J31="",$K31="",$N31=""),0,IF($N31=0,IF(AND(OR(11=7,11=12),11>=$K31,11<=IF($L31="",12,$L31)),$J31,0),IF(AND(11>=$K31,11<=IF($L31="",12,$L31),MOD(11-$K31,$N31)=0),$J31,0))) -> 4000 | Z31: =IF(OR($M31="",$M31="ERR",$J31="",$K31="",$N31=""),0,IF($N31=0,IF(AND(OR(12=7,12=12),12>=$K31,12<=IF($L31="",12,$L31)),$J31,0),IF(AND(12>=$K31,12<=IF($L31="",12,$L31),MOD(12-$K31,$N31)=0),$J31,0))) -> 4000 | AA31: =SUM(O31:Z31) -> 48000 | AB31: =IF(AND($B31="",$D31="",$J31=""),"",IF($B31="","Falta código",IF(ISNA(MATCH($B31,LST_COD,0)),"Código no registrado en Trabajadores",IF($E31="","Concepto no está en el catálogo",IF($M31="ERR","Retención de otro empleador: Origen = Otro empleador",IF(OR($J31="",$K31=""),"Falta monto o mes",IF(OR($K31<1,$K31>12),"Mes inicio inválido",IF(AND($L31<>"",OR($L31<$K31,$L31>12)),"Mes fin inválido",IF($N31="","Falta frecuencia",IF(AND($G31<>"Otro empleador",SUMPRODUCT(($O31:$Z31<>0)*(((COLUMN($O31:$Z31)-14)<INDEX(Trabajadores!$M$6:$M$105,MATCH($B31,LST_COD,0)))+((COLUMN($O31:$Z31)-14)>INDEX(Trabajadores!$N$6:$N$105,MATCH($B31,LST_COD,0)))))>0),"Aviso: hay meses fuera del periodo laboral","OK")))))))))) -> OK
A32: 27 | B32: EJ-003 | C32: =IF($B32="","",IFERROR(INDEX(Trabajadores!$D$6:$D$105,MATCH($B32,LST_COD,0)),"¿Código?")) -> TORRES ROJAS, MARÍA (EJEMPLO) | D32: Gratificación ordinaria (Fiestas Patrias / Navidad) | E32: =IF($D32="","",IFERROR(VLOOKUP($D32,CONC_TABLA,2,FALSE()),"")) -> GRA | F32: =IF($D32="","",IFERROR(VLOOKUP($D32,CONC_TABLA,3,FALSE()),"")) -> No | G32: Otro empleador | H32: 20222222222 – CONSULTORA ANDINA S.A.C. | I32: Julio y Diciembre | J32: 4360 | K32: 1 | L32: 12 | M32: =IF(OR($B32="",$E32=""),"",IF($E32="INA","INA",IF($G32="Otro empleador",IF($E32="RET","RETO",IF($E32="ORD","OTO","OTX")),IF($E32="RET","ERR",$E32)))) -> OTX | N32: =IF($I32="","",IFERROR(VLOOKUP($I32,FREC_TABLA,2,FALSE()),"")) -> 0 | O32: =IF(OR($M32="",$M32="ERR",$J32="",$K32="",$N32=""),0,IF($N32=0,IF(AND(OR(1=7,1=12),1>=$K32,1<=IF($L32="",12,$L32)),$J32,0),IF(AND(1>=$K32,1<=IF($L32="",12,$L32),MOD(1-$K32,$N32)=0),$J32,0))) -> 0 | P32: =IF(OR($M32="",$M32="ERR",$J32="",$K32="",$N32=""),0,IF($N32=0,IF(AND(OR(2=7,2=12),2>=$K32,2<=IF($L32="",12,$L32)),$J32,0),IF(AND(2>=$K32,2<=IF($L32="",12,$L32),MOD(2-$K32,$N32)=0),$J32,0))) -> 0 | Q32: =IF(OR($M32="",$M32="ERR",$J32="",$K32="",$N32=""),0,IF($N32=0,IF(AND(OR(3=7,3=12),3>=$K32,3<=IF($L32="",12,$L32)),$J32,0),IF(AND(3>=$K32,3<=IF($L32="",12,$L32),MOD(3-$K32,$N32)=0),$J32,0))) -> 0 | R32: =IF(OR($M32="",$M32="ERR",$J32="",$K32="",$N32=""),0,IF($N32=0,IF(AND(OR(4=7,4=12),4>=$K32,4<=IF($L32="",12,$L32)),$J32,0),IF(AND(4>=$K32,4<=IF($L32="",12,$L32),MOD(4-$K32,$N32)=0),$J32,0))) -> 0 | S32: =IF(OR($M32="",$M32="ERR",$J32="",$K32="",$N32=""),0,IF($N32=0,IF(AND(OR(5=7,5=12),5>=$K32,5<=IF($L32="",12,$L32)),$J32,0),IF(AND(5>=$K32,5<=IF($L32="",12,$L32),MOD(5-$K32,$N32)=0),$J32,0))) -> 0 | T32: =IF(OR($M32="",$M32="ERR",$J32="",$K32="",$N32=""),0,IF($N32=0,IF(AND(OR(6=7,6=12),6>=$K32,6<=IF($L32="",12,$L32)),$J32,0),IF(AND(6>=$K32,6<=IF($L32="",12,$L32),MOD(6-$K32,$N32)=0),$J32,0))) -> 0 | U32: =IF(OR($M32="",$M32="ERR",$J32="",$K32="",$N32=""),0,IF($N32=0,IF(AND(OR(7=7,7=12),7>=$K32,7<=IF($L32="",12,$L32)),$J32,0),IF(AND(7>=$K32,7<=IF($L32="",12,$L32),MOD(7-$K32,$N32)=0),$J32,0))) -> 4360 | V32: =IF(OR($M32="",$M32="ERR",$J32="",$K32="",$N32=""),0,IF($N32=0,IF(AND(OR(8=7,8=12),8>=$K32,8<=IF($L32="",12,$L32)),$J32,0),IF(AND(8>=$K32,8<=IF($L32="",12,$L32),MOD(8-$K32,$N32)=0),$J32,0))) -> 0 | W32: =IF(OR($M32="",$M32="ERR",$J32="",$K32="",$N32=""),0,IF($N32=0,IF(AND(OR(9=7,9=12),9>=$K32,9<=IF($L32="",12,$L32)),$J32,0),IF(AND(9>=$K32,9<=IF($L32="",12,$L32),MOD(9-$K32,$N32)=0),$J32,0))) -> 0 | X32: =IF(OR($M32="",$M32="ERR",$J32="",$K32="",$N32=""),0,IF($N32=0,IF(AND(OR(10=7,10=12),10>=$K32,10<=IF($L32="",12,$L32)),$J32,0),IF(AND(10>=$K32,10<=IF($L32="",12,$L32),MOD(10-$K32,$N32)=0),$J32,0))) -> 0 | Y32: =IF(OR($M32="",$M32="ERR",$J32="",$K32="",$N32=""),0,IF($N32=0,IF(AND(OR(11=7,11=12),11>=$K32,11<=IF($L32="",12,$L32)),$J32,0),IF(AND(11>=$K32,11<=IF($L32="",12,$L32),MOD(11-$K32,$N32)=0),$J32,0))) -> 0 | Z32: =IF(OR($M32="",$M32="ERR",$J32="",$K32="",$N32=""),0,IF($N32=0,IF(AND(OR(12=7,12=12),12>=$K32,12<=IF($L32="",12,$L32)),$J32,0),IF(AND(12>=$K32,12<=IF($L32="",12,$L32),MOD(12-$K32,$N32)=0),$J32,0))) -> 4360 | AA32: =SUM(O32:Z32) -> 8720 | AB32: =IF(AND($B32="",$D32="",$J32=""),"",IF($B32="","Falta código",IF(ISNA(MATCH($B32,LST_COD,0)),"Código no registrado en Trabajadores",IF($E32="","Concepto no está en el catálogo",IF($M32="ERR","Retención de otro empleador: Origen = Otro empleador",IF(OR($J32="",$K32=""),"Falta monto o mes",IF(OR($K32<1,$K32>12),"Mes inicio inválido",IF(AND($L32<>"",OR($L32<$K32,$L32>12)),"Mes fin inválido",IF($N32="","Falta frecuencia",IF(AND($G32<>"Otro empleador",SUMPRODUCT(($O32:$Z32<>0)*(((COLUMN($O32:$Z32)-14)<INDEX(Trabajadores!$M$6:$M$105,MATCH($B32,LST_COD,0)))+((COLUMN($O32:$Z32)-14)>INDEX(Trabajadores!$N$6:$N$105,MATCH($B32,LST_COD,0)))))>0),"Aviso: hay meses fuera del periodo laboral","OK")))))))))) -> OK
A33: 28 | B33: EJ-003 | C33: =IF($B33="","",IFERROR(INDEX(Trabajadores!$D$6:$D$105,MATCH($B33,LST_COD,0)),"¿Código?")) -> TORRES ROJAS, MARÍA (EJEMPLO) | D33: Gratificación trunca | E33: =IF($D33="","",IFERROR(VLOOKUP($D33,CONC_TABLA,2,FALSE()),"")) -> EXT | F33: =IF($D33="","",IFERROR(VLOOKUP($D33,CONC_TABLA,3,FALSE()),"")) -> No | G33: Empresa principal | I33: Pago único | J33: 8006.25 | K33: 9 | M33: =IF(OR($B33="",$E33=""),"",IF($E33="INA","INA",IF($G33="Otro empleador",IF($E33="RET","RETO",IF($E33="ORD","OTO","OTX")),IF($E33="RET","ERR",$E33)))) -> EXT | N33: =IF($I33="","",IFERROR(VLOOKUP($I33,FREC_TABLA,2,FALSE()),"")) -> 12 | O33: =IF(OR($M33="",$M33="ERR",$J33="",$K33="",$N33=""),0,IF($N33=0,IF(AND(OR(1=7,1=12),1>=$K33,1<=IF($L33="",12,$L33)),$J33,0),IF(AND(1>=$K33,1<=IF($L33="",12,$L33),MOD(1-$K33,$N33)=0),$J33,0))) -> 0 | P33: =IF(OR($M33="",$M33="ERR",$J33="",$K33="",$N33=""),0,IF($N33=0,IF(AND(OR(2=7,2=12),2>=$K33,2<=IF($L33="",12,$L33)),$J33,0),IF(AND(2>=$K33,2<=IF($L33="",12,$L33),MOD(2-$K33,$N33)=0),$J33,0))) -> 0 | Q33: =IF(OR($M33="",$M33="ERR",$J33="",$K33="",$N33=""),0,IF($N33=0,IF(AND(OR(3=7,3=12),3>=$K33,3<=IF($L33="",12,$L33)),$J33,0),IF(AND(3>=$K33,3<=IF($L33="",12,$L33),MOD(3-$K33,$N33)=0),$J33,0))) -> 0 | R33: =IF(OR($M33="",$M33="ERR",$J33="",$K33="",$N33=""),0,IF($N33=0,IF(AND(OR(4=7,4=12),4>=$K33,4<=IF($L33="",12,$L33)),$J33,0),IF(AND(4>=$K33,4<=IF($L33="",12,$L33),MOD(4-$K33,$N33)=0),$J33,0))) -> 0 | S33: =IF(OR($M33="",$M33="ERR",$J33="",$K33="",$N33=""),0,IF($N33=0,IF(AND(OR(5=7,5=12),5>=$K33,5<=IF($L33="",12,$L33)),$J33,0),IF(AND(5>=$K33,5<=IF($L33="",12,$L33),MOD(5-$K33,$N33)=0),$J33,0))) -> 0 | T33: =IF(OR($M33="",$M33="ERR",$J33="",$K33="",$N33=""),0,IF($N33=0,IF(AND(OR(6=7,6=12),6>=$K33,6<=IF($L33="",12,$L33)),$J33,0),IF(AND(6>=$K33,6<=IF($L33="",12,$L33),MOD(6-$K33,$N33)=0),$J33,0))) -> 0 | U33: =IF(OR($M33="",$M33="ERR",$J33="",$K33="",$N33=""),0,IF($N33=0,IF(AND(OR(7=7,7=12),7>=$K33,7<=IF($L33="",12,$L33)),$J33,0),IF(AND(7>=$K33,7<=IF($L33="",12,$L33),MOD(7-$K33,$N33)=0),$J33,0))) -> 0 | V33: =IF(OR($M33="",$M33="ERR",$J33="",$K33="",$N33=""),0,IF($N33=0,IF(AND(OR(8=7,8=12),8>=$K33,8<=IF($L33="",12,$L33)),$J33,0),IF(AND(8>=$K33,8<=IF($L33="",12,$L33),MOD(8-$K33,$N33)=0),$J33,0))) -> 0 | W33: =IF(OR($M33="",$M33="ERR",$J33="",$K33="",$N33=""),0,IF($N33=0,IF(AND(OR(9=7,9=12),9>=$K33,9<=IF($L33="",12,$L33)),$J33,0),IF(AND(9>=$K33,9<=IF($L33="",12,$L33),MOD(9-$K33,$N33)=0),$J33,0))) -> 8006.25 | X33: =IF(OR($M33="",$M33="ERR",$J33="",$K33="",$N33=""),0,IF($N33=0,IF(AND(OR(10=7,10=12),10>=$K33,10<=IF($L33="",12,$L33)),$J33,0),IF(AND(10>=$K33,10<=IF($L33="",12,$L33),MOD(10-$K33,$N33)=0),$J33,0))) -> 0 | Y33: =IF(OR($M33="",$M33="ERR",$J33="",$K33="",$N33=""),0,IF($N33=0,IF(AND(OR(11=7,11=12),11>=$K33,11<=IF($L33="",12,$L33)),$J33,0),IF(AND(11>=$K33,11<=IF($L33="",12,$L33),MOD(11-$K33,$N33)=0),$J33,0))) -> 0 | Z33: =IF(OR($M33="",$M33="ERR",$J33="",$K33="",$N33=""),0,IF($N33=0,IF(AND(OR(12=7,12=12),12>=$K33,12<=IF($L33="",12,$L33)),$J33,0),IF(AND(12>=$K33,12<=IF($L33="",12,$L33),MOD(12-$K33,$N33)=0),$J33,0))) -> 0 | AA33: =SUM(O33:Z33) -> 8006.25 | AB33: =IF(AND($B33="",$D33="",$J33=""),"",IF($B33="","Falta código",IF(ISNA(MATCH($B33,LST_COD,0)),"Código no registrado en Trabajadores",IF($E33="","Concepto no está en el catálogo",IF($M33="ERR","Retención de otro empleador: Origen = Otro empleador",IF(OR($J33="",$K33=""),"Falta monto o mes",IF(OR($K33<1,$K33>12),"Mes inicio inválido",IF(AND($L33<>"",OR($L33<$K33,$L33>12)),"Mes fin inválido",IF($N33="","Falta frecuencia",IF(AND($G33<>"Otro empleador",SUMPRODUCT(($O33:$Z33<>0)*(((COLUMN($O33:$Z33)-14)<INDEX(Trabajadores!$M$6:$M$105,MATCH($B33,LST_COD,0)))+((COLUMN($O33:$Z33)-14)>INDEX(Trabajadores!$N$6:$N$105,MATCH($B33,LST_COD,0)))))>0),"Aviso: hay meses fuera del periodo laboral","OK")))))))))) -> OK
A34: 29 | B34: EJ-003 | C34: =IF($B34="","",IFERROR(INDEX(Trabajadores!$D$6:$D$105,MATCH($B34,LST_COD,0)),"¿Código?")) -> TORRES ROJAS, MARÍA (EJEMPLO) | D34: Vacaciones truncas | E34: =IF($D34="","",IFERROR(VLOOKUP($D34,CONC_TABLA,2,FALSE()),"")) -> EXT | F34: =IF($D34="","",IFERROR(VLOOKUP($D34,CONC_TABLA,3,FALSE()),"")) -> No | G34: Empresa principal | I34: Pago único | J34: 5000 | K34: 9 | M34: =IF(OR($B34="",$E34=""),"",IF($E34="INA","INA",IF($G34="Otro empleador",IF($E34="RET","RETO",IF($E34="ORD","OTO","OTX")),IF($E34="RET","ERR",$E34)))) -> EXT | N34: =IF($I34="","",IFERROR(VLOOKUP($I34,FREC_TABLA,2,FALSE()),"")) -> 12 | O34: =IF(OR($M34="",$M34="ERR",$J34="",$K34="",$N34=""),0,IF($N34=0,IF(AND(OR(1=7,1=12),1>=$K34,1<=IF($L34="",12,$L34)),$J34,0),IF(AND(1>=$K34,1<=IF($L34="",12,$L34),MOD(1-$K34,$N34)=0),$J34,0))) -> 0 | P34: =IF(OR($M34="",$M34="ERR",$J34="",$K34="",$N34=""),0,IF($N34=0,IF(AND(OR(2=7,2=12),2>=$K34,2<=IF($L34="",12,$L34)),$J34,0),IF(AND(2>=$K34,2<=IF($L34="",12,$L34),MOD(2-$K34,$N34)=0),$J34,0))) -> 0 | Q34: =IF(OR($M34="",$M34="ERR",$J34="",$K34="",$N34=""),0,IF($N34=0,IF(AND(OR(3=7,3=12),3>=$K34,3<=IF($L34="",12,$L34)),$J34,0),IF(AND(3>=$K34,3<=IF($L34="",12,$L34),MOD(3-$K34,$N34)=0),$J34,0))) -> 0 | R34: =IF(OR($M34="",$M34="ERR",$J34="",$K34="",$N34=""),0,IF($N34=0,IF(AND(OR(4=7,4=12),4>=$K34,4<=IF($L34="",12,$L34)),$J34,0),IF(AND(4>=$K34,4<=IF($L34="",12,$L34),MOD(4-$K34,$N34)=0),$J34,0))) -> 0 | S34: =IF(OR($M34="",$M34="ERR",$J34="",$K34="",$N34=""),0,IF($N34=0,IF(AND(OR(5=7,5=12),5>=$K34,5<=IF($L34="",12,$L34)),$J34,0),IF(AND(5>=$K34,5<=IF($L34="",12,$L34),MOD(5-$K34,$N34)=0),$J34,0))) -> 0 | T34: =IF(OR($M34="",$M34="ERR",$J34="",$K34="",$N34=""),0,IF($N34=0,IF(AND(OR(6=7,6=12),6>=$K34,6<=IF($L34="",12,$L34)),$J34,0),IF(AND(6>=$K34,6<=IF($L34="",12,$L34),MOD(6-$K34,$N34)=0),$J34,0))) -> 0 | U34: =IF(OR($M34="",$M34="ERR",$J34="",$K34="",$N34=""),0,IF($N34=0,IF(AND(OR(7=7,7=12),7>=$K34,7<=IF($L34="",12,$L34)),$J34,0),IF(AND(7>=$K34,7<=IF($L34="",12,$L34),MOD(7-$K34,$N34)=0),$J34,0))) -> 0 | V34: =IF(OR($M34="",$M34="ERR",$J34="",$K34="",$N34=""),0,IF($N34=0,IF(AND(OR(8=7,8=12),8>=$K34,8<=IF($L34="",12,$L34)),$J34,0),IF(AND(8>=$K34,8<=IF($L34="",12,$L34),MOD(8-$K34,$N34)=0),$J34,0))) -> 0 | W34: =IF(OR($M34="",$M34="ERR",$J34="",$K34="",$N34=""),0,IF($N34=0,IF(AND(OR(9=7,9=12),9>=$K34,9<=IF($L34="",12,$L34)),$J34,0),IF(AND(9>=$K34,9<=IF($L34="",12,$L34),MOD(9-$K34,$N34)=0),$J34,0))) -> 5000 | X34: =IF(OR($M34="",$M34="ERR",$J34="",$K34="",$N34=""),0,IF($N34=0,IF(AND(OR(10=7,10=12),10>=$K34,10<=IF($L34="",12,$L34)),$J34,0),IF(AND(10>=$K34,10<=IF($L34="",12,$L34),MOD(10-$K34,$N34)=0),$J34,0))) -> 0 | Y34: =IF(OR($M34="",$M34="ERR",$J34="",$K34="",$N34=""),0,IF($N34=0,IF(AND(OR(11=7,11=12),11>=$K34,11<=IF($L34="",12,$L34)),$J34,0),IF(AND(11>=$K34,11<=IF($L34="",12,$L34),MOD(11-$K34,$N34)=0),$J34,0))) -> 0 | Z34: =IF(OR($M34="",$M34="ERR",$J34="",$K34="",$N34=""),0,IF($N34=0,IF(AND(OR(12=7,12=12),12>=$K34,12<=IF($L34="",12,$L34)),$J34,0),IF(AND(12>=$K34,12<=IF($L34="",12,$L34),MOD(12-$K34,$N34)=0),$J34,0))) -> 0 | AA34: =SUM(O34:Z34) -> 5000 | AB34: =IF(AND($B34="",$D34="",$J34=""),"",IF($B34="","Falta código",IF(ISNA(MATCH($B34,LST_COD,0)),"Código no registrado en Trabajadores",IF($E34="","Concepto no está en el catálogo",IF($M34="ERR","Retención de otro empleador: Origen = Otro empleador",IF(OR($J34="",$K34=""),"Falta monto o mes",IF(OR($K34<1,$K34>12),"Mes inicio inválido",IF(AND($L34<>"",OR($L34<$K34,$L34>12)),"Mes fin inválido",IF($N34="","Falta frecuencia",IF(AND($G34<>"Otro empleador",SUMPRODUCT(($O34:$Z34<>0)*(((COLUMN($O34:$Z34)-14)<INDEX(Trabajadores!$M$6:$M$105,MATCH($B34,LST_COD,0)))+((COLUMN($O34:$Z34)-14)>INDEX(Trabajadores!$N$6:$N$105,MATCH($B34,LST_COD,0)))))>0),"Aviso: hay meses fuera del periodo laboral","OK")))))))))) -> OK
A35: 30 | B35: EJ-003 | C35: =IF($B35="","",IFERROR(INDEX(Trabajadores!$D$6:$D$105,MATCH($B35,LST_COD,0)),"¿Código?")) -> TORRES ROJAS, MARÍA (EJEMPLO) | D35: CTS – Compensación por tiempo de servicios | E35: =IF($D35="","",IFERROR(VLOOKUP($D35,CONC_TABLA,2,FALSE()),"")) -> INA | F35: =IF($D35="","",IFERROR(VLOOKUP($D35,CONC_TABLA,3,FALSE()),"")) -> No | G35: Empresa principal | I35: Pago único | J35: 8750 | K35: 5 | M35: =IF(OR($B35="",$E35=""),"",IF($E35="INA","INA",IF($G35="Otro empleador",IF($E35="RET","RETO",IF($E35="ORD","OTO","OTX")),IF($E35="RET","ERR",$E35)))) -> INA | N35: =IF($I35="","",IFERROR(VLOOKUP($I35,FREC_TABLA,2,FALSE()),"")) -> 12 | O35: =IF(OR($M35="",$M35="ERR",$J35="",$K35="",$N35=""),0,IF($N35=0,IF(AND(OR(1=7,1=12),1>=$K35,1<=IF($L35="",12,$L35)),$J35,0),IF(AND(1>=$K35,1<=IF($L35="",12,$L35),MOD(1-$K35,$N35)=0),$J35,0))) -> 0 | P35: =IF(OR($M35="",$M35="ERR",$J35="",$K35="",$N35=""),0,IF($N35=0,IF(AND(OR(2=7,2=12),2>=$K35,2<=IF($L35="",12,$L35)),$J35,0),IF(AND(2>=$K35,2<=IF($L35="",12,$L35),MOD(2-$K35,$N35)=0),$J35,0))) -> 0 | Q35: =IF(OR($M35="",$M35="ERR",$J35="",$K35="",$N35=""),0,IF($N35=0,IF(AND(OR(3=7,3=12),3>=$K35,3<=IF($L35="",12,$L35)),$J35,0),IF(AND(3>=$K35,3<=IF($L35="",12,$L35),MOD(3-$K35,$N35)=0),$J35,0))) -> 0 | R35: =IF(OR($M35="",$M35="ERR",$J35="",$K35="",$N35=""),0,IF($N35=0,IF(AND(OR(4=7,4=12),4>=$K35,4<=IF($L35="",12,$L35)),$J35,0),IF(AND(4>=$K35,4<=IF($L35="",12,$L35),MOD(4-$K35,$N35)=0),$J35,0))) -> 0 | S35: =IF(OR($M35="",$M35="ERR",$J35="",$K35="",$N35=""),0,IF($N35=0,IF(AND(OR(5=7,5=12),5>=$K35,5<=IF($L35="",12,$L35)),$J35,0),IF(AND(5>=$K35,5<=IF($L35="",12,$L35),MOD(5-$K35,$N35)=0),$J35,0))) -> 8750 | T35: =IF(OR($M35="",$M35="ERR",$J35="",$K35="",$N35=""),0,IF($N35=0,IF(AND(OR(6=7,6=12),6>=$K35,6<=IF($L35="",12,$L35)),$J35,0),IF(AND(6>=$K35,6<=IF($L35="",12,$L35),MOD(6-$K35,$N35)=0),$J35,0))) -> 0 | U35: =IF(OR($M35="",$M35="ERR",$J35="",$K35="",$N35=""),0,IF($N35=0,IF(AND(OR(7=7,7=12),7>=$K35,7<=IF($L35="",12,$L35)),$J35,0),IF(AND(7>=$K35,7<=IF($L35="",12,$L35),MOD(7-$K35,$N35)=0),$J35,0))) -> 0 | V35: =IF(OR($M35="",$M35="ERR",$J35="",$K35="",$N35=""),0,IF($N35=0,IF(AND(OR(8=7,8=12),8>=$K35,8<=IF($L35="",12,$L35)),$J35,0),IF(AND(8>=$K35,8<=IF($L35="",12,$L35),MOD(8-$K35,$N35)=0),$J35,0))) -> 0 | W35: =IF(OR($M35="",$M35="ERR",$J35="",$K35="",$N35=""),0,IF($N35=0,IF(AND(OR(9=7,9=12),9>=$K35,9<=IF($L35="",12,$L35)),$J35,0),IF(AND(9>=$K35,9<=IF($L35="",12,$L35),MOD(9-$K35,$N35)=0),$J35,0))) -> 0 | X35: =IF(OR($M35="",$M35="ERR",$J35="",$K35="",$N35=""),0,IF($N35=0,IF(AND(OR(10=7,10=12),10>=$K35,10<=IF($L35="",12,$L35)),$J35,0),IF(AND(10>=$K35,10<=IF($L35="",12,$L35),MOD(10-$K35,$N35)=0),$J35,0))) -> 0 | Y35: =IF(OR($M35="",$M35="ERR",$J35="",$K35="",$N35=""),0,IF($N35=0,IF(AND(OR(11=7,11=12),11>=$K35,11<=IF($L35="",12,$L35)),$J35,0),IF(AND(11>=$K35,11<=IF($L35="",12,$L35),MOD(11-$K35,$N35)=0),$J35,0))) -> 0 | Z35: =IF(OR($M35="",$M35="ERR",$J35="",$K35="",$N35=""),0,IF($N35=0,IF(AND(OR(12=7,12=12),12>=$K35,12<=IF($L35="",12,$L35)),$J35,0),IF(AND(12>=$K35,12<=IF($L35="",12,$L35),MOD(12-$K35,$N35)=0),$J35,0))) -> 0 | AA35: =SUM(O35:Z35) -> 8750 | AB35: =IF(AND($B35="",$D35="",$J35=""),"",IF($B35="","Falta código",IF(ISNA(MATCH($B35,LST_COD,0)),"Código no registrado en Trabajadores",IF($E35="","Concepto no está en el catálogo",IF($M35="ERR","Retención de otro empleador: Origen = Otro empleador",IF(OR($J35="",$K35=""),"Falta monto o mes",IF(OR($K35<1,$K35>12),"Mes inicio inválido",IF(AND($L35<>"",OR($L35<$K35,$L35>12)),"Mes fin inválido",IF($N35="","Falta frecuencia",IF(AND($G35<>"Otro empleador",SUMPRODUCT(($O35:$Z35<>0)*(((COLUMN($O35:$Z35)-14)<INDEX(Trabajadores!$M$6:$M$105,MATCH($B35,LST_COD,0)))+((COLUMN($O35:$Z35)-14)>INDEX(Trabajadores!$N$6:$N$105,MATCH($B35,LST_COD,0)))))>0),"Aviso: hay meses fuera del periodo laboral","OK")))))))))) -> OK
A36: 31 | B36: EJ-003 | C36: =IF($B36="","",IFERROR(INDEX(Trabajadores!$D$6:$D$105,MATCH($B36,LST_COD,0)),"¿Código?")) -> TORRES ROJAS, MARÍA (EJEMPLO) | D36: CTS – Compensación por tiempo de servicios | E36: =IF($D36="","",IFERROR(VLOOKUP($D36,CONC_TABLA,2,FALSE()),"")) -> INA | F36: =IF($D36="","",IFERROR(VLOOKUP($D36,CONC_TABLA,3,FALSE()),"")) -> No | G36: Empresa principal | I36: Pago único | J36: 6250 | K36: 9 | M36: =IF(OR($B36="",$E36=""),"",IF($E36="INA","INA",IF($G36="Otro empleador",IF($E36="RET","RETO",IF($E36="ORD","OTO","OTX")),IF($E36="RET","ERR",$E36)))) -> INA | N36: =IF($I36="","",IFERROR(VLOOKUP($I36,FREC_TABLA,2,FALSE()),"")) -> 12 | O36: =IF(OR($M36="",$M36="ERR",$J36="",$K36="",$N36=""),0,IF($N36=0,IF(AND(OR(1=7,1=12),1>=$K36,1<=IF($L36="",12,$L36)),$J36,0),IF(AND(1>=$K36,1<=IF($L36="",12,$L36),MOD(1-$K36,$N36)=0),$J36,0))) -> 0 | P36: =IF(OR($M36="",$M36="ERR",$J36="",$K36="",$N36=""),0,IF($N36=0,IF(AND(OR(2=7,2=12),2>=$K36,2<=IF($L36="",12,$L36)),$J36,0),IF(AND(2>=$K36,2<=IF($L36="",12,$L36),MOD(2-$K36,$N36)=0),$J36,0))) -> 0 | Q36: =IF(OR($M36="",$M36="ERR",$J36="",$K36="",$N36=""),0,IF($N36=0,IF(AND(OR(3=7,3=12),3>=$K36,3<=IF($L36="",12,$L36)),$J36,0),IF(AND(3>=$K36,3<=IF($L36="",12,$L36),MOD(3-$K36,$N36)=0),$J36,0))) -> 0 | R36: =IF(OR($M36="",$M36="ERR",$J36="",$K36="",$N36=""),0,IF($N36=0,IF(AND(OR(4=7,4=12),4>=$K36,4<=IF($L36="",12,$L36)),$J36,0),IF(AND(4>=$K36,4<=IF($L36="",12,$L36),MOD(4-$K36,$N36)=0),$J36,0))) -> 0 | S36: =IF(OR($M36="",$M36="ERR",$J36="",$K36="",$N36=""),0,IF($N36=0,IF(AND(OR(5=7,5=12),5>=$K36,5<=IF($L36="",12,$L36)),$J36,0),IF(AND(5>=$K36,5<=IF($L36="",12,$L36),MOD(5-$K36,$N36)=0),$J36,0))) -> 0 | T36: =IF(OR($M36="",$M36="ERR",$J36="",$K36="",$N36=""),0,IF($N36=0,IF(AND(OR(6=7,6=12),6>=$K36,6<=IF($L36="",12,$L36)),$J36,0),IF(AND(6>=$K36,6<=IF($L36="",12,$L36),MOD(6-$K36,$N36)=0),$J36,0))) -> 0 | U36: =IF(OR($M36="",$M36="ERR",$J36="",$K36="",$N36=""),0,IF($N36=0,IF(AND(OR(7=7,7=12),7>=$K36,7<=IF($L36="",12,$L36)),$J36,0),IF(AND(7>=$K36,7<=IF($L36="",12,$L36),MOD(7-$K36,$N36)=0),$J36,0))) -> 0 | V36: =IF(OR($M36="",$M36="ERR",$J36="",$K36="",$N36=""),0,IF($N36=0,IF(AND(OR(8=7,8=12),8>=$K36,8<=IF($L36="",12,$L36)),$J36,0),IF(AND(8>=$K36,8<=IF($L36="",12,$L36),MOD(8-$K36,$N36)=0),$J36,0))) -> 0 | W36: =IF(OR($M36="",$M36="ERR",$J36="",$K36="",$N36=""),0,IF($N36=0,IF(AND(OR(9=7,9=12),9>=$K36,9<=IF($L36="",12,$L36)),$J36,0),IF(AND(9>=$K36,9<=IF($L36="",12,$L36),MOD(9-$K36,$N36)=0),$J36,0))) -> 6250 | X36: =IF(OR($M36="",$M36="ERR",$J36="",$K36="",$N36=""),0,IF($N36=0,IF(AND(OR(10=7,10=12),10>=$K36,10<=IF($L36="",12,$L36)),$J36,0),IF(AND(10>=$K36,10<=IF($L36="",12,$L36),MOD(10-$K36,$N36)=0),$J36,0))) -> 0 | Y36: =IF(OR($M36="",$M36="ERR",$J36="",$K36="",$N36=""),0,IF($N36=0,IF(AND(OR(11=7,11=12),11>=$K36,11<=IF($L36="",12,$L36)),$J36,0),IF(AND(11>=$K36,11<=IF($L36="",12,$L36),MOD(11-$K36,$N36)=0),$J36,0))) -> 0 | Z36: =IF(OR($M36="",$M36="ERR",$J36="",$K36="",$N36=""),0,IF($N36=0,IF(AND(OR(12=7,12=12),12>=$K36,12<=IF($L36="",12,$L36)),$J36,0),IF(AND(12>=$K36,12<=IF($L36="",12,$L36),MOD(12-$K36,$N36)=0),$J36,0))) -> 0 | AA36: =SUM(O36:Z36) -> 6250 | AB36: =IF(AND($B36="",$D36="",$J36=""),"",IF($B36="","Falta código",IF(ISNA(MATCH($B36,LST_COD,0)),"Código no registrado en Trabajadores",IF($E36="","Concepto no está en el catálogo",IF($M36="ERR","Retención de otro empleador: Origen = Otro empleador",IF(OR($J36="",$K36=""),"Falta monto o mes",IF(OR($K36<1,$K36>12),"Mes inicio inválido",IF(AND($L36<>"",OR($L36<$K36,$L36>12)),"Mes fin inválido",IF($N36="","Falta frecuencia",IF(AND($G36<>"Otro empleador",SUMPRODUCT(($O36:$Z36<>0)*(((COLUMN($O36:$Z36)-14)<INDEX(Trabajadores!$M$6:$M$105,MATCH($B36,LST_COD,0)))+((COLUMN($O36:$Z36)-14)>INDEX(Trabajadores!$N$6:$N$105,MATCH($B36,LST_COD,0)))))>0),"Aviso: hay meses fuera del periodo laboral","OK")))))))))) -> OK
A37: 32 | B37: EJ-004 | C37: =IF($B37="","",IFERROR(INDEX(Trabajadores!$D$6:$D$105,MATCH($B37,LST_COD,0)),"¿Código?")) -> SALAZAR VEGA, CARLOS (EJEMPLO) | D37: Remuneración básica / sueldo | E37: =IF($D37="","",IFERROR(VLOOKUP($D37,CONC_TABLA,2,FALSE()),"")) -> ORD | F37: =IF($D37="","",IFERROR(VLOOKUP($D37,CONC_TABLA,3,FALSE()),"")) -> Sí | G37: Empresa principal | I37: Mensual | J37: 35000 | K37: 1 | L37: 12 | M37: =IF(OR($B37="",$E37=""),"",IF($E37="INA","INA",IF($G37="Otro empleador",IF($E37="RET","RETO",IF($E37="ORD","OTO","OTX")),IF($E37="RET","ERR",$E37)))) -> ORD | N37: =IF($I37="","",IFERROR(VLOOKUP($I37,FREC_TABLA,2,FALSE()),"")) -> 1 | O37: =IF(OR($M37="",$M37="ERR",$J37="",$K37="",$N37=""),0,IF($N37=0,IF(AND(OR(1=7,1=12),1>=$K37,1<=IF($L37="",12,$L37)),$J37,0),IF(AND(1>=$K37,1<=IF($L37="",12,$L37),MOD(1-$K37,$N37)=0),$J37,0))) -> 35000 | P37: =IF(OR($M37="",$M37="ERR",$J37="",$K37="",$N37=""),0,IF($N37=0,IF(AND(OR(2=7,2=12),2>=$K37,2<=IF($L37="",12,$L37)),$J37,0),IF(AND(2>=$K37,2<=IF($L37="",12,$L37),MOD(2-$K37,$N37)=0),$J37,0))) -> 35000 | Q37: =IF(OR($M37="",$M37="ERR",$J37="",$K37="",$N37=""),0,IF($N37=0,IF(AND(OR(3=7,3=12),3>=$K37,3<=IF($L37="",12,$L37)),$J37,0),IF(AND(3>=$K37,3<=IF($L37="",12,$L37),MOD(3-$K37,$N37)=0),$J37,0))) -> 35000 | R37: =IF(OR($M37="",$M37="ERR",$J37="",$K37="",$N37=""),0,IF($N37=0,IF(AND(OR(4=7,4=12),4>=$K37,4<=IF($L37="",12,$L37)),$J37,0),IF(AND(4>=$K37,4<=IF($L37="",12,$L37),MOD(4-$K37,$N37)=0),$J37,0))) -> 35000 | S37: =IF(OR($M37="",$M37="ERR",$J37="",$K37="",$N37=""),0,IF($N37=0,IF(AND(OR(5=7,5=12),5>=$K37,5<=IF($L37="",12,$L37)),$J37,0),IF(AND(5>=$K37,5<=IF($L37="",12,$L37),MOD(5-$K37,$N37)=0),$J37,0))) -> 35000 | T37: =IF(OR($M37="",$M37="ERR",$J37="",$K37="",$N37=""),0,IF($N37=0,IF(AND(OR(6=7,6=12),6>=$K37,6<=IF($L37="",12,$L37)),$J37,0),IF(AND(6>=$K37,6<=IF($L37="",12,$L37),MOD(6-$K37,$N37)=0),$J37,0))) -> 35000 | U37: =IF(OR($M37="",$M37="ERR",$J37="",$K37="",$N37=""),0,IF($N37=0,IF(AND(OR(7=7,7=12),7>=$K37,7<=IF($L37="",12,$L37)),$J37,0),IF(AND(7>=$K37,7<=IF($L37="",12,$L37),MOD(7-$K37,$N37)=0),$J37,0))) -> 35000 | V37: =IF(OR($M37="",$M37="ERR",$J37="",$K37="",$N37=""),0,IF($N37=0,IF(AND(OR(8=7,8=12),8>=$K37,8<=IF($L37="",12,$L37)),$J37,0),IF(AND(8>=$K37,8<=IF($L37="",12,$L37),MOD(8-$K37,$N37)=0),$J37,0))) -> 35000 | W37: =IF(OR($M37="",$M37="ERR",$J37="",$K37="",$N37=""),0,IF($N37=0,IF(AND(OR(9=7,9=12),9>=$K37,9<=IF($L37="",12,$L37)),$J37,0),IF(AND(9>=$K37,9<=IF($L37="",12,$L37),MOD(9-$K37,$N37)=0),$J37,0))) -> 35000 | X37: =IF(OR($M37="",$M37="ERR",$J37="",$K37="",$N37=""),0,IF($N37=0,IF(AND(OR(10=7,10=12),10>=$K37,10<=IF($L37="",12,$L37)),$J37,0),IF(AND(10>=$K37,10<=IF($L37="",12,$L37),MOD(10-$K37,$N37)=0),$J37,0))) -> 35000 | Y37: =IF(OR($M37="",$M37="ERR",$J37="",$K37="",$N37=""),0,IF($N37=0,IF(AND(OR(11=7,11=12),11>=$K37,11<=IF($L37="",12,$L37)),$J37,0),IF(AND(11>=$K37,11<=IF($L37="",12,$L37),MOD(11-$K37,$N37)=0),$J37,0))) -> 35000 | Z37: =IF(OR($M37="",$M37="ERR",$J37="",$K37="",$N37=""),0,IF($N37=0,IF(AND(OR(12=7,12=12),12>=$K37,12<=IF($L37="",12,$L37)),$J37,0),IF(AND(12>=$K37,12<=IF($L37="",12,$L37),MOD(12-$K37,$N37)=0),$J37,0))) -> 35000 | AA37: =SUM(O37:Z37) -> 420000 | AB37: =IF(AND($B37="",$D37="",$J37=""),"",IF($B37="","Falta código",IF(ISNA(MATCH($B37,LST_COD,0)),"Código no registrado en Trabajadores",IF($E37="","Concepto no está en el catálogo",IF($M37="ERR","Retención de otro empleador: Origen = Otro empleador",IF(OR($J37="",$K37=""),"Falta monto o mes",IF(OR($K37<1,$K37>12),"Mes inicio inválido",IF(AND($L37<>"",OR($L37<$K37,$L37>12)),"Mes fin inválido",IF($N37="","Falta frecuencia",IF(AND($G37<>"Otro empleador",SUMPRODUCT(($O37:$Z37<>0)*(((COLUMN($O37:$Z37)-14)<INDEX(Trabajadores!$M$6:$M$105,MATCH($B37,LST_COD,0)))+((COLUMN($O37:$Z37)-14)>INDEX(Trabajadores!$N$6:$N$105,MATCH($B37,LST_COD,0)))))>0),"Aviso: hay meses fuera del periodo laboral","OK")))))))))) -> OK
A38: 33 | B38: EJ-004 | C38: =IF($B38="","",IFERROR(INDEX(Trabajadores!$D$6:$D$105,MATCH($B38,LST_COD,0)),"¿Código?")) -> SALAZAR VEGA, CARLOS (EJEMPLO) | D38: Gratificación ordinaria (Fiestas Patrias / Navidad) | E38: =IF($D38="","",IFERROR(VLOOKUP($D38,CONC_TABLA,2,FALSE()),"")) -> GRA | F38: =IF($D38="","",IFERROR(VLOOKUP($D38,CONC_TABLA,3,FALSE()),"")) -> No | G38: Empresa principal | I38: Julio y Diciembre | J38: 35000 | K38: 1 | L38: 12 | M38: =IF(OR($B38="",$E38=""),"",IF($E38="INA","INA",IF($G38="Otro empleador",IF($E38="RET","RETO",IF($E38="ORD","OTO","OTX")),IF($E38="RET","ERR",$E38)))) -> GRA | N38: =IF($I38="","",IFERROR(VLOOKUP($I38,FREC_TABLA,2,FALSE()),"")) -> 0 | O38: =IF(OR($M38="",$M38="ERR",$J38="",$K38="",$N38=""),0,IF($N38=0,IF(AND(OR(1=7,1=12),1>=$K38,1<=IF($L38="",12,$L38)),$J38,0),IF(AND(1>=$K38,1<=IF($L38="",12,$L38),MOD(1-$K38,$N38)=0),$J38,0))) -> 0 | P38: =IF(OR($M38="",$M38="ERR",$J38="",$K38="",$N38=""),0,IF($N38=0,IF(AND(OR(2=7,2=12),2>=$K38,2<=IF($L38="",12,$L38)),$J38,0),IF(AND(2>=$K38,2<=IF($L38="",12,$L38),MOD(2-$K38,$N38)=0),$J38,0))) -> 0 | Q38: =IF(OR($M38="",$M38="ERR",$J38="",$K38="",$N38=""),0,IF($N38=0,IF(AND(OR(3=7,3=12),3>=$K38,3<=IF($L38="",12,$L38)),$J38,0),IF(AND(3>=$K38,3<=IF($L38="",12,$L38),MOD(3-$K38,$N38)=0),$J38,0))) -> 0 | R38: =IF(OR($M38="",$M38="ERR",$J38="",$K38="",$N38=""),0,IF($N38=0,IF(AND(OR(4=7,4=12),4>=$K38,4<=IF($L38="",12,$L38)),$J38,0),IF(AND(4>=$K38,4<=IF($L38="",12,$L38),MOD(4-$K38,$N38)=0),$J38,0))) -> 0 | S38: =IF(OR($M38="",$M38="ERR",$J38="",$K38="",$N38=""),0,IF($N38=0,IF(AND(OR(5=7,5=12),5>=$K38,5<=IF($L38="",12,$L38)),$J38,0),IF(AND(5>=$K38,5<=IF($L38="",12,$L38),MOD(5-$K38,$N38)=0),$J38,0))) -> 0 | T38: =IF(OR($M38="",$M38="ERR",$J38="",$K38="",$N38=""),0,IF($N38=0,IF(AND(OR(6=7,6=12),6>=$K38,6<=IF($L38="",12,$L38)),$J38,0),IF(AND(6>=$K38,6<=IF($L38="",12,$L38),MOD(6-$K38,$N38)=0),$J38,0))) -> 0 | U38: =IF(OR($M38="",$M38="ERR",$J38="",$K38="",$N38=""),0,IF($N38=0,IF(AND(OR(7=7,7=12),7>=$K38,7<=IF($L38="",12,$L38)),$J38,0),IF(AND(7>=$K38,7<=IF($L38="",12,$L38),MOD(7-$K38,$N38)=0),$J38,0))) -> 35000 | V38: =IF(OR($M38="",$M38="ERR",$J38="",$K38="",$N38=""),0,IF($N38=0,IF(AND(OR(8=7,8=12),8>=$K38,8<=IF($L38="",12,$L38)),$J38,0),IF(AND(8>=$K38,8<=IF($L38="",12,$L38),MOD(8-$K38,$N38)=0),$J38,0))) -> 0 | W38: =IF(OR($M38="",$M38="ERR",$J38="",$K38="",$N38=""),0,IF($N38=0,IF(AND(OR(9=7,9=12),9>=$K38,9<=IF($L38="",12,$L38)),$J38,0),IF(AND(9>=$K38,9<=IF($L38="",12,$L38),MOD(9-$K38,$N38)=0),$J38,0))) -> 0 | X38: =IF(OR($M38="",$M38="ERR",$J38="",$K38="",$N38=""),0,IF($N38=0,IF(AND(OR(10=7,10=12),10>=$K38,10<=IF($L38="",12,$L38)),$J38,0),IF(AND(10>=$K38,10<=IF($L38="",12,$L38),MOD(10-$K38,$N38)=0),$J38,0))) -> 0 | Y38: =IF(OR($M38="",$M38="ERR",$J38="",$K38="",$N38=""),0,IF($N38=0,IF(AND(OR(11=7,11=12),11>=$K38,11<=IF($L38="",12,$L38)),$J38,0),IF(AND(11>=$K38,11<=IF($L38="",12,$L38),MOD(11-$K38,$N38)=0),$J38,0))) -> 0 | Z38: =IF(OR($M38="",$M38="ERR",$J38="",$K38="",$N38=""),0,IF($N38=0,IF(AND(OR(12=7,12=12),12>=$K38,12<=IF($L38="",12,$L38)),$J38,0),IF(AND(12>=$K38,12<=IF($L38="",12,$L38),MOD(12-$K38,$N38)=0),$J38,0))) -> 35000 | AA38: =SUM(O38:Z38) -> 70000 | AB38: =IF(AND($B38="",$D38="",$J38=""),"",IF($B38="","Falta código",IF(ISNA(MATCH($B38,LST_COD,0)),"Código no registrado en Trabajadores",IF($E38="","Concepto no está en el catálogo",IF($M38="ERR","Retención de otro empleador: Origen = Otro empleador",IF(OR($J38="",$K38=""),"Falta monto o mes",IF(OR($K38<1,$K38>12),"Mes inicio inválido",IF(AND($L38<>"",OR($L38<$K38,$L38>12)),"Mes fin inválido",IF($N38="","Falta frecuencia",IF(AND($G38<>"Otro empleador",SUMPRODUCT(($O38:$Z38<>0)*(((COLUMN($O38:$Z38)-14)<INDEX(Trabajadores!$M$6:$M$105,MATCH($B38,LST_COD,0)))+((COLUMN($O38:$Z38)-14)>INDEX(Trabajadores!$N$6:$N$105,MATCH($B38,LST_COD,0)))))>0),"Aviso: hay meses fuera del periodo laboral","OK")))))))))) -> OK
A39: 34 | B39: EJ-004 | C39: =IF($B39="","",IFERROR(INDEX(Trabajadores!$D$6:$D$105,MATCH($B39,LST_COD,0)),"¿Código?")) -> SALAZAR VEGA, CARLOS (EJEMPLO) | D39: Bonificación extraordinaria Ley 30334 (9% / 6.75%) | E39: =IF($D39="","",IFERROR(VLOOKUP($D39,CONC_TABLA,2,FALSE()),"")) -> BON | F39: =IF($D39="","",IFERROR(VLOOKUP($D39,CONC_TABLA,3,FALSE()),"")) -> No | G39: Empresa principal | I39: Julio y Diciembre | J39: 3150 | K39: 1 | L39: 12 | M39: =IF(OR($B39="",$E39=""),"",IF($E39="INA","INA",IF($G39="Otro empleador",IF($E39="RET","RETO",IF($E39="ORD","OTO","OTX")),IF($E39="RET","ERR",$E39)))) -> BON | N39: =IF($I39="","",IFERROR(VLOOKUP($I39,FREC_TABLA,2,FALSE()),"")) -> 0 | O39: =IF(OR($M39="",$M39="ERR",$J39="",$K39="",$N39=""),0,IF($N39=0,IF(AND(OR(1=7,1=12),1>=$K39,1<=IF($L39="",12,$L39)),$J39,0),IF(AND(1>=$K39,1<=IF($L39="",12,$L39),MOD(1-$K39,$N39)=0),$J39,0))) -> 0 | P39: =IF(OR($M39="",$M39="ERR",$J39="",$K39="",$N39=""),0,IF($N39=0,IF(AND(OR(2=7,2=12),2>=$K39,2<=IF($L39="",12,$L39)),$J39,0),IF(AND(2>=$K39,2<=IF($L39="",12,$L39),MOD(2-$K39,$N39)=0),$J39,0))) -> 0 | Q39: =IF(OR($M39="",$M39="ERR",$J39="",$K39="",$N39=""),0,IF($N39=0,IF(AND(OR(3=7,3=12),3>=$K39,3<=IF($L39="",12,$L39)),$J39,0),IF(AND(3>=$K39,3<=IF($L39="",12,$L39),MOD(3-$K39,$N39)=0),$J39,0))) -> 0 | R39: =IF(OR($M39="",$M39="ERR",$J39="",$K39="",$N39=""),0,IF($N39=0,IF(AND(OR(4=7,4=12),4>=$K39,4<=IF($L39="",12,$L39)),$J39,0),IF(AND(4>=$K39,4<=IF($L39="",12,$L39),MOD(4-$K39,$N39)=0),$J39,0))) -> 0 | S39: =IF(OR($M39="",$M39="ERR",$J39="",$K39="",$N39=""),0,IF($N39=0,IF(AND(OR(5=7,5=12),5>=$K39,5<=IF($L39="",12,$L39)),$J39,0),IF(AND(5>=$K39,5<=IF($L39="",12,$L39),MOD(5-$K39,$N39)=0),$J39,0))) -> 0 | T39: =IF(OR($M39="",$M39="ERR",$J39="",$K39="",$N39=""),0,IF($N39=0,IF(AND(OR(6=7,6=12),6>=$K39,6<=IF($L39="",12,$L39)),$J39,0),IF(AND(6>=$K39,6<=IF($L39="",12,$L39),MOD(6-$K39,$N39)=0),$J39,0))) -> 0 | U39: =IF(OR($M39="",$M39="ERR",$J39="",$K39="",$N39=""),0,IF($N39=0,IF(AND(OR(7=7,7=12),7>=$K39,7<=IF($L39="",12,$L39)),$J39,0),IF(AND(7>=$K39,7<=IF($L39="",12,$L39),MOD(7-$K39,$N39)=0),$J39,0))) -> 3150 | V39: =IF(OR($M39="",$M39="ERR",$J39="",$K39="",$N39=""),0,IF($N39=0,IF(AND(OR(8=7,8=12),8>=$K39,8<=IF($L39="",12,$L39)),$J39,0),IF(AND(8>=$K39,8<=IF($L39="",12,$L39),MOD(8-$K39,$N39)=0),$J39,0))) -> 0 | W39: =IF(OR($M39="",$M39="ERR",$J39="",$K39="",$N39=""),0,IF($N39=0,IF(AND(OR(9=7,9=12),9>=$K39,9<=IF($L39="",12,$L39)),$J39,0),IF(AND(9>=$K39,9<=IF($L39="",12,$L39),MOD(9-$K39,$N39)=0),$J39,0))) -> 0 | X39: =IF(OR($M39="",$M39="ERR",$J39="",$K39="",$N39=""),0,IF($N39=0,IF(AND(OR(10=7,10=12),10>=$K39,10<=IF($L39="",12,$L39)),$J39,0),IF(AND(10>=$K39,10<=IF($L39="",12,$L39),MOD(10-$K39,$N39)=0),$J39,0))) -> 0 | Y39: =IF(OR($M39="",$M39="ERR",$J39="",$K39="",$N39=""),0,IF($N39=0,IF(AND(OR(11=7,11=12),11>=$K39,11<=IF($L39="",12,$L39)),$J39,0),IF(AND(11>=$K39,11<=IF($L39="",12,$L39),MOD(11-$K39,$N39)=0),$J39,0))) -> 0 | Z39: =IF(OR($M39="",$M39="ERR",$J39="",$K39="",$N39=""),0,IF($N39=0,IF(AND(OR(12=7,12=12),12>=$K39,12<=IF($L39="",12,$L39)),$J39,0),IF(AND(12>=$K39,12<=IF($L39="",12,$L39),MOD(12-$K39,$N39)=0),$J39,0))) -> 3150 | AA39: =SUM(O39:Z39) -> 6300 | AB39: =IF(AND($B39="",$D39="",$J39=""),"",IF($B39="","Falta código",IF(ISNA(MATCH($B39,LST_COD,0)),"Código no registrado en Trabajadores",IF($E39="","Concepto no está en el catálogo",IF($M39="ERR","Retención de otro empleador: Origen = Otro empleador",IF(OR($J39="",$K39=""),"Falta monto o mes",IF(OR($K39<1,$K39>12),"Mes inicio inválido",IF(AND($L39<>"",OR($L39<$K39,$L39>12)),"Mes fin inválido",IF($N39="","Falta frecuencia",IF(AND($G39<>"Otro empleador",SUMPRODUCT(($O39:$Z39<>0)*(((COLUMN($O39:$Z39)-14)<INDEX(Trabajadores!$M$6:$M$105,MATCH($B39,LST_COD,0)))+((COLUMN($O39:$Z39)-14)>INDEX(Trabajadores!$N$6:$N$105,MATCH($B39,LST_COD,0)))))>0),"Aviso: hay meses fuera del periodo laboral","OK")))))))))) -> OK
A40: 35 | B40: EJ-004 | C40: =IF($B40="","",IFERROR(INDEX(Trabajadores!$D$6:$D$105,MATCH($B40,LST_COD,0)),"¿Código?")) -> SALAZAR VEGA, CARLOS (EJEMPLO) | D40: Bono / gratificación extraordinaria | E40: =IF($D40="","",IFERROR(VLOOKUP($D40,CONC_TABLA,2,FALSE()),"")) -> EXT | F40: =IF($D40="","",IFERROR(VLOOKUP($D40,CONC_TABLA,3,FALSE()),"")) -> No | G40: Empresa principal | I40: Pago único | J40: 50000 | K40: 3 | M40: =IF(OR($B40="",$E40=""),"",IF($E40="INA","INA",IF($G40="Otro empleador",IF($E40="RET","RETO",IF($E40="ORD","OTO","OTX")),IF($E40="RET","ERR",$E40)))) -> EXT | N40: =IF($I40="","",IFERROR(VLOOKUP($I40,FREC_TABLA,2,FALSE()),"")) -> 12 | O40: =IF(OR($M40="",$M40="ERR",$J40="",$K40="",$N40=""),0,IF($N40=0,IF(AND(OR(1=7,1=12),1>=$K40,1<=IF($L40="",12,$L40)),$J40,0),IF(AND(1>=$K40,1<=IF($L40="",12,$L40),MOD(1-$K40,$N40)=0),$J40,0))) -> 0 | P40: =IF(OR($M40="",$M40="ERR",$J40="",$K40="",$N40=""),0,IF($N40=0,IF(AND(OR(2=7,2=12),2>=$K40,2<=IF($L40="",12,$L40)),$J40,0),IF(AND(2>=$K40,2<=IF($L40="",12,$L40),MOD(2-$K40,$N40)=0),$J40,0))) -> 0 | Q40: =IF(OR($M40="",$M40="ERR",$J40="",$K40="",$N40=""),0,IF($N40=0,IF(AND(OR(3=7,3=12),3>=$K40,3<=IF($L40="",12,$L40)),$J40,0),IF(AND(3>=$K40,3<=IF($L40="",12,$L40),MOD(3-$K40,$N40)=0),$J40,0))) -> 50000 | R40: =IF(OR($M40="",$M40="ERR",$J40="",$K40="",$N40=""),0,IF($N40=0,IF(AND(OR(4=7,4=12),4>=$K40,4<=IF($L40="",12,$L40)),$J40,0),IF(AND(4>=$K40,4<=IF($L40="",12,$L40),MOD(4-$K40,$N40)=0),$J40,0))) -> 0 | S40: =IF(OR($M40="",$M40="ERR",$J40="",$K40="",$N40=""),0,IF($N40=0,IF(AND(OR(5=7,5=12),5>=$K40,5<=IF($L40="",12,$L40)),$J40,0),IF(AND(5>=$K40,5<=IF($L40="",12,$L40),MOD(5-$K40,$N40)=0),$J40,0))) -> 0 | T40: =IF(OR($M40="",$M40="ERR",$J40="",$K40="",$N40=""),0,IF($N40=0,IF(AND(OR(6=7,6=12),6>=$K40,6<=IF($L40="",12,$L40)),$J40,0),IF(AND(6>=$K40,6<=IF($L40="",12,$L40),MOD(6-$K40,$N40)=0),$J40,0))) -> 0 | U40: =IF(OR($M40="",$M40="ERR",$J40="",$K40="",$N40=""),0,IF($N40=0,IF(AND(OR(7=7,7=12),7>=$K40,7<=IF($L40="",12,$L40)),$J40,0),IF(AND(7>=$K40,7<=IF($L40="",12,$L40),MOD(7-$K40,$N40)=0),$J40,0))) -> 0 | V40: =IF(OR($M40="",$M40="ERR",$J40="",$K40="",$N40=""),0,IF($N40=0,IF(AND(OR(8=7,8=12),8>=$K40,8<=IF($L40="",12,$L40)),$J40,0),IF(AND(8>=$K40,8<=IF($L40="",12,$L40),MOD(8-$K40,$N40)=0),$J40,0))) -> 0 | W40: =IF(OR($M40="",$M40="ERR",$J40="",$K40="",$N40=""),0,IF($N40=0,IF(AND(OR(9=7,9=12),9>=$K40,9<=IF($L40="",12,$L40)),$J40,0),IF(AND(9>=$K40,9<=IF($L40="",12,$L40),MOD(9-$K40,$N40)=0),$J40,0))) -> 0 | X40: =IF(OR($M40="",$M40="ERR",$J40="",$K40="",$N40=""),0,IF($N40=0,IF(AND(OR(10=7,10=12),10>=$K40,10<=IF($L40="",12,$L40)),$J40,0),IF(AND(10>=$K40,10<=IF($L40="",12,$L40),MOD(10-$K40,$N40)=0),$J40,0))) -> 0 | Y40: =IF(OR($M40="",$M40="ERR",$J40="",$K40="",$N40=""),0,IF($N40=0,IF(AND(OR(11=7,11=12),11>=$K40,11<=IF($L40="",12,$L40)),$J40,0),IF(AND(11>=$K40,11<=IF($L40="",12,$L40),MOD(11-$K40,$N40)=0),$J40,0))) -> 0 | Z40: =IF(OR($M40="",$M40="ERR",$J40="",$K40="",$N40=""),0,IF($N40=0,IF(AND(OR(12=7,12=12),12>=$K40,12<=IF($L40="",12,$L40)),$J40,0),IF(AND(12>=$K40,12<=IF($L40="",12,$L40),MOD(12-$K40,$N40)=0),$J40,0))) -> 0 | AA40: =SUM(O40:Z40) -> 50000 | AB40: =IF(AND($B40="",$D40="",$J40=""),"",IF($B40="","Falta código",IF(ISNA(MATCH($B40,LST_COD,0)),"Código no registrado en Trabajadores",IF($E40="","Concepto no está en el catálogo",IF($M40="ERR","Retención de otro empleador: Origen = Otro empleador",IF(OR($J40="",$K40=""),"Falta monto o mes",IF(OR($K40<1,$K40>12),"Mes inicio inválido",IF(AND($L40<>"",OR($L40<$K40,$L40>12)),"Mes fin inválido",IF($N40="","Falta frecuencia",IF(AND($G40<>"Otro empleador",SUMPRODUCT(($O40:$Z40<>0)*(((COLUMN($O40:$Z40)-14)<INDEX(Trabajadores!$M$6:$M$105,MATCH($B40,LST_COD,0)))+((COLUMN($O40:$Z40)-14)>INDEX(Trabajadores!$N$6:$N$105,MATCH($B40,LST_COD,0)))))>0),"Aviso: hay meses fuera del periodo laboral","OK")))))))))) -> OK
A41: 36 | B41: EJ-004 | C41: =IF($B41="","",IFERROR(INDEX(Trabajadores!$D$6:$D$105,MATCH($B41,LST_COD,0)),"¿Código?")) -> SALAZAR VEGA, CARLOS (EJEMPLO) | D41: Bono por cierre de pliego / convenio colectivo | E41: =IF($D41="","",IFERROR(VLOOKUP($D41,CONC_TABLA,2,FALSE()),"")) -> EXT | F41: =IF($D41="","",IFERROR(VLOOKUP($D41,CONC_TABLA,3,FALSE()),"")) -> No | G41: Empresa principal | I41: Pago único | J41: 4000 | K41: 10 | M41: =IF(OR($B41="",$E41=""),"",IF($E41="INA","INA",IF($G41="Otro empleador",IF($E41="RET","RETO",IF($E41="ORD","OTO","OTX")),IF($E41="RET","ERR",$E41)))) -> EXT | N41: =IF($I41="","",IFERROR(VLOOKUP($I41,FREC_TABLA,2,FALSE()),"")) -> 12 | O41: =IF(OR($M41="",$M41="ERR",$J41="",$K41="",$N41=""),0,IF($N41=0,IF(AND(OR(1=7,1=12),1>=$K41,1<=IF($L41="",12,$L41)),$J41,0),IF(AND(1>=$K41,1<=IF($L41="",12,$L41),MOD(1-$K41,$N41)=0),$J41,0))) -> 0 | P41: =IF(OR($M41="",$M41="ERR",$J41="",$K41="",$N41=""),0,IF($N41=0,IF(AND(OR(2=7,2=12),2>=$K41,2<=IF($L41="",12,$L41)),$J41,0),IF(AND(2>=$K41,2<=IF($L41="",12,$L41),MOD(2-$K41,$N41)=0),$J41,0))) -> 0 | Q41: =IF(OR($M41="",$M41="ERR",$J41="",$K41="",$N41=""),0,IF($N41=0,IF(AND(OR(3=7,3=12),3>=$K41,3<=IF($L41="",12,$L41)),$J41,0),IF(AND(3>=$K41,3<=IF($L41="",12,$L41),MOD(3-$K41,$N41)=0),$J41,0))) -> 0 | R41: =IF(OR($M41="",$M41="ERR",$J41="",$K41="",$N41=""),0,IF($N41=0,IF(AND(OR(4=7,4=12),4>=$K41,4<=IF($L41="",12,$L41)),$J41,0),IF(AND(4>=$K41,4<=IF($L41="",12,$L41),MOD(4-$K41,$N41)=0),$J41,0))) -> 0 | S41: =IF(OR($M41="",$M41="ERR",$J41="",$K41="",$N41=""),0,IF($N41=0,IF(AND(OR(5=7,5=12),5>=$K41,5<=IF($L41="",12,$L41)),$J41,0),IF(AND(5>=$K41,5<=IF($L41="",12,$L41),MOD(5-$K41,$N41)=0),$J41,0))) -> 0 | T41: =IF(OR($M41="",$M41="ERR",$J41="",$K41="",$N41=""),0,IF($N41=0,IF(AND(OR(6=7,6=12),6>=$K41,6<=IF($L41="",12,$L41)),$J41,0),IF(AND(6>=$K41,6<=IF($L41="",12,$L41),MOD(6-$K41,$N41)=0),$J41,0))) -> 0 | U41: =IF(OR($M41="",$M41="ERR",$J41="",$K41="",$N41=""),0,IF($N41=0,IF(AND(OR(7=7,7=12),7>=$K41,7<=IF($L41="",12,$L41)),$J41,0),IF(AND(7>=$K41,7<=IF($L41="",12,$L41),MOD(7-$K41,$N41)=0),$J41,0))) -> 0 | V41: =IF(OR($M41="",$M41="ERR",$J41="",$K41="",$N41=""),0,IF($N41=0,IF(AND(OR(8=7,8=12),8>=$K41,8<=IF($L41="",12,$L41)),$J41,0),IF(AND(8>=$K41,8<=IF($L41="",12,$L41),MOD(8-$K41,$N41)=0),$J41,0))) -> 0 | W41: =IF(OR($M41="",$M41="ERR",$J41="",$K41="",$N41=""),0,IF($N41=0,IF(AND(OR(9=7,9=12),9>=$K41,9<=IF($L41="",12,$L41)),$J41,0),IF(AND(9>=$K41,9<=IF($L41="",12,$L41),MOD(9-$K41,$N41)=0),$J41,0))) -> 0 | X41: =IF(OR($M41="",$M41="ERR",$J41="",$K41="",$N41=""),0,IF($N41=0,IF(AND(OR(10=7,10=12),10>=$K41,10<=IF($L41="",12,$L41)),$J41,0),IF(AND(10>=$K41,10<=IF($L41="",12,$L41),MOD(10-$K41,$N41)=0),$J41,0))) -> 4000 | Y41: =IF(OR($M41="",$M41="ERR",$J41="",$K41="",$N41=""),0,IF($N41=0,IF(AND(OR(11=7,11=12),11>=$K41,11<=IF($L41="",12,$L41)),$J41,0),IF(AND(11>=$K41,11<=IF($L41="",12,$L41),MOD(11-$K41,$N41)=0),$J41,0))) -> 0 | Z41: =IF(OR($M41="",$M41="ERR",$J41="",$K41="",$N41=""),0,IF($N41=0,IF(AND(OR(12=7,12=12),12>=$K41,12<=IF($L41="",12,$L41)),$J41,0),IF(AND(12>=$K41,12<=IF($L41="",12,$L41),MOD(12-$K41,$N41)=0),$J41,0))) -> 0 | AA41: =SUM(O41:Z41) -> 4000 | AB41: =IF(AND($B41="",$D41="",$J41=""),"",IF($B41="","Falta código",IF(ISNA(MATCH($B41,LST_COD,0)),"Código no registrado en Trabajadores",IF($E41="","Concepto no está en el catálogo",IF($M41="ERR","Retención de otro empleador: Origen = Otro empleador",IF(OR($J41="",$K41=""),"Falta monto o mes",IF(OR($K41<1,$K41>12),"Mes inicio inválido",IF(AND($L41<>"",OR($L41<$K41,$L41>12)),"Mes fin inválido",IF($N41="","Falta frecuencia",IF(AND($G41<>"Otro empleador",SUMPRODUCT(($O41:$Z41<>0)*(((COLUMN($O41:$Z41)-14)<INDEX(Trabajadores!$M$6:$M$105,MATCH($B41,LST_COD,0)))+((COLUMN($O41:$Z41)-14)>INDEX(Trabajadores!$N$6:$N$105,MATCH($B41,LST_COD,0)))))>0),"Aviso: hay meses fuera del periodo laboral","OK")))))))))) -> OK
A42: 37 | C42: =IF($B42="","",IFERROR(INDEX(Trabajadores!$D$6:$D$105,MATCH($B42,LST_COD,0)),"¿Código?")) | E42: =IF($D42="","",IFERROR(VLOOKUP($D42,CONC_TABLA,2,FALSE()),"")) | F42: =IF($D42="","",IFERROR(VLOOKUP($D42,CONC_TABLA,3,FALSE()),"")) | M42: =IF(OR($B42="",$E42=""),"",IF($E42="INA","INA",IF($G42="Otro empleador",IF($E42="RET","RETO",IF($E42="ORD","OTO","OTX")),IF($E42="RET","ERR",$E42)))) | N42: =IF($I42="","",IFERROR(VLOOKUP($I42,FREC_TABLA,2,FALSE()),"")) | O42: =IF(OR($M42="",$M42="ERR",$J42="",$K42="",$N42=""),0,IF($N42=0,IF(AND(OR(1=7,1=12),1>=$K42,1<=IF($L42="",12,$L42)),$J42,0),IF(AND(1>=$K42,1<=IF($L42="",12,$L42),MOD(1-$K42,$N42)=0),$J42,0))) -> 0 | P42: =IF(OR($M42="",$M42="ERR",$J42="",$K42="",$N42=""),0,IF($N42=0,IF(AND(OR(2=7,2=12),2>=$K42,2<=IF($L42="",12,$L42)),$J42,0),IF(AND(2>=$K42,2<=IF($L42="",12,$L42),MOD(2-$K42,$N42)=0),$J42,0))) -> 0 | Q42: =IF(OR($M42="",$M42="ERR",$J42="",$K42="",$N42=""),0,IF($N42=0,IF(AND(OR(3=7,3=12),3>=$K42,3<=IF($L42="",12,$L42)),$J42,0),IF(AND(3>=$K42,3<=IF($L42="",12,$L42),MOD(3-$K42,$N42)=0),$J42,0))) -> 0 | R42: =IF(OR($M42="",$M42="ERR",$J42="",$K42="",$N42=""),0,IF($N42=0,IF(AND(OR(4=7,4=12),4>=$K42,4<=IF($L42="",12,$L42)),$J42,0),IF(AND(4>=$K42,4<=IF($L42="",12,$L42),MOD(4-$K42,$N42)=0),$J42,0))) -> 0 | S42: =IF(OR($M42="",$M42="ERR",$J42="",$K42="",$N42=""),0,IF($N42=0,IF(AND(OR(5=7,5=12),5>=$K42,5<=IF($L42="",12,$L42)),$J42,0),IF(AND(5>=$K42,5<=IF($L42="",12,$L42),MOD(5-$K42,$N42)=0),$J42,0))) -> 0 | T42: =IF(OR($M42="",$M42="ERR",$J42="",$K42="",$N42=""),0,IF($N42=0,IF(AND(OR(6=7,6=12),6>=$K42,6<=IF($L42="",12,$L42)),$J42,0),IF(AND(6>=$K42,6<=IF($L42="",12,$L42),MOD(6-$K42,$N42)=0),$J42,0))) -> 0 | U42: =IF(OR($M42="",$M42="ERR",$J42="",$K42="",$N42=""),0,IF($N42=0,IF(AND(OR(7=7,7=12),7>=$K42,7<=IF($L42="",12,$L42)),$J42,0),IF(AND(7>=$K42,7<=IF($L42="",12,$L42),MOD(7-$K42,$N42)=0),$J42,0))) -> 0 | V42: =IF(OR($M42="",$M42="ERR",$J42="",$K42="",$N42=""),0,IF($N42=0,IF(AND(OR(8=7,8=12),8>=$K42,8<=IF($L42="",12,$L42)),$J42,0),IF(AND(8>=$K42,8<=IF($L42="",12,$L42),MOD(8-$K42,$N42)=0),$J42,0))) -> 0 | W42: =IF(OR($M42="",$M42="ERR",$J42="",$K42="",$N42=""),0,IF($N42=0,IF(AND(OR(9=7,9=12),9>=$K42,9<=IF($L42="",12,$L42)),$J42,0),IF(AND(9>=$K42,9<=IF($L42="",12,$L42),MOD(9-$K42,$N42)=0),$J42,0))) -> 0 | X42: =IF(OR($M42="",$M42="ERR",$J42="",$K42="",$N42=""),0,IF($N42=0,IF(AND(OR(10=7,10=12),10>=$K42,10<=IF($L42="",12,$L42)),$J42,0),IF(AND(10>=$K42,10<=IF($L42="",12,$L42),MOD(10-$K42,$N42)=0),$J42,0))) -> 0 | Y42: =IF(OR($M42="",$M42="ERR",$J42="",$K42="",$N42=""),0,IF($N42=0,IF(AND(OR(11=7,11=12),11>=$K42,11<=IF($L42="",12,$L42)),$J42,0),IF(AND(11>=$K42,11<=IF($L42="",12,$L42),MOD(11-$K42,$N42)=0),$J42,0))) -> 0 | Z42: =IF(OR($M42="",$M42="ERR",$J42="",$K42="",$N42=""),0,IF($N42=0,IF(AND(OR(12=7,12=12),12>=$K42,12<=IF($L42="",12,$L42)),$J42,0),IF(AND(12>=$K42,12<=IF($L42="",12,$L42),MOD(12-$K42,$N42)=0),$J42,0))) -> 0 | AA42: =SUM(O42:Z42) -> 0 | AB42: =IF(AND($B42="",$D42="",$J42=""),"",IF($B42="","Falta código",IF(ISNA(MATCH($B42,LST_COD,0)),"Código no registrado en Trabajadores",IF($E42="","Concepto no está en el catálogo",IF($M42="ERR","Retención de otro empleador: Origen = Otro empleador",IF(OR($J42="",$K42=""),"Falta monto o mes",IF(OR($K42<1,$K42>12),"Mes inicio inválido",IF(AND($L42<>"",OR($L42<$K42,$L42>12)),"Mes fin inválido",IF($N42="","Falta frecuencia",IF(AND($G42<>"Otro empleador",SUMPRODUCT(($O42:$Z42<>0)*(((COLUMN($O42:$Z42)-14)<INDEX(Trabajadores!$M$6:$M$105,MATCH($B42,LST_COD,0)))+((COLUMN($O42:$Z42)-14)>INDEX(Trabajadores!$N$6:$N$105,MATCH($B42,LST_COD,0)))))>0),"Aviso: hay meses fuera del periodo laboral","OK"))))))))))
A43: 38 | C43: =IF($B43="","",IFERROR(INDEX(Trabajadores!$D$6:$D$105,MATCH($B43,LST_COD,0)),"¿Código?")) | E43: =IF($D43="","",IFERROR(VLOOKUP($D43,CONC_TABLA,2,FALSE()),"")) | F43: =IF($D43="","",IFERROR(VLOOKUP($D43,CONC_TABLA,3,FALSE()),"")) | M43: =IF(OR($B43="",$E43=""),"",IF($E43="INA","INA",IF($G43="Otro empleador",IF($E43="RET","RETO",IF($E43="ORD","OTO","OTX")),IF($E43="RET","ERR",$E43)))) | N43: =IF($I43="","",IFERROR(VLOOKUP($I43,FREC_TABLA,2,FALSE()),"")) | O43: =IF(OR($M43="",$M43="ERR",$J43="",$K43="",$N43=""),0,IF($N43=0,IF(AND(OR(1=7,1=12),1>=$K43,1<=IF($L43="",12,$L43)),$J43,0),IF(AND(1>=$K43,1<=IF($L43="",12,$L43),MOD(1-$K43,$N43)=0),$J43,0))) -> 0 | P43: =IF(OR($M43="",$M43="ERR",$J43="",$K43="",$N43=""),0,IF($N43=0,IF(AND(OR(2=7,2=12),2>=$K43,2<=IF($L43="",12,$L43)),$J43,0),IF(AND(2>=$K43,2<=IF($L43="",12,$L43),MOD(2-$K43,$N43)=0),$J43,0))) -> 0 | Q43: =IF(OR($M43="",$M43="ERR",$J43="",$K43="",$N43=""),0,IF($N43=0,IF(AND(OR(3=7,3=12),3>=$K43,3<=IF($L43="",12,$L43)),$J43,0),IF(AND(3>=$K43,3<=IF($L43="",12,$L43),MOD(3-$K43,$N43)=0),$J43,0))) -> 0 | R43: =IF(OR($M43="",$M43="ERR",$J43="",$K43="",$N43=""),0,IF($N43=0,IF(AND(OR(4=7,4=12),4>=$K43,4<=IF($L43="",12,$L43)),$J43,0),IF(AND(4>=$K43,4<=IF($L43="",12,$L43),MOD(4-$K43,$N43)=0),$J43,0))) -> 0 | S43: =IF(OR($M43="",$M43="ERR",$J43="",$K43="",$N43=""),0,IF($N43=0,IF(AND(OR(5=7,5=12),5>=$K43,5<=IF($L43="",12,$L43)),$J43,0),IF(AND(5>=$K43,5<=IF($L43="",12,$L43),MOD(5-$K43,$N43)=0),$J43,0))) -> 0 | T43: =IF(OR($M43="",$M43="ERR",$J43="",$K43="",$N43=""),0,IF($N43=0,IF(AND(OR(6=7,6=12),6>=$K43,6<=IF($L43="",12,$L43)),$J43,0),IF(AND(6>=$K43,6<=IF($L43="",12,$L43),MOD(6-$K43,$N43)=0),$J43,0))) -> 0 | U43: =IF(OR($M43="",$M43="ERR",$J43="",$K43="",$N43=""),0,IF($N43=0,IF(AND(OR(7=7,7=12),7>=$K43,7<=IF($L43="",12,$L43)),$J43,0),IF(AND(7>=$K43,7<=IF($L43="",12,$L43),MOD(7-$K43,$N43)=0),$J43,0))) -> 0 | V43: =IF(OR($M43="",$M43="ERR",$J43="",$K43="",$N43=""),0,IF($N43=0,IF(AND(OR(8=7,8=12),8>=$K43,8<=IF($L43="",12,$L43)),$J43,0),IF(AND(8>=$K43,8<=IF($L43="",12,$L43),MOD(8-$K43,$N43)=0),$J43,0))) -> 0 | W43: =IF(OR($M43="",$M43="ERR",$J43="",$K43="",$N43=""),0,IF($N43=0,IF(AND(OR(9=7,9=12),9>=$K43,9<=IF($L43="",12,$L43)),$J43,0),IF(AND(9>=$K43,9<=IF($L43="",12,$L43),MOD(9-$K43,$N43)=0),$J43,0))) -> 0 | X43: =IF(OR($M43="",$M43="ERR",$J43="",$K43="",$N43=""),0,IF($N43=0,IF(AND(OR(10=7,10=12),10>=$K43,10<=IF($L43="",12,$L43)),$J43,0),IF(AND(10>=$K43,10<=IF($L43="",12,$L43),MOD(10-$K43,$N43)=0),$J43,0))) -> 0 | Y43: =IF(OR($M43="",$M43="ERR",$J43="",$K43="",$N43=""),0,IF($N43=0,IF(AND(OR(11=7,11=12),11>=$K43,11<=IF($L43="",12,$L43)),$J43,0),IF(AND(11>=$K43,11<=IF($L43="",12,$L43),MOD(11-$K43,$N43)=0),$J43,0))) -> 0 | Z43: =IF(OR($M43="",$M43="ERR",$J43="",$K43="",$N43=""),0,IF($N43=0,IF(AND(OR(12=7,12=12),12>=$K43,12<=IF($L43="",12,$L43)),$J43,0),IF(AND(12>=$K43,12<=IF($L43="",12,$L43),MOD(12-$K43,$N43)=0),$J43,0))) -> 0 | AA43: =SUM(O43:Z43) -> 0 | AB43: =IF(AND($B43="",$D43="",$J43=""),"",IF($B43="","Falta código",IF(ISNA(MATCH($B43,LST_COD,0)),"Código no registrado en Trabajadores",IF($E43="","Concepto no está en el catálogo",IF($M43="ERR","Retención de otro empleador: Origen = Otro empleador",IF(OR($J43="",$K43=""),"Falta monto o mes",IF(OR($K43<1,$K43>12),"Mes inicio inválido",IF(AND($L43<>"",OR($L43<$K43,$L43>12)),"Mes fin inválido",IF($N43="","Falta frecuencia",IF(AND($G43<>"Otro empleador",SUMPRODUCT(($O43:$Z43<>0)*(((COLUMN($O43:$Z43)-14)<INDEX(Trabajadores!$M$6:$M$105,MATCH($B43,LST_COD,0)))+((COLUMN($O43:$Z43)-14)>INDEX(Trabajadores!$N$6:$N$105,MATCH($B43,LST_COD,0)))))>0),"Aviso: hay meses fuera del periodo laboral","OK"))))))))))
A44: 39 | C44: =IF($B44="","",IFERROR(INDEX(Trabajadores!$D$6:$D$105,MATCH($B44,LST_COD,0)),"¿Código?")) | E44: =IF($D44="","",IFERROR(VLOOKUP($D44,CONC_TABLA,2,FALSE()),"")) | F44: =IF($D44="","",IFERROR(VLOOKUP($D44,CONC_TABLA,3,FALSE()),"")) | M44: =IF(OR($B44="",$E44=""),"",IF($E44="INA","INA",IF($G44="Otro empleador",IF($E44="RET","RETO",IF($E44="ORD","OTO","OTX")),IF($E44="RET","ERR",$E44)))) | N44: =IF($I44="","",IFERROR(VLOOKUP($I44,FREC_TABLA,2,FALSE()),"")) | O44: =IF(OR($M44="",$M44="ERR",$J44="",$K44="",$N44=""),0,IF($N44=0,IF(AND(OR(1=7,1=12),1>=$K44,1<=IF($L44="",12,$L44)),$J44,0),IF(AND(1>=$K44,1<=IF($L44="",12,$L44),MOD(1-$K44,$N44)=0),$J44,0))) -> 0 | P44: =IF(OR($M44="",$M44="ERR",$J44="",$K44="",$N44=""),0,IF($N44=0,IF(AND(OR(2=7,2=12),2>=$K44,2<=IF($L44="",12,$L44)),$J44,0),IF(AND(2>=$K44,2<=IF($L44="",12,$L44),MOD(2-$K44,$N44)=0),$J44,0))) -> 0 | Q44: =IF(OR($M44="",$M44="ERR",$J44="",$K44="",$N44=""),0,IF($N44=0,IF(AND(OR(3=7,3=12),3>=$K44,3<=IF($L44="",12,$L44)),$J44,0),IF(AND(3>=$K44,3<=IF($L44="",12,$L44),MOD(3-$K44,$N44)=0),$J44,0))) -> 0 | R44: =IF(OR($M44="",$M44="ERR",$J44="",$K44="",$N44=""),0,IF($N44=0,IF(AND(OR(4=7,4=12),4>=$K44,4<=IF($L44="",12,$L44)),$J44,0),IF(AND(4>=$K44,4<=IF($L44="",12,$L44),MOD(4-$K44,$N44)=0),$J44,0))) -> 0 | S44: =IF(OR($M44="",$M44="ERR",$J44="",$K44="",$N44=""),0,IF($N44=0,IF(AND(OR(5=7,5=12),5>=$K44,5<=IF($L44="",12,$L44)),$J44,0),IF(AND(5>=$K44,5<=IF($L44="",12,$L44),MOD(5-$K44,$N44)=0),$J44,0))) -> 0 | T44: =IF(OR($M44="",$M44="ERR",$J44="",$K44="",$N44=""),0,IF($N44=0,IF(AND(OR(6=7,6=12),6>=$K44,6<=IF($L44="",12,$L44)),$J44,0),IF(AND(6>=$K44,6<=IF($L44="",12,$L44),MOD(6-$K44,$N44)=0),$J44,0))) -> 0 | U44: =IF(OR($M44="",$M44="ERR",$J44="",$K44="",$N44=""),0,IF($N44=0,IF(AND(OR(7=7,7=12),7>=$K44,7<=IF($L44="",12,$L44)),$J44,0),IF(AND(7>=$K44,7<=IF($L44="",12,$L44),MOD(7-$K44,$N44)=0),$J44,0))) -> 0 | V44: =IF(OR($M44="",$M44="ERR",$J44="",$K44="",$N44=""),0,IF($N44=0,IF(AND(OR(8=7,8=12),8>=$K44,8<=IF($L44="",12,$L44)),$J44,0),IF(AND(8>=$K44,8<=IF($L44="",12,$L44),MOD(8-$K44,$N44)=0),$J44,0))) -> 0 | W44: =IF(OR($M44="",$M44="ERR",$J44="",$K44="",$N44=""),0,IF($N44=0,IF(AND(OR(9=7,9=12),9>=$K44,9<=IF($L44="",12,$L44)),$J44,0),IF(AND(9>=$K44,9<=IF($L44="",12,$L44),MOD(9-$K44,$N44)=0),$J44,0))) -> 0 | X44: =IF(OR($M44="",$M44="ERR",$J44="",$K44="",$N44=""),0,IF($N44=0,IF(AND(OR(10=7,10=12),10>=$K44,10<=IF($L44="",12,$L44)),$J44,0),IF(AND(10>=$K44,10<=IF($L44="",12,$L44),MOD(10-$K44,$N44)=0),$J44,0))) -> 0 | Y44: =IF(OR($M44="",$M44="ERR",$J44="",$K44="",$N44=""),0,IF($N44=0,IF(AND(OR(11=7,11=12),11>=$K44,11<=IF($L44="",12,$L44)),$J44,0),IF(AND(11>=$K44,11<=IF($L44="",12,$L44),MOD(11-$K44,$N44)=0),$J44,0))) -> 0 | Z44: =IF(OR($M44="",$M44="ERR",$J44="",$K44="",$N44=""),0,IF($N44=0,IF(AND(OR(12=7,12=12),12>=$K44,12<=IF($L44="",12,$L44)),$J44,0),IF(AND(12>=$K44,12<=IF($L44="",12,$L44),MOD(12-$K44,$N44)=0),$J44,0))) -> 0 | AA44: =SUM(O44:Z44) -> 0 | AB44: =IF(AND($B44="",$D44="",$J44=""),"",IF($B44="","Falta código",IF(ISNA(MATCH($B44,LST_COD,0)),"Código no registrado en Trabajadores",IF($E44="","Concepto no está en el catálogo",IF($M44="ERR","Retención de otro empleador: Origen = Otro empleador",IF(OR($J44="",$K44=""),"Falta monto o mes",IF(OR($K44<1,$K44>12),"Mes inicio inválido",IF(AND($L44<>"",OR($L44<$K44,$L44>12)),"Mes fin inválido",IF($N44="","Falta frecuencia",IF(AND($G44<>"Otro empleador",SUMPRODUCT(($O44:$Z44<>0)*(((COLUMN($O44:$Z44)-14)<INDEX(Trabajadores!$M$6:$M$105,MATCH($B44,LST_COD,0)))+((COLUMN($O44:$Z44)-14)>INDEX(Trabajadores!$N$6:$N$105,MATCH($B44,LST_COD,0)))))>0),"Aviso: hay meses fuera del periodo laboral","OK"))))))))))
A45: 40 | C45: =IF($B45="","",IFERROR(INDEX(Trabajadores!$D$6:$D$105,MATCH($B45,LST_COD,0)),"¿Código?")) | E45: =IF($D45="","",IFERROR(VLOOKUP($D45,CONC_TABLA,2,FALSE()),"")) | F45: =IF($D45="","",IFERROR(VLOOKUP($D45,CONC_TABLA,3,FALSE()),"")) | M45: =IF(OR($B45="",$E45=""),"",IF($E45="INA","INA",IF($G45="Otro empleador",IF($E45="RET","RETO",IF($E45="ORD","OTO","OTX")),IF($E45="RET","ERR",$E45)))) | N45: =IF($I45="","",IFERROR(VLOOKUP($I45,FREC_TABLA,2,FALSE()),"")) | O45: =IF(OR($M45="",$M45="ERR",$J45="",$K45="",$N45=""),0,IF($N45=0,IF(AND(OR(1=7,1=12),1>=$K45,1<=IF($L45="",12,$L45)),$J45,0),IF(AND(1>=$K45,1<=IF($L45="",12,$L45),MOD(1-$K45,$N45)=0),$J45,0))) -> 0 | P45: =IF(OR($M45="",$M45="ERR",$J45="",$K45="",$N45=""),0,IF($N45=0,IF(AND(OR(2=7,2=12),2>=$K45,2<=IF($L45="",12,$L45)),$J45,0),IF(AND(2>=$K45,2<=IF($L45="",12,$L45),MOD(2-$K45,$N45)=0),$J45,0))) -> 0 | Q45: =IF(OR($M45="",$M45="ERR",$J45="",$K45="",$N45=""),0,IF($N45=0,IF(AND(OR(3=7,3=12),3>=$K45,3<=IF($L45="",12,$L45)),$J45,0),IF(AND(3>=$K45,3<=IF($L45="",12,$L45),MOD(3-$K45,$N45)=0),$J45,0))) -> 0 | R45: =IF(OR($M45="",$M45="ERR",$J45="",$K45="",$N45=""),0,IF($N45=0,IF(AND(OR(4=7,4=12),4>=$K45,4<=IF($L45="",12,$L45)),$J45,0),IF(AND(4>=$K45,4<=IF($L45="",12,$L45),MOD(4-$K45,$N45)=0),$J45,0))) -> 0 | S45: =IF(OR($M45="",$M45="ERR",$J45="",$K45="",$N45=""),0,IF($N45=0,IF(AND(OR(5=7,5=12),5>=$K45,5<=IF($L45="",12,$L45)),$J45,0),IF(AND(5>=$K45,5<=IF($L45="",12,$L45),MOD(5-$K45,$N45)=0),$J45,0))) -> 0 | T45: =IF(OR($M45="",$M45="ERR",$J45="",$K45="",$N45=""),0,IF($N45=0,IF(AND(OR(6=7,6=12),6>=$K45,6<=IF($L45="",12,$L45)),$J45,0),IF(AND(6>=$K45,6<=IF($L45="",12,$L45),MOD(6-$K45,$N45)=0),$J45,0))) -> 0 | U45: =IF(OR($M45="",$M45="ERR",$J45="",$K45="",$N45=""),0,IF($N45=0,IF(AND(OR(7=7,7=12),7>=$K45,7<=IF($L45="",12,$L45)),$J45,0),IF(AND(7>=$K45,7<=IF($L45="",12,$L45),MOD(7-$K45,$N45)=0),$J45,0))) -> 0 | V45: =IF(OR($M45="",$M45="ERR",$J45="",$K45="",$N45=""),0,IF($N45=0,IF(AND(OR(8=7,8=12),8>=$K45,8<=IF($L45="",12,$L45)),$J45,0),IF(AND(8>=$K45,8<=IF($L45="",12,$L45),MOD(8-$K45,$N45)=0),$J45,0))) -> 0 | W45: =IF(OR($M45="",$M45="ERR",$J45="",$K45="",$N45=""),0,IF($N45=0,IF(AND(OR(9=7,9=12),9>=$K45,9<=IF($L45="",12,$L45)),$J45,0),IF(AND(9>=$K45,9<=IF($L45="",12,$L45),MOD(9-$K45,$N45)=0),$J45,0))) -> 0 | X45: =IF(OR($M45="",$M45="ERR",$J45="",$K45="",$N45=""),0,IF($N45=0,IF(AND(OR(10=7,10=12),10>=$K45,10<=IF($L45="",12,$L45)),$J45,0),IF(AND(10>=$K45,10<=IF($L45="",12,$L45),MOD(10-$K45,$N45)=0),$J45,0))) -> 0 | Y45: =IF(OR($M45="",$M45="ERR",$J45="",$K45="",$N45=""),0,IF($N45=0,IF(AND(OR(11=7,11=12),11>=$K45,11<=IF($L45="",12,$L45)),$J45,0),IF(AND(11>=$K45,11<=IF($L45="",12,$L45),MOD(11-$K45,$N45)=0),$J45,0))) -> 0 | Z45: =IF(OR($M45="",$M45="ERR",$J45="",$K45="",$N45=""),0,IF($N45=0,IF(AND(OR(12=7,12=12),12>=$K45,12<=IF($L45="",12,$L45)),$J45,0),IF(AND(12>=$K45,12<=IF($L45="",12,$L45),MOD(12-$K45,$N45)=0),$J45,0))) -> 0 | AA45: =SUM(O45:Z45) -> 0 | AB45: =IF(AND($B45="",$D45="",$J45=""),"",IF($B45="","Falta código",IF(ISNA(MATCH($B45,LST_COD,0)),"Código no registrado en Trabajadores",IF($E45="","Concepto no está en el catálogo",IF($M45="ERR","Retención de otro empleador: Origen = Otro empleador",IF(OR($J45="",$K45=""),"Falta monto o mes",IF(OR($K45<1,$K45>12),"Mes inicio inválido",IF(AND($L45<>"",OR($L45<$K45,$L45>12)),"Mes fin inválido",IF($N45="","Falta frecuencia",IF(AND($G45<>"Otro empleador",SUMPRODUCT(($O45:$Z45<>0)*(((COLUMN($O45:$Z45)-14)<INDEX(Trabajadores!$M$6:$M$105,MATCH($B45,LST_COD,0)))+((COLUMN($O45:$Z45)-14)>INDEX(Trabajadores!$N$6:$N$105,MATCH($B45,LST_COD,0)))))>0),"Aviso: hay meses fuera del periodo laboral","OK"))))))))))
A46: 41 | C46: =IF($B46="","",IFERROR(INDEX(Trabajadores!$D$6:$D$105,MATCH($B46,LST_COD,0)),"¿Código?")) | E46: =IF($D46="","",IFERROR(VLOOKUP($D46,CONC_TABLA,2,FALSE()),"")) | F46: =IF($D46="","",IFERROR(VLOOKUP($D46,CONC_TABLA,3,FALSE()),"")) | M46: =IF(OR($B46="",$E46=""),"",IF($E46="INA","INA",IF($G46="Otro empleador",IF($E46="RET","RETO",IF($E46="ORD","OTO","OTX")),IF($E46="RET","ERR",$E46)))) | N46: =IF($I46="","",IFERROR(VLOOKUP($I46,FREC_TABLA,2,FALSE()),"")) | O46: =IF(OR($M46="",$M46="ERR",$J46="",$K46="",$N46=""),0,IF($N46=0,IF(AND(OR(1=7,1=12),1>=$K46,1<=IF($L46="",12,$L46)),$J46,0),IF(AND(1>=$K46,1<=IF($L46="",12,$L46),MOD(1-$K46,$N46)=0),$J46,0))) -> 0 | P46: =IF(OR($M46="",$M46="ERR",$J46="",$K46="",$N46=""),0,IF($N46=0,IF(AND(OR(2=7,2=12),2>=$K46,2<=IF($L46="",12,$L46)),$J46,0),IF(AND(2>=$K46,2<=IF($L46="",12,$L46),MOD(2-$K46,$N46)=0),$J46,0))) -> 0 | Q46: =IF(OR($M46="",$M46="ERR",$J46="",$K46="",$N46=""),0,IF($N46=0,IF(AND(OR(3=7,3=12),3>=$K46,3<=IF($L46="",12,$L46)),$J46,0),IF(AND(3>=$K46,3<=IF($L46="",12,$L46),MOD(3-$K46,$N46)=0),$J46,0))) -> 0 | R46: =IF(OR($M46="",$M46="ERR",$J46="",$K46="",$N46=""),0,IF($N46=0,IF(AND(OR(4=7,4=12),4>=$K46,4<=IF($L46="",12,$L46)),$J46,0),IF(AND(4>=$K46,4<=IF($L46="",12,$L46),MOD(4-$K46,$N46)=0),$J46,0))) -> 0 | S46: =IF(OR($M46="",$M46="ERR",$J46="",$K46="",$N46=""),0,IF($N46=0,IF(AND(OR(5=7,5=12),5>=$K46,5<=IF($L46="",12,$L46)),$J46,0),IF(AND(5>=$K46,5<=IF($L46="",12,$L46),MOD(5-$K46,$N46)=0),$J46,0))) -> 0 | T46: =IF(OR($M46="",$M46="ERR",$J46="",$K46="",$N46=""),0,IF($N46=0,IF(AND(OR(6=7,6=12),6>=$K46,6<=IF($L46="",12,$L46)),$J46,0),IF(AND(6>=$K46,6<=IF($L46="",12,$L46),MOD(6-$K46,$N46)=0),$J46,0))) -> 0 | U46: =IF(OR($M46="",$M46="ERR",$J46="",$K46="",$N46=""),0,IF($N46=0,IF(AND(OR(7=7,7=12),7>=$K46,7<=IF($L46="",12,$L46)),$J46,0),IF(AND(7>=$K46,7<=IF($L46="",12,$L46),MOD(7-$K46,$N46)=0),$J46,0))) -> 0 | V46: =IF(OR($M46="",$M46="ERR",$J46="",$K46="",$N46=""),0,IF($N46=0,IF(AND(OR(8=7,8=12),8>=$K46,8<=IF($L46="",12,$L46)),$J46,0),IF(AND(8>=$K46,8<=IF($L46="",12,$L46),MOD(8-$K46,$N46)=0),$J46,0))) -> 0 | W46: =IF(OR($M46="",$M46="ERR",$J46="",$K46="",$N46=""),0,IF($N46=0,IF(AND(OR(9=7,9=12),9>=$K46,9<=IF($L46="",12,$L46)),$J46,0),IF(AND(9>=$K46,9<=IF($L46="",12,$L46),MOD(9-$K46,$N46)=0),$J46,0))) -> 0 | X46: =IF(OR($M46="",$M46="ERR",$J46="",$K46="",$N46=""),0,IF($N46=0,IF(AND(OR(10=7,10=12),10>=$K46,10<=IF($L46="",12,$L46)),$J46,0),IF(AND(10>=$K46,10<=IF($L46="",12,$L46),MOD(10-$K46,$N46)=0),$J46,0))) -> 0 | Y46: =IF(OR($M46="",$M46="ERR",$J46="",$K46="",$N46=""),0,IF($N46=0,IF(AND(OR(11=7,11=12),11>=$K46,11<=IF($L46="",12,$L46)),$J46,0),IF(AND(11>=$K46,11<=IF($L46="",12,$L46),MOD(11-$K46,$N46)=0),$J46,0))) -> 0 | Z46: =IF(OR($M46="",$M46="ERR",$J46="",$K46="",$N46=""),0,IF($N46=0,IF(AND(OR(12=7,12=12),12>=$K46,12<=IF($L46="",12,$L46)),$J46,0),IF(AND(12>=$K46,12<=IF($L46="",12,$L46),MOD(12-$K46,$N46)=0),$J46,0))) -> 0 | AA46: =SUM(O46:Z46) -> 0 | AB46: =IF(AND($B46="",$D46="",$J46=""),"",IF($B46="","Falta código",IF(ISNA(MATCH($B46,LST_COD,0)),"Código no registrado en Trabajadores",IF($E46="","Concepto no está en el catálogo",IF($M46="ERR","Retención de otro empleador: Origen = Otro empleador",IF(OR($J46="",$K46=""),"Falta monto o mes",IF(OR($K46<1,$K46>12),"Mes inicio inválido",IF(AND($L46<>"",OR($L46<$K46,$L46>12)),"Mes fin inválido",IF($N46="","Falta frecuencia",IF(AND($G46<>"Otro empleador",SUMPRODUCT(($O46:$Z46<>0)*(((COLUMN($O46:$Z46)-14)<INDEX(Trabajadores!$M$6:$M$105,MATCH($B46,LST_COD,0)))+((COLUMN($O46:$Z46)-14)>INDEX(Trabajadores!$N$6:$N$105,MATCH($B46,LST_COD,0)))))>0),"Aviso: hay meses fuera del periodo laboral","OK"))))))))))
A47: 42 | C47: =IF($B47="","",IFERROR(INDEX(Trabajadores!$D$6:$D$105,MATCH($B47,LST_COD,0)),"¿Código?")) | E47: =IF($D47="","",IFERROR(VLOOKUP($D47,CONC_TABLA,2,FALSE()),"")) | F47: =IF($D47="","",IFERROR(VLOOKUP($D47,CONC_TABLA,3,FALSE()),"")) | M47: =IF(OR($B47="",$E47=""),"",IF($E47="INA","INA",IF($G47="Otro empleador",IF($E47="RET","RETO",IF($E47="ORD","OTO","OTX")),IF($E47="RET","ERR",$E47)))) | N47: =IF($I47="","",IFERROR(VLOOKUP($I47,FREC_TABLA,2,FALSE()),"")) | O47: =IF(OR($M47="",$M47="ERR",$J47="",$K47="",$N47=""),0,IF($N47=0,IF(AND(OR(1=7,1=12),1>=$K47,1<=IF($L47="",12,$L47)),$J47,0),IF(AND(1>=$K47,1<=IF($L47="",12,$L47),MOD(1-$K47,$N47)=0),$J47,0))) -> 0 | P47: =IF(OR($M47="",$M47="ERR",$J47="",$K47="",$N47=""),0,IF($N47=0,IF(AND(OR(2=7,2=12),2>=$K47,2<=IF($L47="",12,$L47)),$J47,0),IF(AND(2>=$K47,2<=IF($L47="",12,$L47),MOD(2-$K47,$N47)=0),$J47,0))) -> 0 | Q47: =IF(OR($M47="",$M47="ERR",$J47="",$K47="",$N47=""),0,IF($N47=0,IF(AND(OR(3=7,3=12),3>=$K47,3<=IF($L47="",12,$L47)),$J47,0),IF(AND(3>=$K47,3<=IF($L47="",12,$L47),MOD(3-$K47,$N47)=0),$J47,0))) -> 0 | R47: =IF(OR($M47="",$M47="ERR",$J47="",$K47="",$N47=""),0,IF($N47=0,IF(AND(OR(4=7,4=12),4>=$K47,4<=IF($L47="",12,$L47)),$J47,0),IF(AND(4>=$K47,4<=IF($L47="",12,$L47),MOD(4-$K47,$N47)=0),$J47,0))) -> 0 | S47: =IF(OR($M47="",$M47="ERR",$J47="",$K47="",$N47=""),0,IF($N47=0,IF(AND(OR(5=7,5=12),5>=$K47,5<=IF($L47="",12,$L47)),$J47,0),IF(AND(5>=$K47,5<=IF($L47="",12,$L47),MOD(5-$K47,$N47)=0),$J47,0))) -> 0 | T47: =IF(OR($M47="",$M47="ERR",$J47="",$K47="",$N47=""),0,IF($N47=0,IF(AND(OR(6=7,6=12),6>=$K47,6<=IF($L47="",12,$L47)),$J47,0),IF(AND(6>=$K47,6<=IF($L47="",12,$L47),MOD(6-$K47,$N47)=0),$J47,0))) -> 0 | U47: =IF(OR($M47="",$M47="ERR",$J47="",$K47="",$N47=""),0,IF($N47=0,IF(AND(OR(7=7,7=12),7>=$K47,7<=IF($L47="",12,$L47)),$J47,0),IF(AND(7>=$K47,7<=IF($L47="",12,$L47),MOD(7-$K47,$N47)=0),$J47,0))) -> 0 | V47: =IF(OR($M47="",$M47="ERR",$J47="",$K47="",$N47=""),0,IF($N47=0,IF(AND(OR(8=7,8=12),8>=$K47,8<=IF($L47="",12,$L47)),$J47,0),IF(AND(8>=$K47,8<=IF($L47="",12,$L47),MOD(8-$K47,$N47)=0),$J47,0))) -> 0 | W47: =IF(OR($M47="",$M47="ERR",$J47="",$K47="",$N47=""),0,IF($N47=0,IF(AND(OR(9=7,9=12),9>=$K47,9<=IF($L47="",12,$L47)),$J47,0),IF(AND(9>=$K47,9<=IF($L47="",12,$L47),MOD(9-$K47,$N47)=0),$J47,0))) -> 0 | X47: =IF(OR($M47="",$M47="ERR",$J47="",$K47="",$N47=""),0,IF($N47=0,IF(AND(OR(10=7,10=12),10>=$K47,10<=IF($L47="",12,$L47)),$J47,0),IF(AND(10>=$K47,10<=IF($L47="",12,$L47),MOD(10-$K47,$N47)=0),$J47,0))) -> 0 | Y47: =IF(OR($M47="",$M47="ERR",$J47="",$K47="",$N47=""),0,IF($N47=0,IF(AND(OR(11=7,11=12),11>=$K47,11<=IF($L47="",12,$L47)),$J47,0),IF(AND(11>=$K47,11<=IF($L47="",12,$L47),MOD(11-$K47,$N47)=0),$J47,0))) -> 0 | Z47: =IF(OR($M47="",$M47="ERR",$J47="",$K47="",$N47=""),0,IF($N47=0,IF(AND(OR(12=7,12=12),12>=$K47,12<=IF($L47="",12,$L47)),$J47,0),IF(AND(12>=$K47,12<=IF($L47="",12,$L47),MOD(12-$K47,$N47)=0),$J47,0))) -> 0 | AA47: =SUM(O47:Z47) -> 0 | AB47: =IF(AND($B47="",$D47="",$J47=""),"",IF($B47="","Falta código",IF(ISNA(MATCH($B47,LST_COD,0)),"Código no registrado en Trabajadores",IF($E47="","Concepto no está en el catálogo",IF($M47="ERR","Retención de otro empleador: Origen = Otro empleador",IF(OR($J47="",$K47=""),"Falta monto o mes",IF(OR($K47<1,$K47>12),"Mes inicio inválido",IF(AND($L47<>"",OR($L47<$K47,$L47>12)),"Mes fin inválido",IF($N47="","Falta frecuencia",IF(AND($G47<>"Otro empleador",SUMPRODUCT(($O47:$Z47<>0)*(((COLUMN($O47:$Z47)-14)<INDEX(Trabajadores!$M$6:$M$105,MATCH($B47,LST_COD,0)))+((COLUMN($O47:$Z47)-14)>INDEX(Trabajadores!$N$6:$N$105,MATCH($B47,LST_COD,0)))))>0),"Aviso: hay meses fuera del periodo laboral","OK"))))))))))
A48: 43 | C48: =IF($B48="","",IFERROR(INDEX(Trabajadores!$D$6:$D$105,MATCH($B48,LST_COD,0)),"¿Código?")) | E48: =IF($D48="","",IFERROR(VLOOKUP($D48,CONC_TABLA,2,FALSE()),"")) | F48: =IF($D48="","",IFERROR(VLOOKUP($D48,CONC_TABLA,3,FALSE()),"")) | M48: =IF(OR($B48="",$E48=""),"",IF($E48="INA","INA",IF($G48="Otro empleador",IF($E48="RET","RETO",IF($E48="ORD","OTO","OTX")),IF($E48="RET","ERR",$E48)))) | N48: =IF($I48="","",IFERROR(VLOOKUP($I48,FREC_TABLA,2,FALSE()),"")) | O48: =IF(OR($M48="",$M48="ERR",$J48="",$K48="",$N48=""),0,IF($N48=0,IF(AND(OR(1=7,1=12),1>=$K48,1<=IF($L48="",12,$L48)),$J48,0),IF(AND(1>=$K48,1<=IF($L48="",12,$L48),MOD(1-$K48,$N48)=0),$J48,0))) -> 0 | P48: =IF(OR($M48="",$M48="ERR",$J48="",$K48="",$N48=""),0,IF($N48=0,IF(AND(OR(2=7,2=12),2>=$K48,2<=IF($L48="",12,$L48)),$J48,0),IF(AND(2>=$K48,2<=IF($L48="",12,$L48),MOD(2-$K48,$N48)=0),$J48,0))) -> 0 | Q48: =IF(OR($M48="",$M48="ERR",$J48="",$K48="",$N48=""),0,IF($N48=0,IF(AND(OR(3=7,3=12),3>=$K48,3<=IF($L48="",12,$L48)),$J48,0),IF(AND(3>=$K48,3<=IF($L48="",12,$L48),MOD(3-$K48,$N48)=0),$J48,0))) -> 0 | R48: =IF(OR($M48="",$M48="ERR",$J48="",$K48="",$N48=""),0,IF($N48=0,IF(AND(OR(4=7,4=12),4>=$K48,4<=IF($L48="",12,$L48)),$J48,0),IF(AND(4>=$K48,4<=IF($L48="",12,$L48),MOD(4-$K48,$N48)=0),$J48,0))) -> 0 | S48: =IF(OR($M48="",$M48="ERR",$J48="",$K48="",$N48=""),0,IF($N48=0,IF(AND(OR(5=7,5=12),5>=$K48,5<=IF($L48="",12,$L48)),$J48,0),IF(AND(5>=$K48,5<=IF($L48="",12,$L48),MOD(5-$K48,$N48)=0),$J48,0))) -> 0 | T48: =IF(OR($M48="",$M48="ERR",$J48="",$K48="",$N48=""),0,IF($N48=0,IF(AND(OR(6=7,6=12),6>=$K48,6<=IF($L48="",12,$L48)),$J48,0),IF(AND(6>=$K48,6<=IF($L48="",12,$L48),MOD(6-$K48,$N48)=0),$J48,0))) -> 0 | U48: =IF(OR($M48="",$M48="ERR",$J48="",$K48="",$N48=""),0,IF($N48=0,IF(AND(OR(7=7,7=12),7>=$K48,7<=IF($L48="",12,$L48)),$J48,0),IF(AND(7>=$K48,7<=IF($L48="",12,$L48),MOD(7-$K48,$N48)=0),$J48,0))) -> 0 | V48: =IF(OR($M48="",$M48="ERR",$J48="",$K48="",$N48=""),0,IF($N48=0,IF(AND(OR(8=7,8=12),8>=$K48,8<=IF($L48="",12,$L48)),$J48,0),IF(AND(8>=$K48,8<=IF($L48="",12,$L48),MOD(8-$K48,$N48)=0),$J48,0))) -> 0 | W48: =IF(OR($M48="",$M48="ERR",$J48="",$K48="",$N48=""),0,IF($N48=0,IF(AND(OR(9=7,9=12),9>=$K48,9<=IF($L48="",12,$L48)),$J48,0),IF(AND(9>=$K48,9<=IF($L48="",12,$L48),MOD(9-$K48,$N48)=0),$J48,0))) -> 0 | X48: =IF(OR($M48="",$M48="ERR",$J48="",$K48="",$N48=""),0,IF($N48=0,IF(AND(OR(10=7,10=12),10>=$K48,10<=IF($L48="",12,$L48)),$J48,0),IF(AND(10>=$K48,10<=IF($L48="",12,$L48),MOD(10-$K48,$N48)=0),$J48,0))) -> 0 | Y48: =IF(OR($M48="",$M48="ERR",$J48="",$K48="",$N48=""),0,IF($N48=0,IF(AND(OR(11=7,11=12),11>=$K48,11<=IF($L48="",12,$L48)),$J48,0),IF(AND(11>=$K48,11<=IF($L48="",12,$L48),MOD(11-$K48,$N48)=0),$J48,0))) -> 0 | Z48: =IF(OR($M48="",$M48="ERR",$J48="",$K48="",$N48=""),0,IF($N48=0,IF(AND(OR(12=7,12=12),12>=$K48,12<=IF($L48="",12,$L48)),$J48,0),IF(AND(12>=$K48,12<=IF($L48="",12,$L48),MOD(12-$K48,$N48)=0),$J48,0))) -> 0 | AA48: =SUM(O48:Z48) -> 0 | AB48: =IF(AND($B48="",$D48="",$J48=""),"",IF($B48="","Falta código",IF(ISNA(MATCH($B48,LST_COD,0)),"Código no registrado en Trabajadores",IF($E48="","Concepto no está en el catálogo",IF($M48="ERR","Retención de otro empleador: Origen = Otro empleador",IF(OR($J48="",$K48=""),"Falta monto o mes",IF(OR($K48<1,$K48>12),"Mes inicio inválido",IF(AND($L48<>"",OR($L48<$K48,$L48>12)),"Mes fin inválido",IF($N48="","Falta frecuencia",IF(AND($G48<>"Otro empleador",SUMPRODUCT(($O48:$Z48<>0)*(((COLUMN($O48:$Z48)-14)<INDEX(Trabajadores!$M$6:$M$105,MATCH($B48,LST_COD,0)))+((COLUMN($O48:$Z48)-14)>INDEX(Trabajadores!$N$6:$N$105,MATCH($B48,LST_COD,0)))))>0),"Aviso: hay meses fuera del periodo laboral","OK"))))))))))
